Workbook
Name _c検索基準日: #REF!
Name _集計月: #REF!
Name スライサー_加工内容: #N/A
Name スライサー_加工内容1: #N/A
Name スライサー_年月__月: #N/A
Name スライサー_年月__月1: #N/A
Name スライサー_年月__月2: #N/A
Name スライサー_年月__月3: #N/A
Name スライサー_年月__月31: #N/A
Name スライサー_年月__年: #N/A
Name スライサー_年月__年1: #N/A
Name スライサー_年月__年2: #N/A
Name スライサー_年月__年3: #N/A
Name スライサー_年月__年31: #N/A
Name 再入力対象依頼No: #REF!
Name 製品参照ｺｰﾄﾞ: #REF!
Name 品種マスタリスト: INDEX(#REF!,0)
Name 品種マスタリスト: INDEX(#REF!,0)

Sheet _t受注ﾌｧｲﾙ
A1: 受注ﾌｧｲﾙ | B1: 依頼Ｎｏ | C1: 入力区分 | D1: 加工区分 | E1: 入力担当 | F1: 入力日 | G1: 受付Ｎｏ | H1: 品名 | I1: 製品 | J1: 梱-等1 | K1: 色1 | L1: 区分1 | M1: 枝番 | N1: 数量1 | O1: ＥＣ面 | P1: ﾄﾘﾐﾝｸﾞ | Q1: 割数 | R1: 品名1 | S1: 原反 | T1: 梱-等 | U1: 色 | V1: 区分 | W1: 数量 | X1: 在庫場所 | Y1: 投入場所 | Z1: 投入日 | AA1: 加工内容 | AB1: 特記事項1 | AC1: 特記事項2 | AD1: 特記事項3 | AE1: 用途 | AF1: ユーザー | AG1: 希望納期 | AH1: 調整納期 | AI1: 加工賃 | AJ1: 契約Ｎｏ | AK1: 原反ロール数 | AL1: 月数 | AM1: 受注金額 | AN1: 受注数 | AO1: 単価 | AP1: 受注金額(修正) | AQ1: masterBase商品(製品) | AR1: masterBase商品(原反) | AS1: 加工完了日 | AT1: 出来高１ | AU1: 出来高 | AV1: 加工金額 | AW1: 列4 | AX1: 桁製品 | AY1: 桁梱-等 | AZ1: 桁色 | BA1: 桁区分 | BB1: 桁枝番 | BC1: 桁原反 | BD1: 桁梱-等5 | BE1: 桁色6 | BF1: 桁区分7 | BG1: 列8 | BH1: 月 | BI1: 単価9 | BJ1: 金額 | BK1: ｴﾗｰ：単価1 | BL1: ｴﾗｰ数量1 | BM1: ｴﾗｰ：単価2 | BN1: ｴﾗｰ数量2 | BO1: ｴﾗｰ：単価3 | BP1: ｴﾗｰ数量3 | BQ1: ｴﾗｰ：単価4 | BR1: ｴﾗｰ数量4 | BS1: ｴﾗｰ：単価5 | BT1: ｴﾗｰ数量5 | BU1: 合計金額 | BV1: Column74 | BW1: Column75 | BX1: Column76 | BY1: Column77 | BZ1: Column78 | CA1: Column79 | CB1: Column80 | CC1: Column81 | CD1: Column82 | CE1: Column83 | CF1: 受注ﾌｧｲﾙ_1 | CG1: Sheet | CH1: false
A2: 受注ﾌｧｲﾙ | B2: W7-4 | C2: 通常入力 | D2: 後加工 | E2: 古家 | F2: 46219 | H2: 6783 | I2: 15020-JX5R-1300X300 | J2: F-A | K2: ナチュラル | L2: R | N2: 1200 | O2: Ｈ面 | Q2: 1 | R2: 6780 | S2: 15020-AX5R-1300X300 | T2: F-A | U2: ナチュラル | V2: P | W2: 2,700 | X2: 滋賀 | Y2: EC | Z2: 46213 | AA2: EC,検査 | AB2: ＊欠点個数確認チェック ラベル◎ 確認済み明記 | AE2: W（自動車） | AF2: 共和天１ | AG2: 46218 | AH2: 46225 | AI2: 38 | AJ2: 186811R | AK2: 9 | AL2: 7 | AN2: 1200 | AO2: 38 | AP2: 45600 | AQ2: A2F20JXD0300FN1 | AR2: B2F20AXD0300FN1 | CF2: 受注ﾌｧｲﾙ | CG2: Sheet | CH2: FALSE
A3: 受注ﾌｧｲﾙ | B3: W7-5 | C3: 通常入力 | D3: 後加工 | E3: 砂田 | F3: 46218 | H3: 6783 | I3: 15020-JX5R-1440X300 | J3: F-A | K3: ナチュラル | L3: R | N3: 3300 | O3: Ｈ面 | Q3: 1 | R3: 6780 | S3: 15020-AX5R-1440X300 | T3: F-A | U3: ナチュラル | V3: P | W3: 3900 | X3: 滋賀 | Y3: EC | Z3: 46213 | AA3: EC,検査 | AB3: ＊欠点個数確認チェック ラベル◎ 確認済み明記 | AE3: W（自動車） | AF3: 共和天１ | AG3: 46220 | AH3: 46221 | AI3: 38 | AJ3: 186812L | AK3: 13 | AL3: 7 | AN3: 3300 | AO3: 38 | AP3: 125400 | AQ3: A2F20JXE4300FN1 | AR3: B2F20AXE4300FN1 | CF3: 受注ﾌｧｲﾙ | CG3: Sheet | CH3: FALSE
A4: 受注ﾌｧｲﾙ | B4: JR260701 | C4: 通常入力 | D4: TPI | E4: 砂田 | F4: 46195 | H4: D33 | I4: 30020-A05W-870X97 | J4: F-A | K4: LG | N4: 1940 | P4: 有 | Q4: 1 | R4: 7A1 | S4: FEL3002BY05-10WD-1000X100 | U4: LG | W4: 1400 600 | X4: 湖南 | Y4: SEC | AA4: SEC,ｽﾘｯﾄ | AB4: 投入ﾛｯﾄ：26060001，0041，0042，0050,0064,0075 | AE4: JR（屋根） | AF4: 自動転記 | AG4: 46211 | AH4: 46211 | AI4: 43 | AJ4: P75564 | AK4: 20 | AL4: 7 | AN4: 1940 | AO4: 43 | AP4: 83420 | AQ4: A3O20A087097FL1 | AR4: B3O202BA0100FLA B3O202BA0100FLA | CF4: 受注ﾌｧｲﾙ | CG4: Sheet | CH4: FALSE
A5: 受注ﾌｧｲﾙ | B5: Y7-1 | C5: 通常入力 | D5: 後加工 | E5: 古家 | F5: 46217 | H5: 6713 | I5: 30020-BY00-640X250 | J5: F-A | L5: C | N5: 6000 | Q5: 1 | R5: 6710 | S5: 30040-AY00-640X250 | T5: F-A | V5: C | W5: 3,000 | Z5: 46204 | AA5: ｽﾗｲｽ | AE5: Y（工材） | AF5: フカサワ | AG5: 46209 | AH5: 46212 | AI5: 11 | AJ5: 187073A | AK5: 12 | AL5: 7 | AN5: 6000 | AO5: 11 | AP5: 66000 | AQ5: A2O20BY64250FN1 | AR5: B2O40AY64250FN1 | CF5: 受注ﾌｧｲﾙ | CG5: Sheet | CH5: FALSE
A6: 受注ﾌｧｲﾙ | B6: Y7-2 | C6: 通常入力 | D6: 後加工 | E6: 古家 | F6: 46217 | H6: 6713 | I6: 30020-8G00-250X200 | J6: J-A | L6: C | N6: 1600 | P6: 有 | Q6: 1 | R6: 6710 | S6: 30040-AG00-1000X200 | T6: F-A | V6: C | W6: 200 | X6: 滋賀 | Y6: SEC | Z6: 46205 | AA6: SEC,ｽﾘｯﾄ | AE6: Y（工材） | AF6: ゼネラル化成 | AG6: 46210 | AH6: 46211 | AI6: 10 | AJ6: 187074V | AK6: 1 | AL6: 7 | AN6: 1600 | AO6: 10 | AP6: 16000 | AQ6: A2O208G25200JN1 | AR6: B2O40AGA0200FN1 | CF6: 受注ﾌｧｲﾙ | CG6: Sheet | CH6: FALSE
A7: 受注ﾌｧｲﾙ | B7: Y7-3 | C7: 通常入力 | D7: 後加工 | E7: 古家 | F7: 46217 | H7: 6713 | I7: 30020-8G00-310X200 | J7: H-A | L7: C | N7: 1200 | P7: 有 | Q7: 1 | R7: 6710 | S7: 30040-AG00-1000X200 | T7: F-A | V7: C | W7: 200 | X7: 滋賀 | Y7: SEC | Z7: 46205 | AA7: SEC,ｽﾘｯﾄ | AE7: Y（工材） | AF7: ゼネラル化成 | AG7: 46210 | AH7: 46211 | AI7: 10 | AJ7: 187075B | AK7: 1 | AL7: 7 | AN7: 1200 | AO7: 10 | AP7: 12000 | AQ7: A2O208G25200HN1 | AR7: B2O40AGA0200FN1 | CF7: 受注ﾌｧｲﾙ | CG7: Sheet | CH7: FALSE
A8: 受注ﾌｧｲﾙ | B8: V6-16 | C8: 通常入力 | D8: 後加工 | E8: 砂田 | F8: 46192 | H8: 6713 | I8: 50090-AY0B-900X100 | J8: F-A | K8: BK0 | L8: C | N8: 100 | Q8: 1 | R8: 6713 | S8: 50090-AY0B-900X100 | T8: F-A | U8: BK0 | V8: C | W8: 100 | X8: 湖南 | Y8: ｽﾗｲｽ | AA8: ｽﾗｲｽ，巻き返し | AB8: スキン取り | AC8: ロット5CNC261 | AE8: V（TPI） | AF8: ＴＰＩ湖南 | AG8: 46192 | AH8: 46192 | AI8: 35 | AJ8: 186455R | AK8: 1 | AL8: 6 | AN8: 100 | AO8: 35 | AP8: 3500 | AQ8: A2Q60AY90100FB4 | AR8: B2Q60AY90100FN1 | CF8: 受注ﾌｧｲﾙ | CG8: Sheet | CH8: FALSE
A9: 受注ﾌｧｲﾙ | B9: W7-1 | C9: 通常入力 | D9: 後加工 | E9: 砂田 | F9: 46192 | H9: 6783 | I9: 15020-JX5R-1440X300 | J9: F-A | L9: R | N9: 6000 | O9: Ｈ面 | Q9: 1 | R9: 6780 | S9: 15020-AX5R-1440X300 | T9: F-A | V9: P | W9: 6,000 | X9: 滋賀 | Y9: EC | Z9: 46206 | AA9: EC,ゴミ除去 | AB9: ＊欠点個数確認チェック ラベル◎ 確認済み明記 | AE9: W（自動車） | AF9: 共和天１ | AG9: 46212 | AH9: 46212 | AI9: 38 | AJ9: 186643J | AK9: 20 | AL9: 7 | AN9: 6000 | AO9: 38 | AP9: 228000 | AQ9: A2F20JXE4300FN1 | AR9: B2F20AXE4300FN1 | CF9: 受注ﾌｧｲﾙ | CG9: Sheet | CH9: FALSE
A10: 受注ﾌｧｲﾙ | B10: W7-2 | C10: 通常入力 | D10: 後加工 | E10: 細川 | F10: 46212 | H10: 6783 | I10: 15020-JX5R-1300X300 | J10: F-A | L10: R | N10: 6000 | O10: Ｈ面 | Q10: 1 | R10: 6780 | S10: 15020-AX5R-1300X300 | T10: F-A | V10: P | W10: 6,000 | X10: 滋賀 | Y10: EC | Z10: 46206 | AA10: EC,ゴミ除去 | AB10: ＊欠点個数確認チェック ラベル◎ 確認済み明記 | AE10: W（自動車） | AF10: 共和天１ | AG10: 46216 | AH10: 46216 | AI10: 38 | AJ10: 186642P | AK10: 20 | AL10: 7 | AN10: 6000 | AO10: 38 | AP10: 228000 | AQ10: A2F20JXD0300FN1 | AR10: B2F20AXD0300FN1 | CF10: 受注ﾌｧｲﾙ | CG10: Sheet | CH10: FALSE
A11: 受注ﾌｧｲﾙ | B11: W7-3 | C11: 通常入力 | D11: 後加工 | E11: 砂田 | F11: 46192 | H11: 6783 | I11: 15020-JX5R-1440X300 | J11: F-A | L11: R | N11: 5400 | O11: Ｈ面 | Q11: 1 | R11: 6780 | S11: 15020-AX5R-1440X300 | T11: F-A | V11: P | W11: 6,000 | X11: 滋賀 | Y11: EC | Z11: 46209 | AA11: EC,ゴミ除去 | AB11: ＊欠点個数確認チェック ラベル◎ 確認済み明記 | AE11: W（自動車） | AF11: 共和天１ | AG11: 46217 | AH11: 46217 | AI11: 38 | AJ11: 186644A | AK11: 20 | AL11: 7 | AN11: 5400 | AO11: 38 | AP11: 205200 | AQ11: A2F20JXE4300FN1 | AR11: B2F20AXE0300FN1 | CF11: 受注ﾌｧｲﾙ | CG11: Sheet | CH11: FALSE
A12: 受注ﾌｧｲﾙ | B12: Y6-18 | C12: 通常入力 | D12: 後加工 | E12: 古家 | F12: 46191 | G12: Y6-18 | H12: 6713 | I12: 30022-BG00-1000X200 | J12: F-A | K12: WH1 | L12: C | N12: 12000 | Q12: 1 | R12: 6710 | S12: 30044-AG00-1000X200 | T12: F-A | U12: WH1 | V12: C | W12: 6,000 | X12: 滋賀 | Y12: ｽﾗｲｽ | Z12: 46196 | AA12: ｽﾗｲｽ | AC12: 検査前入庫依頼 | AE12: Y（工材） | AF12: 大伸工業 | AG12: 46198 | AH12: 46198 | AI12: 1 | AJ12: 185153B | AK12: 30 | AL12: 6 | AN12: 12000 | AO12: 1 | AP12: 12000 | AQ12: A2O22BGA0200FW3 | AR12: B2O44AGA0200FBP | CF12: 受注ﾌｧｲﾙ | CG12: Sheet | CH12: FALSE
A13: 受注ﾌｧｲﾙ | B13: Y6-19 | C13: 通常入力 | D13: 後加工 | E13: 古家 | F13: 46191 | G13: Y6-19 | H13: 6713 | I13: 30033-BY00-640X200 | J13: F-A | K13: GA0 | L13: C | N13: 20000 | Q13: 1 | R13: 6710 | S13: 30066-AY00-640X200 | T13: F-A | U13: GA0 | V13: C | W13: 10,000 | X13: 滋賀 | Y13: ｽﾗｲｽ | Z13: 46195 | AA13: ｽﾗｲｽ | AC13: 検査前入庫依頼 | AE13: Y（工材） | AF13: 阿部加工 | AG13: 46202 | AH13: 46202 | AI13: 11 | AJ13: 185154K | AK13: 50 | AL13: 6 | AN13: 20000 | AO13: 11 | AP13: 220000 | AQ13: A2O33BY64200FG3 | AR13: B2O66AY64200FG3 | CF13: 受注ﾌｧｲﾙ | CG13: Sheet | CH13: FALSE
A14: 受注ﾌｧｲﾙ | B14: W6-21 | C14: 通常入力 | D14: 後加工 | E14: 古家 | F14: 46191 | H14: 6783 | I14: 15020-JX5R-1440X300 | J14: F-A | L14: R | N14: 6000 | O14: Ｈ面 | Q14: 1 | R14: 6780 | S14: 15020-AX5R-1440X300 | T14: F-A | V14: P | W14: 6,000 | X14: 滋賀 | Y14: EC | Z14: 46192 | AA14: EC,検査 | AB14: ＊欠点個数確認チェック ラベル◎ 確認済み明記 | AE14: W（自動車） | AF14: 共和天１ | AG14: 46202 | AH14: 46202 | AI14: 38 | AJ14: 186336S | AK14: 20 | AL14: 6 | AN14: 6000 | AO14: 38 | AP14: 228000 | AQ14: A2F20JXE4300FN1 | AR14: B2F20AXE4300FN1 | CF14: 受注ﾌｧｲﾙ | CG14: Sheet | CH14: FALSE
A15: 受注ﾌｧｲﾙ | B15: W6-22 | C15: 通常入力 | D15: 後加工 | E15: 古家 | F15: 46191 | H15: 6783 | I15: 15020-JX5R-1300X300 | J15: F-A | L15: R | N15: 6000 | Q15: 1 | R15: 6780 | S15: 15020-AX5R-1300X300 | T15: F-A | V15: P | W15: 6,000 | X15: 滋賀 | Y15: EC | Z15: 46195 | AA15: EC,検査 | AB15: ＊欠点個数確認チェック ラベル◎ 確認済み明記 | AE15: W（自動車） | AF15: 共和天１ | AG15: 46203 | AH15: 46203 | AI15: 38 | AJ15: 186526W | AK15: 20 | AL15: 6 | AN15: 6000 | AO15: 38 | AP15: 228000 | AQ15: A2F20JXD0300FN1 | AR15: B2F20AXD0300FN1 | CF15: 受注ﾌｧｲﾙ | CG15: Sheet | CH15: FALSE
A16: 受注ﾌｧｲﾙ | B16: W6-23 | C16: 通常入力 | D16: 後加工 | E16: 古家 | F16: 46191 | H16: 6783 | I16: 20020-AP17-1120X300 20020-AP17-1120X297 20020-AP17-1120X289 | J16: F-A | L16: P | N16: 2400 297 289 | Q16: 1 | R16: 6780 | S16: 20020-AP17-1220X300 | T16: F-A | V16: P | W16: 3,000 | Z16: 46192 | AA16: ｽﾘｯﾄ | AB16: ＊欠点個数確認チェック ラベル◎ | AE16: W（自動車） | AF16: 共和新城 | AG16: 46197 | AH16: 46197 | AI16: 17 | AJ16: 186334G 186527R 186528L | AK16: 10 | AL16: 6 | AN16: 2400 297 289 | AO16: 17 | AP16: 50762 | AQ16: A2K20APB5300FN1 | AR16: B2K20APC2300FN1 | CF16: 受注ﾌｧｲﾙ | CG16: Sheet | CH16: FALSE
A17: 受注ﾌｧｲﾙ | B17: C6-9 | C17: 通常入力 | D17: 後加工 | E17: 古家 | F17: 46191 | H17: 6713 | I17: 30020-KG00-935X200 | J17: F-A | K17: GA1 | L17: V | N17: 400 | Q17: 1 | R17: 6710 | S17: 30040-AG00-935X200 | T17: F-A | U17: GA1 | V17: C | W17: 200 | X17: 滋賀 | Y17: SEC | Z17: 46195 | AA17: SEC,巻き返し | AB17: 穴無し 3インチ紙管 | AE17: Y（工材） | AF17: 東邦紙工 | AG17: 46198 | AH17: 46198 | AI17: 26 | AJ17: 186371M | AK17: 1 | AL17: 6 | AN17: 400 | AO17: 26 | AP17: 10400 | AQ17: A2O20KG93200FG4 | AR17: B2O40AG93200FG4 | CF17: 受注ﾌｧｲﾙ | CG17: Sheet | CH17: FALSE
A18: 受注ﾌｧｲﾙ | B18: C6-10 | C18: 通常入力 | D18: 後加工 | E18: 砂田 | F18: 46197 | H18: 6713 6713 | I18: 0R040-8Y0B-870X200 0R040-8Y0B-870X200 | J18: F-A F-A | K18: GA1 GA1 | L18: H Q | N18: 1600 1600 | Q18: 1 | R18: 6710 | S18: 50080-AY0B-870X200 | T18: F-A | U18: GA1 | V18: C | W18: 1600 | X18: 湖南 | Y18: SEC | Z18: 46204 | AA18: ＳＥＣ | AE18: Y（工材） | AF18: 屋根 | AG18: 46206 | AH18: 46206 | AI18: 13 | AK18: 9 | AL18: 7 | AN18: 1600 1600 | AO18: 13 | AP18: 41600 | AQ18: A2P408Y87200FG4 A2P408Y87200FGD | AR18: B2Q60AY87200FG4 | CF18: 受注ﾌｧｲﾙ | CG18: Sheet | CH18: FALSE
A19: 受注ﾌｧｲﾙ | B19: C6-11 | C19: 通常入力 | D19: 後加工 | E19: 砂田 | F19: 46202 | H19: 6713 | I19: 0R040-8Y0B-680X200 | J19: F-A | K19: BG1 | L19: C | N19: 18800 | Q19: 1 | R19: 6710 | S19: 50080-AY0B-680X200 | T19: F-A | U19: BG1 | V19: C | W19: 9400 | X19: 滋賀 | Y19: SEC | Z19: 46204 | AA19: SEC | AE19: Y（工材） | AF19: 屋根 | AG19: 46209 | AH19: 46209 | AI19: 13 | AJ19: 186932F | AK19: 48 | AL19: 7 | AN19: 18800 | AO19: 13 | AP19: 244400 | AQ19: A2P408Y68200FB1 | AR19: B2Q60AY68200FB1 | CF19: 受注ﾌｧｲﾙ | CG19: Sheet | CH19: FALSE
A20: 受注ﾌｧｲﾙ | B20: C6-12 | C20: 通常入力 | D20: 後加工 | E20: 砂田 | F20: 46198 | H20: 6713 | I20: 0R040-8Y0B-870X200 | J20: F-A | L20: C | N20: 24000 | Q20: 1 | R20: 6710 | S20: 50080-AY0B-870X200 | T20: F-A | V20: C | W20: 12,000 | X20: 滋賀 | Y20: SEC | Z20: 46205 | AA20: SEC | AE20: Y（工材） | AF20: 屋根 | AG20: 46180 | AH20: 46180 | AI20: 13 | AJ20: 186933W | AK20: 60 | AL20: 6 | AN20: 24000 | AO20: 13 | AP20: 312000 | AQ20: A2P408Y87200FN1 | AR20: B2Q60AY87200FN1 | CF20: 受注ﾌｧｲﾙ | CG20: Sheet | CH20: FALSE
A21: 受注ﾌｧｲﾙ | B21: JR260605 | C21: 通常入力 | D21: TPI | E21: 古家 | F21: 46191 | H21: 0 | I21: 40040-E10W-870X95 | N21: 190 | Q21: 1 | R21: 7A1 | S21: FEL4004AY-10WD-1000X100 | W21: 200 | X21: 湖南 | Y21: SEC | Z21: 46195 | AA21: SEC,ｽﾘｯﾄ | AB21: ４倍穴あけ | AE21: JR（屋根） | AG21: 46199 | AH21: 46199 | AI21: 43 | AJ21: P75558 | AK21: 2 | AL21: 6 | AN21: 190 | AO21: 43 | AP21: 8170 | AQ21: A3P40E187095FA1 | AR21: B3P404AA0100FA1 | CF21: 受注ﾌｧｲﾙ | CG21: Sheet | CH21: FALSE
A22: 受注ﾌｧｲﾙ | B22: GB60603 | C22: 通常入力 | D22: TPI | E22: 古家 | F22: 46191 | I22: 15030-JW07-760X3 | N22: 3 | Q22: 1 | S22: 15030-AW07- 760X 3 | W22: 3 | X22: 湖南 | Y22: ＥＣ | Z22: 46196 | AA22: EC | AE22: 小口加工 | AG22: 46196 | AH22: 46196 | AI22: 9 | AK22: 1 | AL22: 6 | AN22: 3 | AO22: 9 | AP22: 27 | AQ22: A3F30JW76050FN1 | AR22: B3F30AW76050FN1 | CF22: 受注ﾌｧｲﾙ | CG22: Sheet | CH22: FALSE
A23: 受注ﾌｧｲﾙ | B23: C6-6 | C23: 通常入力 | D23: 後加工 | E23: 砂田 | F23: 46199 | H23: 6713 6713 | I23: 0R040-8Y0B-680X200 0R040-8Y0B-680X197 | J23: F-A F-A | K23: GA1 GA1 | L23: C C | N23: 19600 394 | Q23: 1 | R23: 6710 | S23: 50080-AY0B-680X200 | T23: F-A | U23: GA1 | V23: C | W23: 10,000 | X23: 滋賀 | Y23: SEC | Z23: 46197 | AA23: SEC | AE23: Y（工材） | AF23: 屋根 | AG23: 46202 | AH23: 46202 | AI23: 13 | AJ23: 186046F 187062R | AK23: 50 | AL23: 6 | AN23: 19600 394 | AO23: 13 | AP23: 259922 | AQ23: A2P408Y68200FG1 A2P408Y68200FG1 | AR23: B2Q60AY68200FG4 | CF23: 受注ﾌｧｲﾙ | CG23: Sheet | CH23: FALSE
A24: 受注ﾌｧｲﾙ | B24: C6-7 | C24: 通常入力 | D24: 後加工 | E24: 砂田 | F24: 46190 | H24: 6713 6713 | I24: 0R040-8Y0B-870X200 0R040-8Y0B-870X200 0R040-8Y0B-870X196 0R040-8Y0B-870X196 | J24: F-A F-A | K24: GA1 GA1 | L24: H Q | N24: 9800 9800 196 196 | Q24: 1 | R24: 6710 | S24: 50080-AY0B-870X200 | T24: F-A | U24: GA1 | V24: C | W24: 10,000 | X24: 滋賀 | Y24: SEC | Z24: 46198 | AA24: SEC | AE24: Y（工材） | AF24: 屋根 | AG24: 46203 | AH24: 46203 | AI24: 13 | AJ24: 186047W 186048R 187435R 187436L | AK24: 50 | AL24: 6 | AN24: 9800 9800 196 196 | AO24: 13 | AP24: 259896 | AQ24: A2P408Y25200GN4 A2P408Y25200GND | AR24: B2Q60AY87200FG4 | CF24: 受注ﾌｧｲﾙ | CG24: Sheet | CH24: FALSE
A25: 受注ﾌｧｲﾙ | B25: C6-8 | C25: 通常入力 | D25: 後加工 | E25: 砂田 | F25: 46190 | H25: 6713 | I25: 0R040-8Y0B-520X200 0R040-8Y0B-520X197 0R040-8Y0B-520X198 0R040-8Y0B-520X199 | J25: F-A | K25: GA1 | L25: C | N25: 1400 197 198 199 | Q25: 1 | R25: 6713 | S25: 0R04-8Y0B-680X200 | T25: F-A | U25: GA1 | V25: C | W25: 2,000 | X25: 湖南 | Y25: ｽﾘｯﾄ | Z25: 46184 | AA25: ｽﾘｯﾄ | AE25: Y（工材） | AF25: 屋根 | AG25: 46188 | AH25: 46188 | AI25: 17 | AJ25: 185767T 185861B 185862K 186037H | AK25: 10 | AL25: 6 | AN25: 1400 197 198 199 | AO25: 17 | AP25: 33898 | AQ25: A2P408Y52200FG1 A2P408Y52200FG1 | AR25: B2P408Y68200FG4 | CF25: 受注ﾌｧｲﾙ | CG25: Sheet | CH25: FALSE
A26: 受注ﾌｧｲﾙ | B26: W6-18 | C26: 通常入力 | D26: 後加工 | E26: 砂田 | F26: 46190 | H26: 6783 6783 | I26: 20020-AP17-1450X60 20020-AP17-1550X240 | J26: F-A F-A | L26: P P | N26: 60 240 | P26: 有 | Q26: 1 | R26: 6780 | S26: 20020-AP17-1550X300 | T26: F-A | V26: P | W26: 500 | X26: 湖南 | Y26: ｽﾘｯﾄ | Z26: 46188 | AA26: スリット、分割 | AE26: W（自動車） | AF26: 共和新城 | AG26: 46190 | AH26: 46190 | AI26: 32 | AJ26: 185860V 186182A | AK26: 1 | AL26: 6 | AN26: 60 240 | AO26: 32 | AP26: 9600 | CF26: 受注ﾌｧｲﾙ | CG26: Sheet | CH26: FALSE
A27: 受注ﾌｧｲﾙ | B27: E6-5 | C27: 通常入力 | D27: 後加工 | E27: 砂田 | F27: 46190 | H27: 6783 | I27: 18030-JX5R-1390X250 | J27: F-A | L27: B | N27: 3250 | O27: Ｈ面 | Q27: 1 | R27: 6780 | S27: 18030-AX5R-1390X250 | T27: F-A | V27: B | W27: 3250 | X27: 滋賀 | Y27: EC | Z27: 46191 | AA27: EC,巻き返し | AB27: Ｑ面外巻き（ｲﾝﾗｲﾝEC仕様） | AE27: B（輸出） | AF27: 共和興 | AG27: 46202 | AH27: 46202 | AI27: 31 | AJ27: 186188R | AK27: 13 | AL27: 6 | AN27: 3250 | AO27: 31 | AP27: 100750 | AQ27: A2I30JXD9250FN1 | AR27: B2I30AXD9300FN1 | CF27: 受注ﾌｧｲﾙ | CG27: Sheet | CH27: FALSE
A28: 受注ﾌｧｲﾙ | B28: Y6-29 | C28: 通常入力 | D28: 後加工 | E28: 砂田 | F28: 46190 | H28: 6713 | I28: 10010-FY00-740X200 | J28: F-A | K28: GR0 | L28: C | N28: 200 | Q28: 1 | R28: 6710 | S28: 10010-AY00-750X200 | T28: F-A | U28: GR0 | V28: C | W28: 200 | X28: 湖南 | Y28: ｴﾝﾎﾞｽ | Z28: 46190 | AA28: ｴﾝﾎﾞｽ | AB28: コクヨシボ | AE28: Y（工材） | AF28: ニックス | AG28: 46191 | AH28: 46191 | AI28: 1 | AJ28: 186245G | AK28: 1 | AL28: 6 | AN28: 200 | AO28: 1 | AP28: 200 | AQ28: A2A10FY74200FGF | AR28: B2A10AY75200FG6 | CF28: 受注ﾌｧｲﾙ | CG28: Sheet | CH28: FALSE
A29: 受注ﾌｧｲﾙ | B29: W6-19 | C29: 通常入力 | D29: 後加工 | E29: 砂田 | F29: 46190 | H29: 6783 | I29: 15020-JX5R-1300X300 | J29: F-A | L29: R | N29: 2400 | P29: 有 | Q29: 1 | R29: 6780 | S29: 15020-AX5R-1440X300 | T29: F-A | V29: P | W29: 2,400 | X29: 滋賀 | Y29: ｽﾘｯﾄ | Z29: 46191 | AA29: ｽﾘｯﾄ，EC，検査 | AB29: ＊欠点個数確認チェック ラベル◎ 確認済み明記 | AE29: W（自動車） | AF29: 共和天１ | AG29: 46196 | AH29: 46196 | AI29: 55 | AJ29: 186178Z | AK29: 8 | AL29: 6 | AN29: 2400 | AO29: 55 | AP29: 132000 | AQ29: A2F20JXD0300FN1 | AR29: B2F20AXE4300FN1 | CF29: 受注ﾌｧｲﾙ | CG29: Sheet | CH29: FALSE
A30: 受注ﾌｧｲﾙ | B30: W6-20 | C30: 通常入力 | D30: 後加工 | E30: 砂田 | F30: 46190 | H30: 6783 | I30: 15020-JX5R-1440X300 | J30: F-A | L30: R | N30: 6600 | O30: Ｈ面 | Q30: 1 | R30: 6780 | S30: 15020-AX5R-1440X300 | T30: F-A | V30: P | W30: 6,600 | X30: 滋賀 | Z30: 46191 | AA30: EC，検査 | AB30: ＊欠点個数確認チェック ラベル◎ 確認済み明記 6/23 1200m6/24 3600m6/25 1800m出荷可能 | AC30: 6/23 1200m6/24 3600m6/25 1800m出荷可能 | AF30: 共和天１ | AG30: 46196 | AH30: 46196 | AI30: 38 | AJ30: 186179T | AK30: 22 | AL30: 6 | AN30: 6600 | AO30: 38 | AP30: 250800 | AQ30: A2F20JXE4300FN1 | AR30: B2F20AXE4300FN1 | CF30: 受注ﾌｧｲﾙ | CG30: Sheet | CH30: FALSE
A31: 受注ﾌｧｲﾙ | B31: Y6-25 | C31: 通常入力 | D31: 後加工 | E31: 古家 | F31: 46211 | H31: 6713 | I31: 30033-BY00-640X200 | J31: F-A | K31: GA0 | L31: C | N31: 20000 | Q31: 1 | R31: 6710 | S31: 30066-AY00-640X200 | T31: F-A | U31: GA0 | V31: C | W31: 10,000 | X31: 滋賀 | Y31: ｽﾗｲｽ | Z31: 46210 | AA31: ｽﾗｲｽ | AC31: 検査前入庫依頼 | AE31: Y（工材） | AF31: 阿部加工 | AG31: 46217 | AH31: 46217 | AI31: 11 | AJ31: 186241M | AK31: 50 | AL31: 7 | AN31: 20000 | AO31: 11 | AP31: 220000 | AQ31: A2O33BY64200FG3 | AR31: B2O66AY64200FG3 | CF31: 受注ﾌｧｲﾙ | CG31: Sheet | CH31: FALSE
A32: 受注ﾌｧｲﾙ | B32: Y6-26 | C32: 通常入力 | D32: 後加工 | E32: 古家 | F32: 46211 | H32: 6713 | I32: 30033-BY00-640X200 | J32: F-A | K32: GA0 | L32: C | N32: 0 | Q32: 1 | R32: 6710 | S32: 30066-AY00-640X200 | T32: F-A | U32: GA0 | V32: C | W32: 0 | X32: 滋賀 | Y32: ｽﾗｲｽ | AA32: ｽﾗｲｽ | AB32: 国分工場へ | AC32: 検査前入庫依頼 | AE32: Y（工材） | AF32: 阿部加工 | AI32: 11 | AK32: 50 | AL32: 1 | AN32: 0 | AO32: 11 | AP32: 0 | AQ32: A2O33BY64200FG3 | AR32: B2O66AY64200FG3 | CF32: 受注ﾌｧｲﾙ | CG32: Sheet | CH32: FALSE
A33: 受注ﾌｧｲﾙ | B33: Y6-27 | C33: 通常入力 | D33: 後加工 | E33: 砂田 | F33: 46190 | H33: 6713 | I33: 30020-BG00-780X300 | J33: F-A | L33: V | N33: 22200 | Q33: 1 | R33: 6710 | S33: 30040-AG00-780X300 | T33: F-A | V33: C | W33: 11,100 | X33: 湖南 | Y33: ｽﾗｲｽ | Z33: 46191 | AA33: ｽﾗｲｽ | AB33: 3インチ紙管 | AE33: Y（工材） | AF33: 菅原電気 | AG33: 46197 | AH33: 46197 | AI33: 11 | AJ33: 186217T | AK33: 37 | AL33: 6 | AN33: 22200 | AO33: 11 | AP33: 244200 | AQ33: A2O20BG78300FN1 | AR33: B2O40AG78300FN1 | CF33: 受注ﾌｧｲﾙ | CG33: Sheet | CH33: FALSE
A34: 受注ﾌｧｲﾙ | B34: Y6-28 | C34: 通常入力 | D34: 後加工 | E34: 砂田 | F34: 46190 | H34: 6783 | I34: 30030-AP66-550X300 | J34: F-A | K34: BK0 | L34: M | N34: 0 | P34: 有 | Q34: 1 | R34: 6780 | S34: 30030-AP66-1110X300 | T34: F-A | U34: BK0 | V34: M | W34: 0 | X34: 湖南 | Y34: ｽﾘｯﾄ | Z34: 46204 | AA34: ｽﾘｯﾄ，欠点表示 | AB34: スリットした側にもラベル貼付 | AC34: 検査前入庫依頼 | AE34: Y（工材） | AF34: ｺﾞﾄｰﾌﾟﾗｽﾁｯｸ | AG34: 46206 | AH34: 46206 | AI34: 21.5 | AK34: 15 | AL34: 7 | AN34: 0 | AO34: 21.5 | AP34: 0 | AQ34: A2O30AP55300FB4 | AR34: B2O30APB0300FB4 | CF34: 受注ﾌｧｲﾙ | CG34: Sheet | CH34: FALSE
A35: 受注ﾌｧｲﾙ | B35: T6-20 | C35: 通常入力 | D35: 後加工 | E35: 古家 | F35: 46184 | H35: 6713 | I35: 30030-JG20-1050X200 | J35: F-A | K35: GA0 | L35: Q | N35: 1600 | O35: Ｑ面 | Q35: 1 | R35: 6710 | S35: 30030-AG20-1050X200 | T35: F-A | U35: GA0 | V35: U | W35: 1,600 | X35: 滋賀 | Y35: EC | Z35: 46188 | AA35: EC | AE35: Y（工材） | AF35: 中央物産 | AG35: 46195 | AH35: 46195 | AI35: 18 | AJ35: 185821Z | AK35: 8 | AL35: 6 | AN35: 1600 | AO35: 18 | AP35: 28800 | AQ35: A2O30JGA5200F35 | AR35: B2O30AGA5200FG3 | CF35: 受注ﾌｧｲﾙ | CG35: Sheet | CH35: FALSE
A36: 受注ﾌｧｲﾙ | B36: T6-21 | C36: 通常入力 | D36: 後加工 | E36: 古家 | F36: 46184 | H36: 6713 | I36: 10010-FY00-740X200 | J36: F-A | K36: GR0 | L36: C | N36: 400 | Q36: 1 | R36: 6710 | S36: 10010-AY00-750X200 | T36: F-A | U36: GR0 | V36: C | W36: 400 | X36: 湖南 | Y36: ｴﾝﾎﾞｽ | Z36: 46191 | AA36: エンボス | AE36: Y（工材） | AF36: ニックス | AG36: 46198 | AH36: 46198 | AI36: 17 | AJ36: 185817Y | AK36: 2 | AL36: 6 | AN36: 400 | AO36: 17 | AP36: 6800 | AQ36: A2A10FY74200FG6 | AR36: B2A10AY75200FG6 | CF36: 受注ﾌｧｲﾙ | CG36: Sheet | CH36: FALSE
A37: 受注ﾌｧｲﾙ | B37: JR260604-1 | C37: 通常入力 | D37: TPI | E37: 古家 | F37: 46184 | I37: 40040-R10W-870X95 | J37: F-A | N37: 190 | Q37: 1 | R37: 7A1 | S37: FEL4004AY-10WD-1000X100 | T37: F-A | W37: 200 | X37: 湖南 | Y37: 融着 | Z37: 46183 | AA37: 熱融着 | AE37: JR（屋根） | AF37: 小口加工 | AG37: 46195 | AH37: 46195 | AK37: 2 | AL37: 6 | AN37: 190 | AP37: 0 | AQ37: A3P40R187095F51 | AR37: B3P404AA0100FA1 | CF37: 受注ﾌｧｲﾙ | CG37: Sheet | CH37: FALSE
A38: 受注ﾌｧｲﾙ | B38: W6-15 | C38: 通常入力 | D38: 後加工 | E38: 古家 | F38: 46184 | H38: 6783 | I38: 30030-JP66-1300X200 | J38: F-A | L38: Q | N38: 400 | O38: Ｑ面 | Q38: 1 | R38: 6780 | S38: 30030-AP66-1300X200 | T38: F-A | V38: G | W38: 400 | X38: 滋賀 | Y38: EC | Z38: 46188 | AA38: EC,欠点表示 | AB38: ＊欠点個数確認チェック ラベル◎ H面マジックマーキングしてください Ｑ面にテープマーキングしてください | AE38: W（自動車） | AF38: 共和天１ | AG38: 46190 | AH38: 46190 | AI38: 31 | AJ38: 185822T | AK38: 2 | AL38: 6 | AN38: 400 | AO38: 31 | AP38: 12400 | AQ38: A2O30JPD0200FN1 | AR38: B2O30APD0200FN1 | CF38: 受注ﾌｧｲﾙ | CG38: Sheet | CH38: FALSE
A39: 受注ﾌｧｲﾙ | B39: W6-16 | C39: 通常入力 | D39: 後加工 | E39: 古家 | F39: 46184 | H39: 6783 | I39: 25025-JP17-1440X250 | J39: F-A | L39: Q | N39: 500 | O39: Ｑ面 | Q39: 1 | R39: 6780 | S39: 25025-AP17-1580X250 | T39: F-A | V39: P | W39: 500 | X39: 滋賀 | Y39: ｽﾘｯﾄ | Z39: 46188 | AA39: EC,ｽﾘｯﾄ | AB39: ＊欠点個数確認チェック ラベル◎ | AE39: W（自動車） | AF39: 共和天１ | AG39: 46190 | AH39: 46190 | AI39: 35 | AJ39: 185823P | AK39: 2 | AL39: 6 | AN39: 500 | AO39: 35 | AP39: 17500 | AQ39: A2N25JPE4250FN1 | AR39: B2N25APF8250FN1 | CF39: 受注ﾌｧｲﾙ | CG39: Sheet | CH39: FALSE
A40: 受注ﾌｧｲﾙ | B40: W6-17 | C40: 通常入力 | D40: 後加工 | E40: 古家 | F40: 46184 | H40: 6783 6783 6783 | I40: 15015-AP67-1310X60 15015-AP67-950X60 15015-AP67-1550X | J40: F-A F-A F-A | L40: P P P | N40: 60 60 | P40: 有 有 | Q40: 1 | R40: 6783 | S40: 15015-AP67-1550X317 | T40: F-A | V40: P | W40: 317 | X40: 湖南 | Y40: ｽﾘｯﾄ | Z40: 46188 | AA40: スリット、分割 | AE40: W（自動車） | AF40: 共和新城 | AG40: 46190 | AH40: 46190 | AI40: 32 | AJ40: 185858J 185859A | AK40: 1 | AL40: 6 | AN40: 60 60 | AO40: 32 | AP40: 3840 | AQ40: A2F15APD1100FN1 A2F15AP95100FN1 A2F15APF5190FN1 | AR40: B2F15APF5350FN1 | CF40: 受注ﾌｧｲﾙ | CG40: Sheet | CH40: FALSE
A41: 受注ﾌｧｲﾙ | B41: T6-19 | C41: 通常入力 | D41: 後加工 | E41: 砂田 | F41: 46183 | H41: 6713 | I41: 30040-JG00-1030X200 | J41: F-A | K41: BK0 | L41: Q | N41: 800 | O41: Ｑ面 | Q41: 1 | R41: 6710 | S41: 30040-AG00-1030X200 | T41: F-A | U41: BK0 | V41: C | W41: 800 | X41: 滋賀 | Y41: EC | Z41: 46185 | AA41: EC | AE41: Y（工材） | AF41: 中央物産 | AG41: 46195 | AH41: 46195 | AI41: 18 | AJ41: 185771V | AK41: 4 | AL41: 6 | AN41: 800 | AO41: 18 | AP41: 14400 | AQ41: A2O40JGA3200FB4 | AR41: B2O40AGA3200FB4 | CF41: 受注ﾌｧｲﾙ | CG41: Sheet | CH41: FALSE
A42: 受注ﾌｧｲﾙ | B42: V6-14 | C42: 通常入力 | D42: 後加工 | E42: 砂田 | F42: 46183 | H42: 6713 | I42: 30060-AG00-1000X100 | J42: F-A | L42: C | N42: 7000 | Q42: 1 | R42: 6710 | S42: 30060-AG00-1000X200 | T42: F-A | V42: C | W42: 7,000 | X42: 滋賀 | Y42: ｽﾘｯﾄ | Z42: 46192 | AA42: 分割 | AE42: V（TPI） | AF42: ＴＰＩ湖南 | AG42: 46203 | AH42: 46203 | AI42: 15 | AJ42: 185654L | AK42: 35 | AL42: 6 | AN42: 7000 | AO42: 15 | AP42: 105000 | AQ42: A2O60AGA0100FN1 | AR42: B2O60AGA0200FN1 | CF42: 受注ﾌｧｲﾙ | CG42: Sheet | CH42: FALSE
A43: 受注ﾌｧｲﾙ | B43: V6-15 | C43: 通常入力 | D43: 後加工 | E43: 砂田 | F43: 46183 | H43: 6713 | I43: 30100-AG00-1000X50 | J43: F-A | L43: C | N43: 3100 | Q43: 1 | R43: 6710 | S43: 30100-AG00-1000X100 | T43: F-A | V43: C | W43: 3,100 | X43: 湖南 | Y43: ｽﾘｯﾄ | Z43: 46198 | AA43: 分割 | AE43: V（TPI） | AF43: ＴＰＩ湖南 | AG43: 46203 | AH43: 46203 | AI43: 15 | AJ43: 185652W | AK43: 31 | AL43: 6 | AN43: 3100 | AO43: 15 | AP43: 46500 | AQ43: A2100AGA0050FN1 | AR43: B2OA0AGA0100FN1 | CF43: 受注ﾌｧｲﾙ | CG43: Sheet | CH43: FALSE
A44: 受注ﾌｧｲﾙ | B44: Y6-16 | C44: 通常入力 | D44: 後加工 | E44: 細川 | F44: 46182 | H44: 6713 | I44: 30020-BG00-780X300 | J44: F-A | L44: V | N44: 16200 | R44: 6710 6710 | S44: 30040-AG00-780X300 30040-AG00-780X300 | T44: F-A F-A | V44: C C | W44: 7200 900 | X44: 滋賀 滋賀 | Y44: ｽﾗｲｽ ｽﾗｲｽ | Z44: 46183 | AA44: ｽﾗｲｽ | AB44: 3インチ紙管 | AE44: Y（工材） | AF44: 菅原電気 | AG44: 46190 | AH44: 46190 | AI44: 11 | AJ44: 184871Y | AK44: 24 3 | AL44: 6 | AN44: 16200 | AO44: 11 | AP44: 178200 | AQ44: A2O20BG78300FN1 | AR44: B2O40AG78300FN1 B2O40AG78300FN1 | CF44: 受注ﾌｧｲﾙ | CG44: Sheet | CH44: FALSE
A45: 受注ﾌｧｲﾙ | B45: T6-15 | C45: 通常入力 | D45: 後加工 | E45: 古家 | F45: 46182 | H45: 6713 | I45: 15020-BA00-1000X150 | J45: F-A | K45: BK0 | L45: C | N45: 300 | Q45: 1 | R45: 6710 | S45: 15040-AA00-1000X150 | T45: F-A | U45: BK0 | V45: C | W45: 150 | X45: 滋賀 | Y45: ｽﾗｲｽ | Z45: 46189 | AA45: スライス | AE45: Y（工材） | AF45: 中央物産 | AG45: 46195 | AH45: 46195 | AI45: 11 | AJ45: 185608H | AK45: 1 | AL45: 6 | AN45: 300 | AO45: 11 | AP45: 3300 | AQ45: A2F20BAA0150FB4 | AR45: B2F40AAA0150FB4 | CF45: 受注ﾌｧｲﾙ | CG45: Sheet | CH45: FALSE
A46: 受注ﾌｧｲﾙ | B46: T6-16 | C46: 通常入力 | D46: 後加工 | E46: 古家 | F46: 46182 | H46: 6713 | I46: 30020-BG20-1050X200 | J46: F-A | K46: GA0 | L46: U | N46: 800 | Q46: 1 | R46: 6710 | S46: 30040-AG20-1050X200 | T46: F-A | U46: GA0 | V46: U | W46: 400 | X46: 滋賀 | Y46: ｽﾗｲｽ | Z46: 46189 | AA46: スライス | AE46: Y（工材） | AF46: 中央物産 | AG46: 46195 | AH46: 46195 | AI46: 11 | AJ46: 185609Z | AK46: 2 | AL46: 6 | AN46: 800 | AO46: 11 | AP46: 8800 | AQ46: A2O20BGA5200FG3 | AR46: B2O40AGA5200FG3 | CF46: 受注ﾌｧｲﾙ | CG46: Sheet | CH46: FALSE
A47: 受注ﾌｧｲﾙ | B47: T6-17 | C47: 通常入力 | D47: 後加工 | E47: 古家 | F47: 46182 | H47: 6713 | I47: 30015-BG00-1030X200 | J47: F-A | K47: BK0 | L47: C | N47: 800 | Q47: 1 | R47: 6710 | S47: 30030-AG00-1030X200 | T47: F-A | U47: BK0 | V47: C | W47: 400 | X47: 滋賀 | Y47: ｽﾗｲｽ | Z47: 46189 | AA47: スライス | AE47: Y（工材） | AF47: 中央物産 | AG47: 46195 | AH47: 46195 | AI47: 11 | AJ47: 185610T | AK47: 2 | AL47: 6 | AN47: 800 | AO47: 11 | AP47: 8800 | AQ47: A2O15BGA3200FB4 | AR47: B2O30AGA3200FB4 | CF47: 受注ﾌｧｲﾙ | CG47: Sheet | CH47: FALSE
A48: 受注ﾌｧｲﾙ | B48: T6-18 | C48: 通常入力 | D48: 後加工 | E48: 古家 | F48: 46182 | H48: 6713 | I48: 30050-JG00-1030X200 | J48: F-A | K48: BK0 | L48: Q | N48: 1000 | O48: Ｑ面 | Q48: 1 | R48: 6710 | S48: 30050-AG00-1030X200 | T48: F-A | U48: BK0 | V48: C | W48: 1,000 | X48: 滋賀 | Y48: EC | Z48: 46184 | AA48: ＥＣ | AE48: Y（工材） | AF48: 中央物産 | AG48: 46189 | AH48: 46189 | AI48: 18 | AJ48: 185606S | AK48: 5 | AL48: 6 | AN48: 1000 | AO48: 18 | AP48: 18000 | AQ48: A2O50JGA3200FB4 | AR48: B2O50AGA3200FB4 | CF48: 受注ﾌｧｲﾙ | CG48: Sheet | CH48: FALSE
A49: 受注ﾌｧｲﾙ | B49: C6-4 | C49: 通常入力 | D49: 後加工 | E49: 砂田 | F49: 46181 | H49: 6713 6713 | I49: 0R040-8Y0B-870X200 0R040-8Y0B-870X200 | J49: F-A F-A | K49: GA1 GA1 | L49: H Q | N49: 10,000 10,000 | Q49: 1 | R49: 6710 | S49: 50080-AY0B-870X200 | T49: F-A | U49: GA1 | V49: C | W49: 10,000 | X49: 滋賀 | Y49: SEC | Z49: 46196 | AA49: SEC | AE49: Y（工材） | AF49: 屋根 | AG49: 46199 | AH49: 46199 | AI49: 13 | AJ49: 186042A 186043V | AK49: 50 | AL49: 6 | AN49: 10,000 10,000 | AO49: 13 | AP49: 260000 | AQ49: A2P408Y18200HG4 A2P408Y18200HGD | AR49: B2Q60AY87200FG4 | CF49: 受注ﾌｧｲﾙ | CG49: Sheet | CH49: FALSE
A50: 受注ﾌｧｲﾙ | B50: C6-3 | C50: 通常入力 | D50: 後加工 | E50: 砂田 | F50: 46181 | H50: 6713 6713 | I50: 0R040-8Y0B-870X200 0R040-8Y0B-870X200 | J50: F-A F-A | K50: GA1 GA1 | L50: H Q | N50: 10,000 10,000 | Q50: 1 | R50: 6710 | S50: 50080-AY0B-870X200 | T50: F-A | U50: GA1 | V50: C | W50: 10,000 | X50: 滋賀 | Y50: SEC | Z50: 46196 | AA50: SEC | AE50: Y（工材） | AF50: 屋根 | AG50: 46198 | AH50: 46198 | AI50: 13 | AJ50: 186039T 186040P | AK50: 50 | AL50: 6 | AN50: 10,000 10,000 | AO50: 13 | AP50: 260000 | AQ50: A2P408Y87200FG4 A2P408Y87200FGD | AR50: B2Q60AY87200FG4 | CF50: 受注ﾌｧｲﾙ | CG50: Sheet | CH50: FALSE
A51: 受注ﾌｧｲﾙ | B51: C6-5 | C51: 通常入力 | D51: 後加工 | E51: 砂田 | F51: 46181 | H51: 6713 | I51: 0R040-8Y0B-870X200 | J51: F-A | K51: BG1 | L51: C | N51: 20000 | Q51: 1 | R51: 6710 | S51: 50080-AY0B-870X200 | T51: F-A | U51: BG1 | V51: C | W51: 10,000 | X51: 滋賀 | Z51: 46198 | AA51: SEC | AE51: Y（工材） | AF51: 屋根 | AG51: 46203 | AH51: 46203 | AI51: 13 | AJ51: 186045K | AK51: 50 | AL51: 6 | AN51: 20000 | AO51: 13 | AP51: 260000 | AQ51: A2P408Y68200FG1 | AR51: B2Q60AY87200FBA | CF51: 受注ﾌｧｲﾙ | CG51: Sheet | CH51: FALSE
A52: 受注ﾌｧｲﾙ | B52: V6-12 | C52: 通常入力 | D52: 後加工 | E52: 砂田 | F52: 46181 | H52: 6713 | I52: 05020-AY00-630X100 | J52: F-A | K52: WH1 | L52: P | N52: 3000 | Q52: 1 | R52: 6710 | S52: 05020-AY00-630X200 | T52: F-A | U52: WH1 | V52: P | W52: 3,000 | X52: 滋賀 | Y52: ｽﾘｯﾄ | Z52: 46192 | AA52: 分割 | AE52: V（TPI） | AF52: ＴＰＩ湖南 | AG52: 46197 | AH52: 46197 | AI52: 15 | AJ52: 185657S | AK52: 15 | AL52: 6 | AN52: 3000 | AO52: 15 | AP52: 45000 | AQ52: A2520AY63100FW3 | AR52: B2520AY07100CN1 | CF52: 受注ﾌｧｲﾙ | CG52: Sheet | CH52: FALSE
A53: 受注ﾌｧｲﾙ | B53: V6-13 | C53: 通常入力 | D53: 後加工 | E53: 砂田 | F53: 46181 | H53: 6783 | I53: 30050-AS60-1000X100 | J53: F-A | L53: C | N53: 1000 | Q53: 1 | R53: 6780 | S53: 30050-AS60-1000X200 | T53: F-A | V53: C | W53: 1,000 | X53: 滋賀 | Y53: ｽﾘｯﾄ | Z53: 46196 | AA53: 分割 | AE53: V（TPI） | AF53: ＴＰＩ湖南 | AG53: 46199 | AH53: 46199 | AI53: 15 | AJ53: 185656Y | AK53: 5 | AL53: 6 | AN53: 1000 | AO53: 15 | AP53: 15000 | AQ53: A2O50ASA0100FN1 | AR53: B2O50ASA0200FN1 | CF53: 受注ﾌｧｲﾙ | CG53: Sheet | CH53: FALSE
A54: 受注ﾌｧｲﾙ | B54: E6-4 | C54: 通常入力 | D54: 後加工 | E54: 砂田 | F54: 46181 | H54: 6783 | I54: 15025-NR28-1550X250 | J54: F-A | K54: BK0 | L54: J | N54: 2500 | Q54: 1 | R54: 6780 | S54: 15025-SR28-1550X250 | T54: F-A | U54: BK0 | V54: J | W54: 2500 | X54: 滋賀 | Y54: EC | Z54: 46183 | AA54: EC,巻き返し | AB54: Ｑ面外巻き（ｲﾝﾗｲﾝEC仕様） 国分で加工時は巻き返し賃不要 | AE54: B（輸出） | AF54: 天安 | AG54: 46190 | AH54: 46190 | AI54: 49 | AJ54: 185638G | AK54: 15 | AL54: 6 | AN54: 2500 | AO54: 49 | AP54: 122500 | AQ54: A2F25NRF5250FB4 | AR54: B2F25SRF5200FB4 | CF54: 受注ﾌｧｲﾙ | CG54: Sheet | CH54: FALSE
A55: 受注ﾌｧｲﾙ | B55: V6-11 | C55: 通常入力 | D55: 後加工 | E55: 砂田 | F55: 46178 | G55: V6-11 | H55: 6713 | I55: 50060-AM0C-1030X100 | J55: F-A | K55: BK0 | L55: C | N55: 2000 | Q55: 1 | R55: 6710 | S55: 50060-AM0C-1030X200 | T55: F-A | U55: BK0 | V55: C | W55: 2,000 | X55: 滋賀 | Y55: ｽﾘｯﾄ | Z55: 46192 | AA55: 分割 | AE55: V（TPI） | AF55: ＴＰＩ湖南 | AG55: 46197 | AH55: 46197 | AI55: 15 | AJ55: 185333F | AK55: 10 | AL55: 6 | AN55: 2000 | AO55: 15 | AP55: 30000 | AQ55: A2Q60AMA3100FB4 | AR55: B2060AMA3200FB4 | CF55: 受注ﾌｧｲﾙ | CG55: Sheet | CH55: FALSE
A56: 受注ﾌｧｲﾙ | B56: W6-11 | C56: 通常入力 | D56: 後加工 | E56: 砂田 | F56: 46178 | H56: 6783 | I56: 30030-JP66-1300X200 | J56: F-A | L56: Q | N56: 400 | O56: Ｑ面 | Q56: 1 | R56: 6780 | S56: 30030-AP66-1300X200 | T56: F-A | V56: G | W56: 400 | X56: 滋賀 | Y56: EC | Z56: 46182 | AA56: EC,欠点表示 | AB56: ＊欠点個数確認チェック ラベル◎ H面マジックマーキングしてください Ｑ面にテープマーキングしてください | AE56: W（自動車） | AF56: 共和天１ | AG56: 46188 | AH56: 46188 | AI56: 31 | AJ56: 185409G | AK56: 2 | AL56: 6 | AN56: 400 | AO56: 31 | AP56: 12400 | AQ56: A2O30JPD0200FN1 | AR56: B2O30APD0200FN1 | CF56: 受注ﾌｧｲﾙ | CG56: Sheet | CH56: FALSE
A57: 受注ﾌｧｲﾙ | B57: W6-12 | C57: 通常入力 | D57: 後加工 | E57: 砂田 | F57: 46178 | H57: 6783 | I57: 25025-JP17-1440X250 | J57: F-A | L57: Q | N57: 500 | O57: Ｑ面 | Q57: 1 | R57: 6780 | S57: 25025-AP17-1580X250 | T57: F-A | V57: P | W57: 500 | X57: 滋賀 | Y57: ｽﾘｯﾄ | Z57: 46182 | AA57: EC,ｽﾘｯﾄ | AB57: ＊欠点個数確認チェック ラベル◎ | AE57: W（自動車） | AF57: 共和天１ | AG57: 46189 | AH57: 46189 | AI57: 35 | AJ57: 185408L | AK57: 2 | AL57: 6 | AN57: 500 | AO57: 35 | AP57: 17500 | AQ57: A2N25JPE4250FN1 | AR57: B2N25APF8250FN1 | CF57: 受注ﾌｧｲﾙ | CG57: Sheet | CH57: FALSE
A58: 受注ﾌｧｲﾙ | B58: W6-13 | C58: 通常入力 | D58: 後加工 | E58: 砂田 | F58: 46178 | H58: 6783 | I58: 25025-JP17-940X250 | J58: F-A | L58: Q | N58: 0 | O58: Ｑ面 | P58: 有 | Q58: 1 | R58: 6780 | S58: 25025-AP17-1100X250 | T58: F-A | V58: P | W58: 0 | X58: 滋賀 | Y58: ｽﾘｯﾄ | Z58: 46183 | AA58: EC,ｽﾘｯﾄ | AB58: キャンセル | AE58: W（自動車） | AF58: 共和天１ | AG58: 46189 | AH58: 46189 | AI58: 35 | AK58: 6 | AL58: 6 | AN58: 0 | AO58: 35 | AP58: 0 | AQ58: A2N25JP84250FN1 | AR58: B2N25APB0250FN1 | CF58: 受注ﾌｧｲﾙ | CG58: Sheet | CH58: FALSE
A59: 受注ﾌｧｲﾙ | B59: W6-14 | C59: 通常入力 | D59: 後加工 | E59: 砂田 | F59: 46178 | H59: 6785 | I59: 25025-JP17-940X250 | J59: F-A | L59: Q | N59: 1000 | O59: Ｑ面 | Q59: 1 | R59: 6783 | S59: 25025-JP17-940X250 | T59: F-A | V59: Q | W59: 1,000 | X59: 湖南 | Y59: EC | Z59: 46188 | AA59: EC | AB59: ＊欠点個数確認チェック ラベル◎ 再ＥＣ | AE59: W（自動車） | AF59: 共和天１ | AG59: 46189 | AH59: 46189 | AI59: 18 | AJ59: 185406W | AK59: 4 | AL59: 6 | AN59: 1000 | AO59: 18 | AP59: 18000 | AQ59: A2N25JPB0250FS1 | AR59: B2N25JP84250FN1 | CF59: 受注ﾌｧｲﾙ | CG59: Sheet | CH59: FALSE
A60: 受注ﾌｧｲﾙ | B60: T6-1 | C60: 通常入力 | D60: 後加工 | E60: 古家 | F60: 46177 | H60: 6715 | I60: 30100-VG00-1000X50 | J60: FA | L60: C | M60: 1 | N60: 500 | Q60: 1 | R60: 6713 | S60: 30100-NG00-1000X100 | T60: FA | V60: C | W60: 500 | X60: 滋賀 | Y60: ｴﾝﾎﾞｽ | Z60: 46174 | AA60: ｴﾝﾎﾞｽ,巻き返し,分割 | AB60: 【NVｼｰﾄ】明記 | AC60: 片面ｴﾝﾎﾞｽ+両面EC+ｴﾝﾎﾞｽ面内巻（巻き返し） | AE60: Y（工材） | AF60: ﾊﾞﾊﾞｿﾞﾉ | AG60: 46181 | AH60: 46181 | AI60: 45 | AJ60: 185240A | AK60: 5 | AL60: 6 | AM60: 22500 | AN60: 500 | AO60: 45 | AP60: 22500 | AQ60: A2O60NGA0050FN1 | AR60: B2OA0NGA0100FN1 | BH60: 7 | BI60: 38 | BJ60: 0 | CF60: 受注ﾌｧｲﾙ | CG60: Sheet | CH60: FALSE
A61: 受注ﾌｧｲﾙ | B61: A6-3 | C61: 通常入力 | D61: TPI | E61: 古家 | F61: 46177 | H61: 6713 | I61: 50070-BY0B-900X100 | J61: F-A | K61: BK0 | L61: X | N61: 300 | Q61: 1 | R61: 6710 | S61: 50090-AY0B-900X100 | T61: F-A | U61: BK0 | V61: C | W61: 300 | X61: 湖南 | Y61: ｽﾗｲｽ | Z61: 46181 | AA61: スライス | AE61: A（TPI） | AG61: 46184 | AH61: 46184 | AI61: 22 | AJ61: P521903 | AK61: 3 | AL61: 6 | AN61: 300 | AO61: 22 | AP61: 6600 | AQ61: A3O70BY90100FB4 | AR61: B3Q60AY90100FB4 | CF61: 受注ﾌｧｲﾙ | CG61: Sheet | CH61: FALSE
A62: 受注ﾌｧｲﾙ | B62: GB60601 | C62: 通常入力 | D62: TPI | E62: 古家 | F62: 46177 | H62: 0 | I62: HB3000GB45-1050X100 | J62: F-A | N62: 200 | Q62: 1 | R62: 0 | S62: HB3000GB45-1050X100 | T62: F-A | W62: 100 | X62: 湖南 | Y62: ｽﾗｲｽ | Z62: 46181 | AA62: スライス | AE62: 小口加工 | AG62: 46183 | AH62: 46183 | AK62: 1 | AL62: 6 | AN62: 200 | AP62: 0 | AR62: A3O202B05100FBA | CF62: 受注ﾌｧｲﾙ | CG62: Sheet | CH62: FALSE
A63: 受注ﾌｧｲﾙ | B63: A6-4 | C63: 通常入力 | D63: TPI | E63: 古家 | F63: 46177 | H63: 6713 | I63: 40050-BG00-1080X210 | J63: F-A | L63: X | N63: 1260 | Q63: 1 | R63: 6710 | S63: 40100-AG00-1080X105 | T63: F-A | V63: C | W63: 630 | X63: 湖南 | Y63: ｽﾗｲｽ | Z63: 46190 | AA63: スライス、接続 | AB63: 実測長さラベルと原反に明記 | AE63: A（TPI） | AG63: 46196 | AH63: 46196 | AI63: 26 | AJ63: P521904 | AK63: 6 | AL63: 6 | AN63: 1260 | AO63: 26 | AP63: 32760 | AQ63: A3P50BGA8210FN1 | AR63: B3PA0AGA8105FN1 | CF63: 受注ﾌｧｲﾙ | CG63: Sheet | CH63: FALSE
A64: 受注ﾌｧｲﾙ | B64: JR260603 | C64: 通常入力 | D64: TPI | E64: 古家 | F64: 46177 | H64: 0 | I64: 40040-R10W-870X95 | J64: F-A | K64: LG | N64: 475 | Q64: 1 | R64: 7A1 | S64: FEL4004AY-10WD-1000X100 | U64: LG | W64: 500 | X64: 湖南 | Y64: SEC | Z64: 46183 | AA64: SEC,ｽﾘｯﾄ | AE64: JR（屋根） | AG64: 46188 | AH64: 46188 | AI64: 43 | AJ64: P75424 | AK64: 5 | AL64: 6 | AN64: 475 | AO64: 43 | AP64: 20425 | AQ64: A3P40R187095FL1 | AR64: B3P404AA0100FAA | CF64: 受注ﾌｧｲﾙ | CG64: Sheet | CH64: FALSE
A65: 受注ﾌｧｲﾙ | B65: JR260604 | C65: 通常入力 | D65: TPI | E65: 古家 | F65: 46177 | H65: 0 | I65: 40040-R10W-870X95 | J65: F-A | N65: 950 | Q65: 1 | R65: 7A1 | S65: FEL4004AY-10WD-1000X100 | W65: 1000 | X65: 湖南 | Y65: SEC | Z65: 46183 | AA65: SEC,ｽﾘｯﾄ | AE65: JR（屋根） | AG65: 46195 | AH65: 46195 | AI65: 43 | AJ65: P75425 | AK65: 10 | AL65: 6 | AN65: 950 | AO65: 43 | AP65: 40850 | AQ65: A3P40R187095F51 | AR65: B3P404AA0100FA1 | CF65: 受注ﾌｧｲﾙ | CG65: Sheet | CH65: FALSE
A66: 受注ﾌｧｲﾙ | B66: E6-2 | C66: 通常入力 | D66: 後加工 | E66: 古家 | F66: 46176 | H66: 6783 | I66: 15020-NP17-1300X245 | J66: F-A | L66: J | N66: 245 | O66: 両面 | Q66: 1 | R66: 6783 | S66: 15020-AP17-1300X250 | T66: F-A | V66: P | W66: 250 | X66: 湖南 | Y66: EC | Z66: 46175 | AA66: EC,巻き返し | AB66: Ｑ面外巻き（ｲﾝﾗｲﾝEC仕様） 国分で加工時は巻き返し賃不要 | AC66: ※欠点表示はそのままでOK | AE66: B（輸出） | AF66: 天安 | AG66: 46178 | AH66: 46178 | AI66: 49 | AJ66: 185066F | AK66: 1 | AL66: 6 | AN66: 245 | AO66: 49 | AP66: 12005 | AQ66: A2F20NPB0250FNJ | AR66: B2F20APD0250FN1 | CF66: 受注ﾌｧｲﾙ | CG66: Sheet | CH66: FALSE
A67: 受注ﾌｧｲﾙ | B67: C5-1 | C67: 通常入力 | D67: 後加工 | E67: ゲスト | F67: 46176 | H67: 6713 | I67: 20010-H600-1180X250 | J67: FA | K67: WH1 | L67: C | N67: 2000 | O67: 両面 | Q67: 1 | R67: 6713 | S67: 20010-B600-1250X250 | T67: FA | U67: WH1 | V67: C | W67: 2000 | X67: 湖南 | Y67: ｽﾘｯﾄ | Z67: 46163 | AA67: EC,ｽﾘｯﾄ | AE67: Y（工材） | AF67: ｱﾝﾄﾞｰ | AG67: 46171 | AH67: 46171 | AI67: 53 | AJ67: 183597J | AK67: 8 | AL67: 5 | AM67: 106000 | AN67: 2000 | AO67: 53 | AP67: 106000 | BH67: 6 | BI67: 11 | BJ67: 0 | CF67: 受注ﾌｧｲﾙ | CG67: Sheet | CH67: FALSE
A68: 受注ﾌｧｲﾙ | B68: Y6-20 | C68: 通常入力 | D68: 後加工 | E68: 砂田 | F68: 46176 | G68: Y6-20 | H68: 6713 | I68: 30033-BY00-640X200 | J68: F-A | K68: GA0 | L68: C | N68: 20000 | Q68: 1 | R68: 6710 | S68: 30066-AY00-640X200 | T68: F-A | U68: GA0 | V68: C | W68: 10,000 | X68: 滋賀 | Y68: ｽﾗｲｽ | Z68: 46198 | AA68: ｽﾗｲｽ | AC68: 検査前入庫依頼 | AE68: Y（工材） | AF68: 阿部加工 | AG68: 46203 | AH68: 46203 | AI68: 11 | AJ68: 185155F | AK68: 50 | AL68: 6 | AN68: 20000 | AO68: 11 | AP68: 220000 | AQ68: A2O33BY64200FG3 | AR68: B2O66AY64200FG3 | CF68: 受注ﾌｧｲﾙ | CG68: Sheet | CH68: FALSE
A69: 受注ﾌｧｲﾙ | B69: Y6-21 | C69: 通常入力 | D69: 後加工 | E69: 砂田 | F69: 46202 | G69: Y6-21 | H69: 6713 | I69: 30033-BY00-640X200 | J69: F-A | K69: GA0 | L69: C | N69: 6000 | Q69: 1 | R69: 6710 | S69: 30066-AY00-640X200 | T69: F-A | U69: GA0 | V69: C | W69: 3000 | X69: 滋賀 | Y69: ｽﾗｲｽ | Z69: 46204 | AA69: ｽﾗｲｽ | AC69: 検査前入庫依頼 | AE69: Y（工材） | AF69: 阿部加工 | AG69: 46206 | AH69: 46206 | AI69: 11 | AJ69: 185287Z | AK69: 15 | AL69: 7 | AN69: 6000 | AO69: 11 | AP69: 66000 | AQ69: A2O33BY64200FG3 | AR69: B2O66AY64200FG3 | CF69: 受注ﾌｧｲﾙ | CG69: Sheet | CH69: FALSE
A70: 受注ﾌｧｲﾙ | B70: Y6-22 | C70: 通常入力 | D70: 後加工 | E70: 砂田 | F70: 46176 | G70: Y6-22 | H70: 6713 | I70: 30033-BY00-640X200 | J70: F-A | K70: GA0 | L70: C | N70: 20000 | Q70: 1 | R70: 6710 | S70: 30066-AY00-640X200 | T70: F-A | U70: GA0 | V70: C | W70: 10,000 | X70: 滋賀 | Y70: ｽﾗｲｽ | Z70: 46209 | AA70: ｽﾗｲｽ | AC70: 検査前入庫依頼 | AE70: Y（工材） | AF70: 阿部加工 | AG70: 46212 | AH70: 46212 | AI70: 11 | AJ70: 185288T | AK70: 50 | AL70: 7 | AN70: 20000 | AO70: 11 | AP70: 220000 | AQ70: A2O33BY64200FG3 | AR70: B2O66AY64200FG3 | CF70: 受注ﾌｧｲﾙ | CG70: Sheet | CH70: FALSE
A71: 受注ﾌｧｲﾙ | B71: Y6-23 | C71: 通常入力 | D71: 後加工 | E71: 砂田 | F71: 46176 | G71: Ｙ6-23 | H71: 6713 | I71: 30020-BG00-780X300 | J71: F-A | L71: V | N71: 16200 | Q71: 1 | R71: 6710 | S71: 30040-AG00-780X300 | T71: F-A | V71: C | W71: 8,100 | X71: 滋賀 | Y71: ｽﾗｲｽ | Z71: 46185 | AA71: ｽﾗｲｽ | AB71: 3インチ紙管 | AE71: Y（工材） | AF71: 菅原電気 | AG71: 46195 | AH71: 46195 | AI71: 11 | AJ71: 185289P | AK71: 27 | AL71: 6 | AN71: 16200 | AO71: 11 | AP71: 178200 | AQ71: A2O20BG78300FN1 | AR71: B2O40AG78300FN1 | CF71: 受注ﾌｧｲﾙ | CG71: Sheet | CH71: FALSE
A72: 受注ﾌｧｲﾙ | B72: Y6-24 | C72: 通常入力 | D72: 後加工 | E72: 砂田 | F72: 46176 | G72: Y6-24 | H72: 6713 | I72: 30020-BG00-780X300 | J72: F-A | L72: V | N72: 16200 | Q72: 1 | R72: 6710 | S72: 30040-AG00-780X300 | T72: F-A | V72: C | W72: 8,100 | X72: 滋賀 | Y72: ｽﾗｲｽ | Z72: 46188 | AA72: ｽﾗｲｽ | AB72: 3インチ紙管 | AE72: Y（工材） | AF72: 菅原電気 | AG72: 46196 | AH72: 46196 | AI72: 11 | AJ72: 185290J | AK72: 27 | AL72: 6 | AN72: 16200 | AO72: 11 | AP72: 178200 | AQ72: A2O20BG78300FN1 | AR72: B2O40AG78300FN1 | CF72: 受注ﾌｧｲﾙ | CG72: Sheet | CH72: FALSE
A73: 受注ﾌｧｲﾙ | B73: T6-11 | C73: 通常入力 | D73: 後加工 | E73: 砂田 | F73: 46176 | G73: T6-11 | H73: 6713 | I73: 30050-JG00-1030X200 | J73: F-A | K73: BK0 | L73: Q | N73: 2000 | O73: Ｑ面 | Q73: 1 | R73: 6710 | S73: 30050-AG00-1030X200 | T73: F-A | U73: BK0 | V73: C | W73: 2,000 | X73: 滋賀 | Y73: EC | Z73: 46190 | AA73: EC | AE73: Y（工材） | AF73: 中央物産 | AG73: 46195 | AH73: 46195 | AI73: 18 | AJ73: 185163H | AK73: 10 | AL73: 6 | AN73: 2000 | AO73: 18 | AP73: 36000 | AQ73: A2O30JGA3200FB4 | AR73: B2O50AGA3200FB4 | CF73: 受注ﾌｧｲﾙ | CG73: Sheet | CH73: FALSE
A74: 受注ﾌｧｲﾙ | B74: T6-12 | C74: 通常入力 | D74: 後加工 | E74: 砂田 | F74: 46176 | G74: T6-12 | H74: 6783 | I74: 30025-BS60-1000X200 | J74: F-A | L74: C | N74: 400 | Q74: 1 | R74: 6780 | S74: 30050-AS60-1000X200 | T74: F-A | V74: C | W74: 200 | X74: 滋賀 | Y74: ｽﾗｲｽ | Z74: 46178 | AA74: ｽﾗｲｽ | AE74: Y（工材） | AF74: 中央物産 | AG74: 46190 | AH74: 46190 | AI74: 11 | AJ74: 185282G | AK74: 1 | AL74: 6 | AN74: 400 | AO74: 11 | AP74: 4400 | AQ74: A2O25BSA0200FN1 | AR74: B2O50ASA0200FN1 | CF74: 受注ﾌｧｲﾙ | CG74: Sheet | CH74: FALSE
A75: 受注ﾌｧｲﾙ | B75: T6-13 | C75: 通常入力 | D75: 後加工 | E75: 砂田 | F75: 46176 | G75: T6-13 | H75: 6713 | I75: 30040-JG00-1030X200 | J75: F-A | K75: BK0 | L75: Q | N75: 400 | O75: Ｑ面 | Q75: 1 | R75: 6710 | S75: 30040-AG00-1030X200 | T75: F-A | U75: BK0 | V75: C | W75: 400 | X75: 滋賀 | AA75: EC | AE75: Y（工材） | AF75: 中央物産 | AG75: 46188 | AH75: 46188 | AI75: 18 | AJ75: 185283Y | AK75: 2 | AL75: 6 | AN75: 400 | AO75: 18 | AP75: 7200 | AQ75: A2O40JGA3200FB4 | AR75: B2O40AGA3200FB4 | CF75: 受注ﾌｧｲﾙ | CG75: Sheet | CH75: FALSE
A76: 受注ﾌｧｲﾙ | B76: T6-14 | C76: 通常入力 | D76: 後加工 | E76: 砂田 | F76: 46176 | G76: T6-14 | H76: 6713 | I76: 30020-KG00-1030X200 | J76: F-A | K76: BK0 | L76: C | N76: 2400 | O76: ｽｷﾝ面 | Q76: 1 | R76: 6710 | S76: 30040-AG00-1030X200 | T76: F-A | U76: BK0 | V76: C | W76: 1,200 | X76: 滋賀 | Y76: EC | Z76: 46178 | AA76: ｽﾗｲｽ，EC | AE76: Y（工材） | AF76: 中央物産 | AG76: 46188 | AH76: 46188 | AI76: 29 | AJ76: 185284S | AK76: 6 | AL76: 6 | AN76: 2400 | AO76: 29 | AP76: 69600 | AQ76: A2O20KGA3200FB4 | AR76: B2O40AGA3200FB4 | CF76: 受注ﾌｧｲﾙ | CG76: Sheet | CH76: FALSE
A77: 受注ﾌｧｲﾙ | B77: W6-9 | C77: 通常入力 | D77: 後加工 | E77: 砂田 | F77: 46175 | G77: W6-9 | H77: 6783 | I77: 25025-AP17-1010X250 | J77: F-A | L77: P | N77: 0 | P77: 有 | Q77: 1 | R77: 6780 | S77: 25025-AP17-1100X250 | T77: F-A | V77: P | W77: 0 | X77: 滋賀 | Y77: ｽﾘｯﾄ | Z77: 46191 | AA77: ｽﾘｯﾄ | AB77: キャンセル | AE77: W（自動車） | AF77: 共和新城 | AG77: 46195 | AH77: 46195 | AI77: 17 | AK77: 0 | AL77: 6 | AN77: 0 | AO77: 17 | AP77: 0 | AQ77: A2N25APA1250FN1 | AR77: B2N25APB0250FN1 | CF77: 受注ﾌｧｲﾙ | CG77: Sheet | CH77: FALSE
A78: 受注ﾌｧｲﾙ | B78: W6-10 | C78: 通常入力 | D78: 後加工 | E78: 細川 | F78: 46211 | G78: W6-10 | H78: 6783 | I78: 25025-JP17-1100X250 | J78: F-A | L78: Q | N78: 250 | O78: Ｑ面 | Q78: 1 | R78: 6780 | S78: 25025-AP17-1580X250 | T78: F-A | V78: P | W78: 250 | X78: 滋賀 | Y78: ｽﾘｯﾄ | Z78: 46181 | AA78: EC,ｽﾘｯﾄ | AB78: ＊欠点個数確認チェック ラベル◎ | AE78: W（自動車） | AF78: 共和天１ | AG78: 46185 | AH78: 46185 | AI78: 18 | AJ78: 185410Y | AK78: 1 | AL78: 6 | AN78: 250 | AO78: 18 | AP78: 4500 | AQ78: A2N25JPB0250FN1 | AR78: B2N25APB0250FN1 | CF78: 受注ﾌｧｲﾙ | CG78: Sheet | CH78: FALSE
A79: 受注ﾌｧｲﾙ | B79: Y6-17 | C79: 通常入力 | D79: 後加工 | E79: 砂田 | F79: 46175 | G79: Y6-17 | H79: 6713 | I79: 30020-BG00-780X300 | J79: F-A | L79: V | N79: 16200 | Q79: 2 | R79: 6710 | S79: 30040-AG00-780X300 | T79: F-A | V79: C | W79: 8,100 | X79: 滋賀 | Y79: ｽﾗｲｽ | Z79: 46184 | AA79: ｽﾗｲｽ | AB79: 3インチ紙管 | AE79: Y（工材） | AF79: 菅原電気 | AG79: 46192 | AH79: 46192 | AI79: 11 | AJ79: 185150J | AK79: 0 | AL79: 6 | AN79: 16200 | AO79: 11 | AP79: 178200 | AQ79: A2O20BG78300FN1 | AR79: B2O40AG78300FN1 | CF79: 受注ﾌｧｲﾙ | CG79: Sheet | CH79: FALSE
A80: 受注ﾌｧｲﾙ | B80: V6-7 | C80: 通常入力 | D80: 後加工 | E80: 古家 | F80: 46174 | H80: 6783 | I80: 0 | J80: F-A | L80: C | N80: 0 | Q80: 1 | R80: 6780 | S80: 30050-AS60-1000X200 | T80: F-A | V80: C | W80: 0 | X80: 滋賀 | Y80: ｽﾗｲｽ | Z80: 46178 | AA80: スライス | AB80: キャンセル | AE80: V（TPI） | AF80: ＴＰＩ湖南 | AG80: 46183 | AH80: 46183 | AI80: 11 | AJ80: 184659Y | AL80: 6 | AN80: 0 | AO80: 11 | AP80: 0 | CF80: 受注ﾌｧｲﾙ | CG80: Sheet | CH80: FALSE
A81: 受注ﾌｧｲﾙ | B81: V6-8 | C81: 通常入力 | D81: 後加工 | E81: 古家 | F81: 46174 | H81: 6713 | I81: 30100-AG00-1000X50 | J81: F-A | K81: BK0 | L81: C | N81: 4600 | Q81: 1 | R81: 6710 | S81: 30100-AG00-1000X100 | T81: F-A | U81: BK0 | V81: M | W81: 4,600 | X81: 滋賀 | Y81: ｽﾘｯﾄ | Z81: 46189 | AA81: 分割 | AE81: V（TPI） | AF81: ＴＰＩ湖南 | AG81: 46192 | AH81: 46192 | AI81: 15 | AJ81: 184661M | AK81: 0 | AL81: 6 | AN81: 4600 | AO81: 15 | AP81: 69000 | AQ81: A2100AGA0050FB4 | AR81: B2O60AGA0100FB4 | CF81: 受注ﾌｧｲﾙ | CG81: Sheet | CH81: FALSE
A82: 受注ﾌｧｲﾙ | B82: T6-7 | C82: 通常入力 | D82: 後加工 | E82: 古家 | F82: 46174 | H82: 6713 | I82: 30030-JG20-1050X200 | J82: F-A | K82: GA0 | L82: Q | N82: 0 | O82: Ｑ面 | Q82: 1 | R82: 6710 | S82: 30030-AG20-1050X200 | T82: F-A | U82: GA0 | V82: U | W82: 0 | X82: 滋賀 | Y82: EC | Z82: 46177 | AA82: EC | AB82: キャンセル | AE82: Y（工材） | AF82: 中央物産 | AG82: 46181 | AH82: 46181 | AI82: 18 | AK82: 0 | AL82: 6 | AN82: 0 | AO82: 18 | AP82: 0 | CF82: 受注ﾌｧｲﾙ | CG82: Sheet | CH82: FALSE
A83: 受注ﾌｧｲﾙ | B83: T6-8 | C83: 通常入力 | D83: 後加工 | E83: 古家 | F83: 46174 | H83: 6713 | I83: 30040-JG00-1030X200 | J83: F-A | K83: BK0 | L83: Q | N83: 1400 | O83: Ｑ面 | Q83: 1 | R83: 6710 | S83: 30040-AG00-1030X200 | T83: F-A | U83: BK0 | V83: C | W83: 1,400 | X83: 滋賀 | Y83: EC | Z83: 46178 | AA83: EC | AE83: Y（工材） | AF83: 中央物産 | AG83: 46183 | AH83: 46183 | AI83: 18 | AJ83: 184977Y | AK83: 0 | AL83: 6 | AN83: 1400 | AO83: 18 | AP83: 25200 | AQ83: A2O40JGA3200FB4 | AR83: B2O40AGA3200FB4 | CF83: 受注ﾌｧｲﾙ | CG83: Sheet | CH83: FALSE
A84: 受注ﾌｧｲﾙ | B84: T6-9 | C84: 通常入力 | D84: 後加工 | E84: 古家 | F84: 46174 | H84: 6713 | I84: 30020-KG00-1030X200 | J84: F-A | K84: BK0 | L84: C | N84: 2400 | O84: ｽｷﾝ面 | Q84: 1 | R84: 6710 | S84: 30040-AG00-1030X200 | T84: F-A | U84: BK0 | V84: C | W84: 1,200 | X84: 滋賀 | Y84: EC | Z84: 46178 | AA84: EC,ｽﾗｲｽ | AE84: Y（工材） | AF84: 中央物産 | AG84: 46183 | AH84: 46183 | AI84: 29 | AJ84: 184979M | AK84: 0 | AL84: 6 | AN84: 2400 | AO84: 29 | AP84: 69600 | AQ84: A2O20KGA3200FB4 | AR84: B2O40AGA3200FB4 | CF84: 受注ﾌｧｲﾙ | CG84: Sheet | CH84: FALSE
A85: 受注ﾌｧｲﾙ | B85: T6-10 | C85: 通常入力 | D85: 後加工 | E85: 古家 | F85: 46174 | H85: 6713 | I85: 30030-JG00-1030X200 | J85: F-A | K85: BK0 | L85: Q | N85: 1000 | O85: Ｑ面 | Q85: 1 | R85: 6710 | S85: 30030-AG00-1030X200 | T85: F-A | U85: BK0 | V85: C | W85: 1,000 | X85: 滋賀 | Y85: EC | Z85: 46178 | AA85: ＥＣ | AE85: Y（工材） | AF85: 中央物産 | AG85: 46190 | AH85: 46190 | AI85: 18 | AJ85: 184976G | AK85: 0 | AL85: 6 | AN85: 1000 | AO85: 18 | AP85: 18000 | AQ85: A2O30JGA3200FB4 | AR85: B2O30AGA3200FB4 | CF85: 受注ﾌｧｲﾙ | CG85: Sheet | CH85: FALSE
A86: 受注ﾌｧｲﾙ | B86: Y6-13 | C86: 通常入力 | D86: 後加工 | E86: 古家 | F86: 46174 | H86: 6713 | I86: 30020-BG00-780X300 | J86: F-A | L86: V | N86: 16200 | Q86: 1 | R86: 6710 | S86: 30040-AG00-780X300 | T86: F-A | V86: C | W86: 8,100 | X86: 湖南 | Y86: ｽﾗｲｽ | Z86: 46175 | AA86: ｽﾗｲｽ | AB86: 3インチ紙管 | AE86: Y（工材） | AF86: 菅原電気 | AG86: 46178 | AH86: 46178 | AI86: 11 | AJ86: 184866F | AK86: 0 | AL86: 6 | AN86: 16200 | AO86: 11 | AP86: 178200 | AQ86: A2O20BG78300FN1 | AR86: B2O40AG78300FN1 | CF86: 受注ﾌｧｲﾙ | CG86: Sheet | CH86: FALSE
A87: 受注ﾌｧｲﾙ | B87: Y6-14 | C87: 通常入力 | D87: 後加工 | E87: 古家 | F87: 46174 | H87: 6713 | I87: 30020-BG00-780X300 | J87: F-A | L87: V | N87: 16200 | Q87: 1 | R87: 6710 | S87: 30040-AG00-780X300 | T87: F-A | V87: C | W87: 8,100 | X87: 湖南 | Y87: ｽﾗｲｽ | Z87: 46181 | AA87: ｽﾗｲｽ | AB87: 3インチ紙管 | AE87: Y（工材） | AF87: 菅原電気 | AG87: 46185 | AH87: 46185 | AI87: 11 | AJ87: 184867W | AK87: 0 | AL87: 6 | AN87: 16200 | AO87: 11 | AP87: 178200 | AQ87: A2O20BG78300FN1 | AR87: B2O40AG78300FN1 | CF87: 受注ﾌｧｲﾙ | CG87: Sheet | CH87: FALSE
A88: 受注ﾌｧｲﾙ | B88: Y6-15 | C88: 通常入力 | D88: 後加工 | E88: 古家 | F88: 46174 | H88: 6713 | I88: 30020-BG00-780X300 | J88: F-A | L88: V | N88: 16200 | Q88: 1 | R88: 6710 | S88: 30040-AG00-780X300 | T88: F-A | V88: C | W88: 8,100 | X88: 滋賀 | Y88: ｽﾗｲｽ | Z88: 46182 | AA88: ｽﾗｲｽ | AB88: 3インチ紙管 | AE88: Y（工材） | AF88: 菅原電気 | AG88: 46188 | AH88: 46188 | AI88: 11 | AJ88: 184869L | AK88: 0 | AL88: 6 | AN88: 16200 | AO88: 11 | AP88: 178200 | AQ88: A2O20BG78300FN1 | AR88: B2O40AG78300FN1 | CF88: 受注ﾌｧｲﾙ | CG88: Sheet | CH88: FALSE
A89: 受注ﾌｧｲﾙ | B89: A6-2 | C89: 通常入力 | D89: TPI | E89: 図司 | F89: 46171 | H89: 6713 | I89: 30080-AG00-1000X100 | J89: FA | L89: X | N89: 600 | O89: 0 | Q89: 1 | R89: 6710 | S89: 30080-AG00-1000X100 | T89: FA | W89: 600 | X89: 湖南 | Y89: ｽﾘｯﾄ | Z89: 46181 | AA89: 巻き返し | AE89: A（TPI） | AF89: 0 | AG89: 46183 | AH89: 46183 | AI89: 13 | AJ89: P521902 | AK89: 1 | AL89: 6 | AN89: 600 | AO89: 13 | AP89: 7800 | AQ89: A3O60AGA0100FNA | AR89: B3O60AGA0100FNA | CF89: 受注ﾌｧｲﾙ | CG89: Sheet | CH89: FALSE
A90: 受注ﾌｧｲﾙ | B90: W6-6 | C90: 通常入力 | D90: 後加工 | E90: 古家 | F90: 46171 | H90: 6783 | I90: 20020-AP17-1120X300 | J90: F-A | L90: P | N90: 1500 | P90: 有 | Q90: 1 | R90: 6780 | S90: 20020-AP17-1310X300 | T90: F-A | V90: P | W90: 1,500 | X90: 湖南 | Y90: ｽﾘｯﾄ | Z90: 46174 | AA90: ｽﾘｯﾄ | AB90: ＊欠点個数確認チェック ラベル◎ | AE90: W（自動車） | AF90: 共和新城 | AG90: 46176 | AH90: 46176 | AI90: 17 | AJ90: 184441K | AK90: 0 | AL90: 6 | AN90: 1500 | AO90: 17 | AP90: 25500 | AQ90: A2K20APB5300FN1 | AR90: B2K20APD3300FN1 | CF90: 受注ﾌｧｲﾙ | CG90: Sheet | CH90: FALSE
A91: 受注ﾌｧｲﾙ | B91: E6-3 | C91: 通常入力 | D91: 後加工 | E91: 古家 | F91: 46171 | H91: 6783 | I91: 15030-SR28-1100X300 | J91: F-A | K91: BK0 | L91: E | N91: 9600 | P91: 有 | Q91: 1 | R91: 6780 | S91: 15030-SR28-1150X300 | T91: F-A | U91: BK0 | V91: E | W91: 9,600 | X91: 奥田数 | Y91: ｽﾘｯﾄ | Z91: 46183 | AA91: ｽﾘｯﾄ | AE91: B（輸出） | AF91: Greentech | AG91: 46191 | AH91: 46191 | AI91: 17 | AJ91: 184785H | AK91: 32 | AL91: 6 | AN91: 9600 | AO91: 17 | AP91: 163200 | AQ91: A2F30SRB0300FB1 | AR91: B2F30SRB5300FB1 | CF91: 受注ﾌｧｲﾙ | CG91: Sheet | CH91: FALSE
A92: 受注ﾌｧｲﾙ | B92: V6-10 | C92: 通常入力 | D92: 後加工 | E92: 図司 | F92: 46171 | H92: 6713 | I92: 30100-AG00-1000X50 | J92: F-A | L92: C | N92: 6600 | Q92: 1 | R92: 6710 | S92: 30100-AG00-1000X100 | T92: F-A | V92: C | W92: 6,600 | X92: 滋賀 | Z92: 46188 | AA92: 分割 | AF92: ＴＰＩ湖南 | AG92: 46192 | AH92: 46192 | AI92: 15 | AJ92: 184914T | AK92: 0 | AL92: 6 | AN92: 6600 | AO92: 15 | AP92: 99000 | AQ92: A2O60AGA5050FB1 | AR92: B2OA0AGA0100FB4 | CF92: 受注ﾌｧｲﾙ | CG92: Sheet | CH92: FALSE
A93: 受注ﾌｧｲﾙ | B93: V6-9 | C93: 通常入力 | D93: 後加工 | E93: 図司 | F93: 46171 | H93: 6713 | I93: 30100-AG00-1000X50 | J93: F-A | L93: C | N93: 1800 | Q93: 1 | R93: 6710 | S93: 30100-AG00-1000X100 | T93: F-A | V93: C | W93: 1,800 | X93: 滋賀 | Z93: 46188 | AA93: 分割 | AF93: ＴＰＩ湖南 | AG93: 46192 | AH93: 46192 | AI93: 15 | AJ93: 184913Z | AK93: 0 | AL93: 6 | AN93: 1800 | AO93: 15 | AP93: 27000 | AQ93: A2O60AGA5050FB1 | AR93: B2OA0AGA0100FN1 | CF93: 受注ﾌｧｲﾙ | CG93: Sheet | CH93: FALSE
A94: 受注ﾌｧｲﾙ | B94: W6-8 | C94: 通常入力 | D94: 後加工 | E94: 図司 | F94: 46171 | H94: 6783 | I94: 15020-JX5R-770X300 | J94: F-A | L94: R | N94: 5400 290 | Q94: 1 | R94: 6780 | S94: 15020-AX5R-770X300 | T94: F-A | V94: P | W94: 5700 | X94: 滋賀 | Z94: 46177 | AA94: EC,検査 | AB94: ＊欠点個数確認チェック ラベル◎ 確認済み明記 | AF94: 共和天１ | AG94: 46185 | AH94: 46185 | AI94: 38 | AJ94: 184951A 185679P | AK94: 0 | AL94: 6 | AN94: 5400 290 | AO94: 38 | AP94: 216220 | AQ94: A2F20JX77300FN1 | AR94: B2F25AX77300FN1 | CF94: 受注ﾌｧｲﾙ | CG94: Sheet | CH94: FALSE
A95: 受注ﾌｧｲﾙ | B95: C6-2 | C95: 通常入力 | D95: 後加工 | E95: 古家 | F95: 46171 | H95: 6713 | I95: 30020-KG00-935X200 | J95: F-A | K95: GA1 | L95: V | N95: 400 | O95: ｽｷﾝ面 | Q95: 1 | R95: 6710 | S95: 30040-AG00-935X200 | T95: F-A | U95: GA1 | V95: C | W95: 200 | X95: 滋賀 | Y95: SEC | Z95: 46181 | AA95: SEC | AB95: 穴なし3インチ紙管 | AE95: Y（工材） | AF95: 田窪工業所 | AG95: 46183 | AH95: 46183 | AI95: 26 | AJ95: 185152V | AK95: 1 | AL95: 6 | AN95: 400 | AO95: 26 | AP95: 10400 | AQ95: A2O20KG93200FG4 | AR95: B2O40AG93200FG4 | CF95: 受注ﾌｧｲﾙ | CG95: Sheet | CH95: FALSE
A96: 受注ﾌｧｲﾙ | B96: T6-5 | C96: 通常入力 | D96: 後加工 | E96: 古家 | F96: 46170 | H96: 6713 | I96: 30020-KG00-1050X200 | J96: F-A | L96: C | N96: 400 | O96: ｽｷﾝ面 | Q96: 1 | R96: 6710 | S96: 30040-AG00-1050X200 | T96: F-A | V96: C | W96: 200 | X96: 滋賀 | Y96: EC | Z96: 46174 | AA96: EC,ｽﾗｲｽ | AE96: Y（工材） | AF96: 中央物産 | AG96: 46181 | AH96: 46181 | AI96: 29 | AJ96: 184400Z | AK96: 1 | AL96: 6 | AN96: 400 | AO96: 29 | AP96: 11600 | AQ96: A2O20KGA5200FN1 | AR96: B2O40AGA5200FN1 | CF96: 受注ﾌｧｲﾙ | CG96: Sheet | CH96: FALSE
A97: 受注ﾌｧｲﾙ | B97: Y6-11 | C97: 通常入力 | D97: 後加工 | E97: 古家 | F97: 46170 | H97: 6713 | I97: 30030-BG00-1000X200 | J97: F-A | K97: BK0 | L97: C | N97: 2000 | Q97: 1 | R97: 6710 | S97: 30060-AG00-1000X200 | T97: F-A | U97: BK0 | V97: C | W97: 1,000 | X97: 湖南 | Y97: ｽﾗｲｽ | Z97: 46177 | AA97: ｽﾗｲｽ | AE97: Y（工材） | AF97: 芙蓉 | AG97: 46183 | AH97: 46183 | AI97: 11 | AJ97: 184461R | AK97: 0 | AL97: 6 | AN97: 2000 | AO97: 11 | AP97: 22000 | AQ97: A2O30BGA0200FB4 | AR97: B2O60AGA0200FB1 | CF97: 受注ﾌｧｲﾙ | CG97: Sheet | CH97: FALSE
A98: 受注ﾌｧｲﾙ | B98: C6-1 | C98: 通常入力 | D98: 後加工 | E98: 砂田 | F98: 46170 | H98: 6713 | I98: 0R040-8Y0B-310X200 0R040-8Y0B-310X197 0R040-8Y0B-310X198 | J98: G-A | L98: C | N98: 1600 394 1188 | P98: 有 | Q98: 1 | R98: 6713 | S98: 0R040-8Y0B-820X200 | T98: F-A | V98: C | W98: 1,600 | X98: 湖南 | Y98: ｽﾘｯﾄ | Z98: 46175 | AA98: ｽﾘｯﾄ | AE98: Y（工材） | AF98: 屋根 | AG98: 46178 | AH98: 46178 | AI98: 8.5 | AJ98: 184488J 185148T 185149P | AK98: 0 | AL98: 6 | AN98: 1600 394 1188 | AO98: 8.5 | AP98: 27047 | AQ98: A2P408Y31200GN1 | AR98: B2P408Y82200FN1 | CF98: 受注ﾌｧｲﾙ | CG98: Sheet | CH98: FALSE
A99: 受注ﾌｧｲﾙ | B99: Y6-12 | C99: 通常入力 | D99: 後加工 | E99: 古家 | F99: 46170 | H99: 6713 | I99: 30020-BY00-640X250 | J99: F-A | L99: C | N99: 12000 | Q99: 1 | R99: 6710 | S99: 30040-AY00-640X250 | T99: F-A | V99: C | W99: 6,000 | X99: 滋賀 | Y99: ｽﾗｲｽ | Z99: 46177 | AA99: スライス | AE99: Y（工材） | AF99: フカサワ | AG99: 46188 | AH99: 46188 | AI99: 11 | AJ99: 184523Z | AK99: 0 | AL99: 6 | AN99: 12000 | AO99: 11 | AP99: 132000 | AQ99: A2O20BY64250FW3 | AR99: B2O40AY64250FN1 | CF99: 受注ﾌｧｲﾙ | CG99: Sheet | CH99: FALSE
A100: 受注ﾌｧｲﾙ | B100: W5-22 | C100: 通常入力 | D100: 後加工 | E100: 古家 | F100: 46170 | H100: 6798 | I100: 13011-APR0-1500X63 | J100: F-A | L100: X | N100: 63 | Q100: 1 | R100: 6798 | S100: 13011-APR0-1500X63 | T100: F-A | V100: ｘ | W100: 63 | X100: 湖南 | Y100: ｽﾘｯﾄ | Z100: 46171 | AA100: 検査 | AB100: ラベル張替えのみ | AE100: W（自動車） | AF100: 共和新城 | AG100: 46171 | AH100: 46171 | AI100: 15 | AK100: 1 | AL100: 5 | AN100: 63 | AO100: 15 | AP100: 945 | AQ100: A2D11APF0100FNX | AR100: B2D11APF0100FNX | CF100: 受注ﾌｧｲﾙ | CG100: Sheet | CH100: FALSE
...

Sheet 呼び出された関数
A1: 依頼NO | B1: 項目 | C1: スライス | D1: EC | E1: スリット | F1: SEC | G1: 分割 | H1: 接続 | I1: 巻返し | J1: エンボス | K1: 欠点表示 | L1: 検査 | M1: --合計-- | N1: --計-- | O1: Column15 | P1: 年月 | Q1: 依頼NO(-1除外)
A2: C10-1 | B2: 加工金額 | C2: 198000 | D2: 0 | E2: 0 | F2: 0 | G2: 0 | H2: 0 | I2: 0 | J2: 0 | K2: 0 | L2: 0 | M2: 198000 | N2: 396000 | P2: 45931 | Q2: C10-1
A3: C10-10 | B3: 加工金額 | C3: 198000 | D3: 0 | E3: 0 | F3: 0 | G3: 0 | H3: 0 | I3: 0 | J3: 0 | K3: 0 | L3: 0 | M3: 198000 | N3: 396000 | P3: 45931 | Q3: C10-10
A4: C10-11 | B4: 加工金額 | C4: 0 | D4: 0 | E4: 40630 | F4: 62140 | G4: 0 | H4: 0 | I4: 0 | J4: 0 | K4: 0 | L4: 0 | M4: 102770 | N4: 205540 | P4: 45931 | Q4: C10-11
A5: C10-11-1 | B5: 加工金額 | C5: 0 | D5: 0 | E5: 6800 | F5: 10400 | G5: 0 | H5: 12000 | I5: 0 | J5: 0 | K5: 0 | L5: 0 | M5: 29200 | N5: 58400 | P5: 45931 | Q5: C10-11
A6: C10-12 | B6: 加工金額 | C6: 0 | D6: 0 | E6: 40800 | F6: 31200 | G6: 0 | H6: 0 | I6: 0 | J6: 0 | K6: 0 | L6: 0 | M6: 72000 | N6: 144000 | P6: 45931 | Q6: C10-12
A7: C10-13 | B7: 加工金額 | C7: 0 | D7: 0 | E7: 0 | F7: 213200 | G7: 0 | H7: 0 | I7: 0 | J7: 0 | K7: 0 | L7: 0 | M7: 213200 | N7: 426400 | P7: 45931 | Q7: C10-13
A8: C10-13-1 | B8: 加工金額 | C8: 0 | D8: 0 | E8: 0 | F8: 41600 | G8: 0 | H8: 48000 | I8: 0 | J8: 0 | K8: 0 | L8: 0 | M8: 89600 | N8: 179200 | P8: 45931 | Q8: C10-13
A9: C10-14 | B9: 加工金額 | C9: 0 | D9: 0 | E9: 0 | F9: 0 | G9: 0 | H9: 0 | I9: 0 | J9: 0 | K9: 0 | L9: 0 | M9: 0 | N9: 0 | P9: 45931 | Q9: C10-14
A10: C10-14-1 | B10: 加工金額 | C10: 0 | D10: 0 | E10: 0 | F10: 41600 | G10: 0 | H10: 48000 | I10: 0 | J10: 0 | K10: 0 | L10: 0 | M10: 89600 | N10: 179200 | P10: 45931 | Q10: C10-14
A11: C10-15 | B11: 加工金額 | C11: 0 | D11: 0 | E11: 81600 | F11: 62400 | G11: 0 | H11: 0 | I11: 0 | J11: 0 | K11: 0 | L11: 0 | M11: 144000 | N11: 288000 | P11: 45931 | Q11: C10-15
A12: C10-16 | B12: 加工金額 | C12: 0 | D12: 0 | E12: 13608 | F12: 31200 | G12: 0 | H12: 0 | I12: 0 | J12: 0 | K12: 0 | L12: 0 | M12: 44808 | N12: 89616 | P12: 45931 | Q12: C10-16
A13: C10-17 | B13: 加工金額 | C13: 0 | D13: 0 | E13: 34000 | F13: 26000 | G13: 0 | H13: 0 | I13: 0 | J13: 0 | K13: 0 | L13: 0 | M13: 60000 | N13: 120000 | P13: 45931 | Q13: C10-17
... A131: W9-22 | B131: 加工金額 | C131: 0 | D131: 10800 | E131: 0 | F131: 0 | G131: 0 | H131: 0 | I131: 0 | J131: 0 | K131: 0 | L131: 0 | M131: 10800 | N131: 21600 | P131: 45931 | Q131: W9-22

Sheet 月次実績表
A1: Date modified | B1: 依頼NO | C1: 依頼NO(-1除外) | D1: 項目 | E1: スライス | F1: EC | G1: スリット | H1: SEC | I1: 分割 | J1: 接続 | K1: 巻返し | L1: エンボス | M1: 改装 | N1: 欠点表示 | O1: 検査 | P1: 梱包 | Q1: --合計-- | R1: 年月 | S1: 依頼NO_年月
A2: 46260.665 | B2: C8-1 | C2: C8-1 | D2: 加工金額 | E2: 0 | F2: 0 | G2: 0 | H2: 207922 | I2: 0 | J2: 0 | K2: 0 | L2: 0 | M2: 0 | O2: 0 | P2: 0 | Q2: 207922 | R2: 46235 | S2: C8-1-202608
A3: 46260.665 | B3: C8-13 | C3: C8-13 | D3: 加工金額 | E3: 0 | F3: 0 | G3: 33507 | H3: 51246 | I3: 0 | J3: 0 | K3: 0 | L3: 0 | M3: 0 | O3: 0 | P3: 0 | Q3: 84753 | R3: 46235 | S3: C8-13-202608
A4: 46260.665 | B4: C8-14 | C4: C8-14 | D4: 加工金額 | E4: 0 | F4: 0 | G4: 6800 | H4: 5200 | I4: 0 | J4: 0 | K4: 0 | L4: 0 | M4: 0 | O4: 0 | P4: 0 | Q4: 12000 | R4: 46235 | S4: C8-14-202608
A5: 46260.665 | B5: C8-15 | C5: C8-15 | D5: 加工金額 | E5: 0 | F5: 0 | G5: 0 | H5: 104000 | I5: 0 | J5: 120000 | K5: 0 | L5: 0 | M5: 0 | O5: 0 | P5: 0 | Q5: 224000 | R5: 46235 | S5: C8-15-202608
A6: 46260.665 | B6: C8-16 | C6: C8-16 | D6: 加工金額 | E6: 0 | F6: 0 | G6: 0 | H6: 104000 | I6: 0 | J6: 0 | K6: 0 | L6: 0 | M6: 0 | O6: 0 | P6: 0 | Q6: 104000 | R6: 46235 | S6: C8-16-202608
A7: 46260.665 | B7: C8-17 | C7: C8-17 | D7: 加工金額 | E7: 0 | F7: 0 | G7: 0 | H7: 20800 | I7: 0 | J7: 24000 | K7: 0 | L7: 0 | M7: 0 | O7: 0 | P7: 0 | Q7: 44800 | R7: 46235 | S7: C8-17-202608
A8: 46260.665 | B8: C8-2 | C8: C8-2 | D8: 加工金額 | E8: 0 | F8: 0 | G8: 0 | H8: 130000 | I8: 0 | J8: 0 | K8: 0 | L8: 0 | M8: 0 | O8: 0 | P8: 0 | Q8: 130000 | R8: 46235 | S8: C8-2-202608
A9: 46260.665 | B9: C8-3 | C9: C8-3 | D9: 加工金額 | E9: 0 | F9: 0 | G9: 0 | H9: 254800 | I9: 0 | J9: 0 | K9: 0 | L9: 0 | M9: 0 | O9: 0 | P9: 0 | Q9: 254800 | R9: 46235 | S9: C8-3-202608
A10: 46260.665 | B10: C8-3-1 | C10: C8-3 | D10: 加工金額 | E10: 0 | F10: 0 | G10: 6800 | H10: 5200 | I10: 0 | J10: 0 | K10: 0 | L10: 0 | M10: 0 | O10: 0 | P10: 0 | Q10: 12000 | R10: 46235 | S10: C8-3-1-202608
A11: 46260.665 | B11: C8-4 | C11: C8-4 | D11: 加工金額 | E11: 0 | F11: 0 | G11: 0 | H11: 260000 | I11: 0 | J11: 0 | K11: 0 | L11: 0 | M11: 0 | O11: 0 | P11: 0 | Q11: 260000 | R11: 46235 | S11: C8-4-202608
A12: 46260.665 | B12: C8-5 | C12: C8-5 | D12: 加工金額 | E12: 0 | F12: 0 | G12: 0 | H12: 82862 | I12: 0 | J12: 0 | K12: 0 | L12: 0 | M12: 0 | O12: 0 | P12: 0 | Q12: 82862 | R12: 46235 | S12: C8-5-202608
A13: 46260.665 | B13: C8-6 | C13: C8-6 | D13: 加工金額 | E13: 4246 | F13: 0 | G13: 0 | H13: 0 | I13: 0 | J13: 0 | K13: 0 | L13: 0 | M13: 0 | O13: 0 | P13: 0 | Q13: 4246 | R13: 46235 | S13: C8-6-202608
... A64: 46260.665 | B64: PN08-05 | C64: PN08-05 | D64: 加工金額 | E64: 0 | F64: 36000 | G64: 0 | H64: 0 | I64: 0 | J64: 0 | K64: 0 | L64: 0 | M64: 0 | O64: 0 | P64: 3200 | Q64: 39200 | R64: 46235 | S64: PN08-05-202608
A65: 46268.397 | B65: C9-1 | C65: C9-1 | D65: 加工金額 | E65: 0 | F65: 0 | G65: 0 | H65: 220000 | K65: 0 | P65: 0 | Q65: 220000
A66: 46268.397 | B66: E9-1 | C66: E9-1 | D66: 加工金額 | E66: 0 | F66: 22500 | G66: 0 | H66: 0 | K66: 16250 | P66: 0 | Q66: 38750
A67: 46268.397 | B67: Y9-1 | C67: Y9-1 | D67: 加工金額 | E67: 54000 | F67: 0 | G67: 10500 | H67: 0 | K67: 0 | P67: 0 | Q67: 64500
A68: 46268.397 | B68: GB60802 | C68: GB60802 | D68: 加工金額 | E68: 9102 | F68: 0 | G68: 0 | H68: 0 | K68: 0 | P68: 0 | Q68: 9102
A69: 46268.397 | B69: GB60804 | C69: GB60804 | D69: 加工金額 | E69: 2275 | F69: 0 | G69: 0 | H69: 0 | K69: 0 | P69: 0 | Q69: 2275
A70: 46268.397 | B70: JR260901 | C70: JR260901 | D70: 加工金額 | E70: 0 | F70: 0 | G70: 16150 | H70: 24700 | K70: 0 | P70: 1600 | Q70: 42450

Sheet 月次実績表_PIVOT
A1: 売上表 | R1: 構成比率
A2: 単位:千円 | H2: * | J2: * | L2: * | M2: * | N2: ↓*印の合計 | Y2: * | AA2: * | AC2: * | AD2: *
A3: 年月 | B3: _スライス | C3: _EC | D3: _スリット | E3: _SEC | F3: _分割 | G3: _接続 | H3: _巻返し | I3: _エンボス | J3: _改装 | K3: _欠点表示 | L3: _検査 | M3: _梱包 | N3: その他(*) | O3: 合計 | R3: 年月 | S3: _スライス | T3: _EC | U3: _スリット | V3: _SEC | W3: _分割 | X3: _接続 | Y3: _巻返し | Z3: _エンボス | AA3: _改装 | AB3: _欠点表示 | AC3: _検査 | AD3: _梱包 | AE3: その他(*)
A4: 46235 | B4: 64306 | C4: 1197648 | D4: 200562.95 | E4: 1346371 | F4: 78915 | G4: 233400.27 | H4: 3900 | I4: 95081 | J4: 6000 | L4: 996000 | M4: 18240 | N4: =H4+J4+L4+M4 -> 1024140 | O4: =SUM(B4:M4) -> 4240424.2 | R4: =A4 -> 46235 | S4: =B4/$O4 -> 0.015164992 | T4: =C4/$O4 -> 0.28243589 | U4: =D4/$O4 -> 0.04729785 | V4: =E4/$O4 -> 0.31750856 | W4: =F4/$O4 -> 0.018610166 | X4: =G4/$O4 -> 0.055041726 | Y4: =H4/$O4 -> 0.0009197193 | Z4: =I4/$O4 -> 0.022422521 | ... AE4: =N4/$O4 -> 0.24151829
N5: =H5+J5+L5+M5 -> 0 | O5: =SUM(B5:M5) -> 0 | R5: =A5 -> 0 | S5: =B5/$O5 -> #DIV/0! | T5: =C5/$O5 -> #DIV/0! | U5: =D5/$O5 -> #DIV/0! | V5: =E5/$O5 -> #DIV/0! | W5: =F5/$O5 -> #DIV/0! | X5: =G5/$O5 -> #DIV/0! | Y5: =H5/$O5 -> #DIV/0! | Z5: =I5/$O5 -> #DIV/0! | ... AE5: =N5/$O5 -> #DIV/0!
N6: =H6+J6+L6+M6 -> 0 | O6: =SUM(B6:M6) -> 0 | R6: =A6 -> 0 | S6: =B6/$O6 -> #DIV/0! | T6: =C6/$O6 -> #DIV/0! | U6: =D6/$O6 -> #DIV/0! | V6: =E6/$O6 -> #DIV/0! | W6: =F6/$O6 -> #DIV/0! | X6: =G6/$O6 -> #DIV/0! | Y6: =H6/$O6 -> #DIV/0! | Z6: =I6/$O6 -> #DIV/0! | ... AE6: =N6/$O6 -> #DIV/0!
N7: =H7+J7+L7+M7 -> 0 | O7: =SUM(B7:M7) -> 0 | R7: =A7 -> 0 | S7: =B7/$O7 -> #DIV/0! | T7: =C7/$O7 -> #DIV/0! | U7: =D7/$O7 -> #DIV/0! | V7: =E7/$O7 -> #DIV/0! | W7: =F7/$O7 -> #DIV/0! | X7: =G7/$O7 -> #DIV/0! | Y7: =H7/$O7 -> #DIV/0! | Z7: =I7/$O7 -> #DIV/0! | ... AE7: =N7/$O7 -> #DIV/0!
N8: =H8+J8+L8+M8 -> 0 | O8: =SUM(B8:M8) -> 0 | R8: =A8 -> 0 | S8: =B8/$O8 -> #DIV/0! | T8: =C8/$O8 -> #DIV/0! | U8: =D8/$O8 -> #DIV/0! | V8: =E8/$O8 -> #DIV/0! | W8: =F8/$O8 -> #DIV/0! | X8: =G8/$O8 -> #DIV/0! | Y8: =H8/$O8 -> #DIV/0! | Z8: =I8/$O8 -> #DIV/0! | ... AE8: =N8/$O8 -> #DIV/0!
N9: =H9+J9+L9+M9 -> 0 | O9: =SUM(B9:M9) -> 0 | R9: =A9 -> 0 | S9: =B9/$O9 -> #DIV/0! | T9: =C9/$O9 -> #DIV/0! | U9: =D9/$O9 -> #DIV/0! | V9: =E9/$O9 -> #DIV/0! | W9: =F9/$O9 -> #DIV/0! | X9: =G9/$O9 -> #DIV/0! | Y9: =H9/$O9 -> #DIV/0! | Z9: =I9/$O9 -> #DIV/0! | ... AE9: =N9/$O9 -> #DIV/0!
N10: =H10+J10+L10+M10 -> 0 | O10: =SUM(B10:M10) -> 0 | R10: =A10 -> 0 | S10: =B10/$O10 -> #DIV/0! | T10: =C10/$O10 -> #DIV/0! | U10: =D10/$O10 -> #DIV/0! | V10: =E10/$O10 -> #DIV/0! | W10: =F10/$O10 -> #DIV/0! | X10: =G10/$O10 -> #DIV/0! | Y10: =H10/$O10 -> #DIV/0! | Z10: =I10/$O10 -> #DIV/0! | ... AE10: =N10/$O10 -> #DIV/0!
N11: =H11+J11+L11+M11 -> 0 | O11: =SUM(B11:M11) -> 0 | R11: =A11 -> 0 | S11: =B11/$O11 -> #DIV/0! | T11: =C11/$O11 -> #DIV/0! | U11: =D11/$O11 -> #DIV/0! | V11: =E11/$O11 -> #DIV/0! | W11: =F11/$O11 -> #DIV/0! | X11: =G11/$O11 -> #DIV/0! | Y11: =H11/$O11 -> #DIV/0! | Z11: =I11/$O11 -> #DIV/0! | ... AE11: =N11/$O11 -> #DIV/0!
N12: =H12+J12+L12+M12 -> 0 | O12: =SUM(B12:M12) -> 0 | R12: =A12 -> 0 | S12: =B12/$O12 -> #DIV/0! | T12: =C12/$O12 -> #DIV/0! | U12: =D12/$O12 -> #DIV/0! | V12: =E12/$O12 -> #DIV/0! | W12: =F12/$O12 -> #DIV/0! | X12: =G12/$O12 -> #DIV/0! | Y12: =H12/$O12 -> #DIV/0! | Z12: =I12/$O12 -> #DIV/0! | ... AE12: =N12/$O12 -> #DIV/0!
N13: =H13+J13+L13+M13 -> 0 | O13: =SUM(B13:M13) -> 0 | R13: =A13 -> 0 | S13: =B13/$O13 -> #DIV/0! | T13: =C13/$O13 -> #DIV/0! | U13: =D13/$O13 -> #DIV/0! | V13: =E13/$O13 -> #DIV/0! | W13: =F13/$O13 -> #DIV/0! | X13: =G13/$O13 -> #DIV/0! | Y13: =H13/$O13 -> #DIV/0! | Z13: =I13/$O13 -> #DIV/0! | ... AE13: =N13/$O13 -> #DIV/0!
N14: =H14+J14+L14+M14 -> 0 | O14: =SUM(B14:M14) -> 0 | R14: =A14 -> 0 | S14: =B14/$O14 -> #DIV/0! | T14: =C14/$O14 -> #DIV/0! | U14: =D14/$O14 -> #DIV/0! | V14: =E14/$O14 -> #DIV/0! | W14: =F14/$O14 -> #DIV/0! | X14: =G14/$O14 -> #DIV/0! | Y14: =H14/$O14 -> #DIV/0! | Z14: =I14/$O14 -> #DIV/0! | ... AE14: =N14/$O14 -> #DIV/0!
N15: =H15+J15+L15+M15 -> 0 | O15: =SUM(B15:M15) -> 0 | R15: =A15 -> 0 | S15: =B15/$O15 -> #DIV/0! | T15: =C15/$O15 -> #DIV/0! | U15: =D15/$O15 -> #DIV/0! | V15: =E15/$O15 -> #DIV/0! | W15: =F15/$O15 -> #DIV/0! | X15: =G15/$O15 -> #DIV/0! | Y15: =H15/$O15 -> #DIV/0! | Z15: =I15/$O15 -> #DIV/0! | ... AE15: =N15/$O15 -> #DIV/0!
N16: =H16+J16+L16+M16 -> 0 | O16: =SUM(B16:M16) -> 0 | R16: =A16 -> 0 | S16: =B16/$O16 -> #DIV/0! | T16: =C16/$O16 -> #DIV/0! | U16: =D16/$O16 -> #DIV/0! | V16: =E16/$O16 -> #DIV/0! | W16: =F16/$O16 -> #DIV/0! | X16: =G16/$O16 -> #DIV/0! | Y16: =H16/$O16 -> #DIV/0! | Z16: =I16/$O16 -> #DIV/0! | ... AE16: =N16/$O16 -> #DIV/0!
N17: =H17+J17+L17+M17 -> 0 | O17: =SUM(B17:M17) -> 0 | R17: =A17 -> 0 | S17: =B17/$O17 -> #DIV/0! | T17: =C17/$O17 -> #DIV/0! | U17: =D17/$O17 -> #DIV/0! | V17: =E17/$O17 -> #DIV/0! | W17: =F17/$O17 -> #DIV/0! | X17: =G17/$O17 -> #DIV/0! | Y17: =H17/$O17 -> #DIV/0! | Z17: =I17/$O17 -> #DIV/0! | ... AE17: =N17/$O17 -> #DIV/0!

Sheet _t受注ﾌｧｲﾙ_総合計
A1: 依頼Ｎｏ | B1: 加工内容 | C1: 調整納期 | D1: 受注数 | E1: 受注金額(修正) | F1: 加工完了日 | G1: 加工計画(完了日) | H1: 集計日 | I1: 加工金額合計(月次実績) | J1: 加工金額 | K1: 加工完了金額 | L1: TPI2 | M1: 東レ | N1: 工程1 | O1: 工程2 | P1: 工程3 | Q1: 工程4 | R1: 工程5
A2: W7-4 | B2: EC,検査 | C2: 46225 | D2: 1200 | E2: 45600 | F2: {=_xlfn.LET( _xlpm._完了日,_加工実績DATA[加工完了日], _xlpm._調整納期列,_t受注ﾌｧｲﾙ_総合計[調整納期], _xlpm._加工完了日,_xlfn.TAKE( _xlfn._xlws.FILTER(_xlpm._完了日, (A2=_加工実績DATA[依頼NO])* (YEAR(C2) = YEAR(_xlpm._完了日)) ),1), IF(_xlpm._加工完了日 = 0,NA(),_xlpm._加工完了日) )} -> 46227 | G2: {=_xlfn.LET( _xlpm._完了日列,#REF!, _xlpm._完了日, _xlfn.TAKE( _xlfn._xlws.FILTER(_xlpm._完了日列, (A2=#REF!)* (DATEVALUE("2025/1/1") < C2) ),1 ), IFERROR(_xlpm._完了日,"") )} | H2: {=_xlfn.LET( _xlpm.f, IFERROR(F2, 0), _xlpm.g, IFERROR(G2, 0), _xlpm.c, IFERROR(C2, 0), _xlfn.IFS( ISNUMBER(_xlpm.f)*(_xlpm.f>0), _xlpm.f, ISNUMBER(_xlpm.g)*(_xlpm.g>0), _xlpm.g, ISNUMBER(_xlpm.c)*(_xlpm.c>0), _xlpm.c, TRUE, "" ) )} -> 46227 | I2: {=_xlfn.LET( _xlpm._加工金額合計列,_t月次実績表[--合計--], _xlpm._月次年月日列,_t月次実績表[年月], _xlpm._依頼NO列,_t月次実績表[依頼NO(-1除外)], IFERROR( SUM( _xlfn._xlws.FILTER(_xlpm._加工金額合計列, (A2=_xlpm._依頼NO列) * (YEAR(_xlpm._月次年月日列) = YEAR(H2)) ) ), 0) )} -> 0 | J2: =IFERROR( IF( _t受注ﾌｧｲﾙ_総合計[[#This Row],[受注金額(修正)]] > _t受注ﾌｧｲﾙ_総合計[[#This Row],[加工金額合計(月次実績)]], _t受注ﾌｧｲﾙ_総合計[[#This Row],[受注金額(修正)]], _t受注ﾌｧｲﾙ_総合計[[#This Row],[加工金額合計(月次実績)]] ), 0 ) -> 45600 | K2: =IF(ISERROR(F2),0,E2) -> 45600 | L2: =_xlfn.LET( _xlpm._依頼NO, A2, _xlpm._集計年, YEAR(H2), _xlpm._依頼列, _t受注ﾌｧｲﾙ_TPI[依頼Ｎｏ], _xlpm._集計日列, _t受注ﾌｧｲﾙ_TPI[集計日], COUNTIFS( _xlpm._依頼列, _xlpm._依頼NO, _xlpm._集計日列, ">=" & DATE(_xlpm._集計年,1,1), _xlpm._集計日列, "<" & DATE(_xlpm._集計年+1,1,1) ) ) -> 0 | M2: =_xlfn.LET( _xlpm._依頼NO, A2, _xlpm._集計年, YEAR(H2), _xlpm._依頼列,_t受注ﾌｧｲﾙ_東レ[依頼Ｎｏ], _xlpm._集計日列, _t受注ﾌｧｲﾙ_東レ[集計日], COUNTIFS( _xlpm._依頼列, _xlpm._依頼NO, _xlpm._集計日列, ">=" & DATE(_xlpm._集計年,1,1), _xlpm._集計日列, "<" & DATE(_xlpm._集計年+1,1,1) ) ) -> 1 | N2: =IFERROR( INDEX( _xlfn.TEXTSPLIT( SUBSTITUTE(SUBSTITUTE(B2, "，", ","), "、", ","), ",", ), 1, 1 ), "" ) -> EC | O2: =IFERROR( INDEX( _xlfn.TEXTSPLIT( SUBSTITUTE(SUBSTITUTE(B2, "，", ","), "、", ","), ",", ), 1, 2 ), "" ) -> 検査 | P2: =IFERROR( INDEX( _xlfn.TEXTSPLIT( SUBSTITUTE(SUBSTITUTE(B2, "，", ","), "、", ","), ",", ), 1, 3 ), "" ) | Q2: =IFERROR( INDEX( _xlfn.TEXTSPLIT( SUBSTITUTE(SUBSTITUTE(B2, "，", ","), "、", ","), ",", ), 1, 4 ), "" ) | R2: =IFERROR( INDEX( _xlfn.TEXTSPLIT( SUBSTITUTE(SUBSTITUTE(B2, "，", ","), "、", ","), ",", ), 1, 5 ), "" )
A3: W7-5 | B3: EC,検査 | C3: 46221 | D3: 3300 | E3: 125400 | F3: {=_xlfn.LET( _xlpm._完了日,_加工実績DATA[加工完了日], _xlpm._調整納期列,_t受注ﾌｧｲﾙ_総合計[調整納期], _xlpm._加工完了日,_xlfn.TAKE( _xlfn._xlws.FILTER(_xlpm._完了日, (A3=_加工実績DATA[依頼NO])* (YEAR(C3) = YEAR(_xlpm._完了日)) ),1), IF(_xlpm._加工完了日 = 0,NA(),_xlpm._加工完了日) )} -> 46227 | G3: {=_xlfn.LET( _xlpm._完了日列,#REF!, _xlpm._完了日, _xlfn.TAKE( _xlfn._xlws.FILTER(_xlpm._完了日列, (A3=#REF!)* (DATEVALUE("2025/1/1") < C3) ),1 ), IFERROR(_xlpm._完了日,"") )} | H3: {=_xlfn.LET( _xlpm.f, IFERROR(F3, 0), _xlpm.g, IFERROR(G3, 0), _xlpm.c, IFERROR(C3, 0), _xlfn.IFS( ISNUMBER(_xlpm.f)*(_xlpm.f>0), _xlpm.f, ISNUMBER(_xlpm.g)*(_xlpm.g>0), _xlpm.g, ISNUMBER(_xlpm.c)*(_xlpm.c>0), _xlpm.c, TRUE, "" ) )} -> 46227 | I3: {=_xlfn.LET( _xlpm._加工金額合計列,_t月次実績表[--合計--], _xlpm._月次年月日列,_t月次実績表[年月], _xlpm._依頼NO列,_t月次実績表[依頼NO(-1除外)], IFERROR( SUM( _xlfn._xlws.FILTER(_xlpm._加工金額合計列, (A3=_xlpm._依頼NO列) * (YEAR(_xlpm._月次年月日列) = YEAR(H3)) ) ), 0) )} -> 0 | J3: =IFERROR( IF( _t受注ﾌｧｲﾙ_総合計[[#This Row],[受注金額(修正)]] > _t受注ﾌｧｲﾙ_総合計[[#This Row],[加工金額合計(月次実績)]], _t受注ﾌｧｲﾙ_総合計[[#This Row],[受注金額(修正)]], _t受注ﾌｧｲﾙ_総合計[[#This Row],[加工金額合計(月次実績)]] ), 0 ) -> 125400 | K3: =IF(ISERROR(F3),0,E3) -> 125400 | L3: =_xlfn.LET( _xlpm._依頼NO, A3, _xlpm._集計年, YEAR(H3), _xlpm._依頼列, _t受注ﾌｧｲﾙ_TPI[依頼Ｎｏ], _xlpm._集計日列, _t受注ﾌｧｲﾙ_TPI[集計日], COUNTIFS( _xlpm._依頼列, _xlpm._依頼NO, _xlpm._集計日列, ">=" & DATE(_xlpm._集計年,1,1), _xlpm._集計日列, "<" & DATE(_xlpm._集計年+1,1,1) ) ) -> 0 | M3: =_xlfn.LET( _xlpm._依頼NO, A3, _xlpm._集計年, YEAR(H3), _xlpm._依頼列,_t受注ﾌｧｲﾙ_東レ[依頼Ｎｏ], _xlpm._集計日列, _t受注ﾌｧｲﾙ_東レ[集計日], COUNTIFS( _xlpm._依頼列, _xlpm._依頼NO, _xlpm._集計日列, ">=" & DATE(_xlpm._集計年,1,1), _xlpm._集計日列, "<" & DATE(_xlpm._集計年+1,1,1) ) ) -> 1 | N3: =IFERROR( INDEX( _xlfn.TEXTSPLIT( SUBSTITUTE(SUBSTITUTE(B3, "，", ","), "、", ","), ",", ), 1, 1 ), "" ) -> EC | O3: =IFERROR( INDEX( _xlfn.TEXTSPLIT( SUBSTITUTE(SUBSTITUTE(B3, "，", ","), "、", ","), ",", ), 1, 2 ), "" ) -> 検査 | P3: =IFERROR( INDEX( _xlfn.TEXTSPLIT( SUBSTITUTE(SUBSTITUTE(B3, "，", ","), "、", ","), ",", ), 1, 3 ), "" ) | Q3: =IFERROR( INDEX( _xlfn.TEXTSPLIT( SUBSTITUTE(SUBSTITUTE(B3, "，", ","), "、", ","), ",", ), 1, 4 ), "" ) | R3: =IFERROR( INDEX( _xlfn.TEXTSPLIT( SUBSTITUTE(SUBSTITUTE(B3, "，", ","), "、", ","), ",", ), 1, 5 ), "" )
A4: JR260701 | B4: SEC,ｽﾘｯﾄ | C4: 46211 | D4: 1940 | E4: 83420 | F4: {=_xlfn.LET( _xlpm._完了日,_加工実績DATA[加工完了日], _xlpm._調整納期列,_t受注ﾌｧｲﾙ_総合計[調整納期], _xlpm._加工完了日,_xlfn.TAKE( _xlfn._xlws.FILTER(_xlpm._完了日, (A4=_加工実績DATA[依頼NO])* (YEAR(C4) = YEAR(_xlpm._完了日)) ),1), IF(_xlpm._加工完了日 = 0,NA(),_xlpm._加工完了日) )} -> 46206 | G4: {=_xlfn.LET( _xlpm._完了日列,#REF!, _xlpm._完了日, _xlfn.TAKE( _xlfn._xlws.FILTER(_xlpm._完了日列, (A4=#REF!)* (DATEVALUE("2025/1/1") < C4) ),1 ), IFERROR(_xlpm._完了日,"") )} | H4: {=_xlfn.LET( _xlpm.f, IFERROR(F4, 0), _xlpm.g, IFERROR(G4, 0), _xlpm.c, IFERROR(C4, 0), _xlfn.IFS( ISNUMBER(_xlpm.f)*(_xlpm.f>0), _xlpm.f, ISNUMBER(_xlpm.g)*(_xlpm.g>0), _xlpm.g, ISNUMBER(_xlpm.c)*(_xlpm.c>0), _xlpm.c, TRUE, "" ) )} -> 46206 | I4: {=_xlfn.LET( _xlpm._加工金額合計列,_t月次実績表[--合計--], _xlpm._月次年月日列,_t月次実績表[年月], _xlpm._依頼NO列,_t月次実績表[依頼NO(-1除外)], IFERROR( SUM( _xlfn._xlws.FILTER(_xlpm._加工金額合計列, (A4=_xlpm._依頼NO列) * (YEAR(_xlpm._月次年月日列) = YEAR(H4)) ) ), 0) )} -> 0 | J4: =IFERROR( IF( _t受注ﾌｧｲﾙ_総合計[[#This Row],[受注金額(修正)]] > _t受注ﾌｧｲﾙ_総合計[[#This Row],[加工金額合計(月次実績)]], _t受注ﾌｧｲﾙ_総合計[[#This Row],[受注金額(修正)]], _t受注ﾌｧｲﾙ_総合計[[#This Row],[加工金額合計(月次実績)]] ), 0 ) -> 83420 | K4: =IF(ISERROR(F4),0,E4) -> 83420 | L4: =_xlfn.LET( _xlpm._依頼NO, A4, _xlpm._集計年, YEAR(H4), _xlpm._依頼列, _t受注ﾌｧｲﾙ_TPI[依頼Ｎｏ], _xlpm._集計日列, _t受注ﾌｧｲﾙ_TPI[集計日], COUNTIFS( _xlpm._依頼列, _xlpm._依頼NO, _xlpm._集計日列, ">=" & DATE(_xlpm._集計年,1,1), _xlpm._集計日列, "<" & DATE(_xlpm._集計年+1,1,1) ) ) -> 1 | M4: =_xlfn.LET( _xlpm._依頼NO, A4, _xlpm._集計年, YEAR(H4), _xlpm._依頼列,_t受注ﾌｧｲﾙ_東レ[依頼Ｎｏ], _xlpm._集計日列, _t受注ﾌｧｲﾙ_東レ[集計日], COUNTIFS( _xlpm._依頼列, _xlpm._依頼NO, _xlpm._集計日列, ">=" & DATE(_xlpm._集計年,1,1), _xlpm._集計日列, "<" & DATE(_xlpm._集計年+1,1,1) ) ) -> 0 | N4: =IFERROR( INDEX( _xlfn.TEXTSPLIT( SUBSTITUTE(SUBSTITUTE(B4, "，", ","), "、", ","), ",", ), 1, 1 ), "" ) -> SEC | O4: =IFERROR( INDEX( _xlfn.TEXTSPLIT( SUBSTITUTE(SUBSTITUTE(B4, "，", ","), "、", ","), ",", ), 1, 2 ), "" ) -> ｽﾘｯﾄ | P4: =IFERROR( INDEX( _xlfn.TEXTSPLIT( SUBSTITUTE(SUBSTITUTE(B4, "，", ","), "、", ","), ",", ), 1, 3 ), "" ) | Q4: =IFERROR( INDEX( _xlfn.TEXTSPLIT( SUBSTITUTE(SUBSTITUTE(B4, "，", ","), "、", ","), ",", ), 1, 4 ), "" ) | R4: =IFERROR( INDEX( _xlfn.TEXTSPLIT( SUBSTITUTE(SUBSTITUTE(B4, "，", ","), "、", ","), ",", ), 1, 5 ), "" )
A5: Y7-1 | B5: ｽﾗｲｽ | C5: 46212 | D5: 6000 | E5: 66000 | F5: {=_xlfn.LET( _xlpm._完了日,_加工実績DATA[加工完了日], _xlpm._調整納期列,_t受注ﾌｧｲﾙ_総合計[調整納期], _xlpm._加工完了日,_xlfn.TAKE( _xlfn._xlws.FILTER(_xlpm._完了日, (A5=_加工実績DATA[依頼NO])* (YEAR(C5) = YEAR(_xlpm._完了日)) ),1), IF(_xlpm._加工完了日 = 0,NA(),_xlpm._加工完了日) )} -> 46205 | G5: {=_xlfn.LET( _xlpm._完了日列,#REF!, _xlpm._完了日, _xlfn.TAKE( _xlfn._xlws.FILTER(_xlpm._完了日列, (A5=#REF!)* (DATEVALUE("2025/1/1") < C5) ),1 ), IFERROR(_xlpm._完了日,"") )} | H5: {=_xlfn.LET( _xlpm.f, IFERROR(F5, 0), _xlpm.g, IFERROR(G5, 0), _xlpm.c, IFERROR(C5, 0), _xlfn.IFS( ISNUMBER(_xlpm.f)*(_xlpm.f>0), _xlpm.f, ISNUMBER(_xlpm.g)*(_xlpm.g>0), _xlpm.g, ISNUMBER(_xlpm.c)*(_xlpm.c>0), _xlpm.c, TRUE, "" ) )} -> 46205 | I5: {=_xlfn.LET( _xlpm._加工金額合計列,_t月次実績表[--合計--], _xlpm._月次年月日列,_t月次実績表[年月], _xlpm._依頼NO列,_t月次実績表[依頼NO(-1除外)], IFERROR( SUM( _xlfn._xlws.FILTER(_xlpm._加工金額合計列, (A5=_xlpm._依頼NO列) * (YEAR(_xlpm._月次年月日列) = YEAR(H5)) ) ), 0) )} -> 0 | J5: =IFERROR( IF( _t受注ﾌｧｲﾙ_総合計[[#This Row],[受注金額(修正)]] > _t受注ﾌｧｲﾙ_総合計[[#This Row],[加工金額合計(月次実績)]], _t受注ﾌｧｲﾙ_総合計[[#This Row],[受注金額(修正)]], _t受注ﾌｧｲﾙ_総合計[[#This Row],[加工金額合計(月次実績)]] ), 0 ) -> 66000 | K5: =IF(ISERROR(F5),0,E5) -> 66000 | L5: =_xlfn.LET( _xlpm._依頼NO, A5, _xlpm._集計年, YEAR(H5), _xlpm._依頼列, _t受注ﾌｧｲﾙ_TPI[依頼Ｎｏ], _xlpm._集計日列, _t受注ﾌｧｲﾙ_TPI[集計日], COUNTIFS( _xlpm._依頼列, _xlpm._依頼NO, _xlpm._集計日列, ">=" & DATE(_xlpm._集計年,1,1), _xlpm._集計日列, "<" & DATE(_xlpm._集計年+1,1,1) ) ) -> 0 | M5: =_xlfn.LET( _xlpm._依頼NO, A5, _xlpm._集計年, YEAR(H5), _xlpm._依頼列,_t受注ﾌｧｲﾙ_東レ[依頼Ｎｏ], _xlpm._集計日列, _t受注ﾌｧｲﾙ_東レ[集計日], COUNTIFS( _xlpm._依頼列, _xlpm._依頼NO, _xlpm._集計日列, ">=" & DATE(_xlpm._集計年,1,1), _xlpm._集計日列, "<" & DATE(_xlpm._集計年+1,1,1) ) ) -> 1 | N5: =IFERROR( INDEX( _xlfn.TEXTSPLIT( SUBSTITUTE(SUBSTITUTE(B5, "，", ","), "、", ","), ",", ), 1, 1 ), "" ) -> ｽﾗｲｽ | O5: =IFERROR( INDEX( _xlfn.TEXTSPLIT( SUBSTITUTE(SUBSTITUTE(B5, "，", ","), "、", ","), ",", ), 1, 2 ), "" ) | P5: =IFERROR( INDEX( _xlfn.TEXTSPLIT( SUBSTITUTE(SUBSTITUTE(B5, "，", ","), "、", ","), ",", ), 1, 3 ), "" ) | Q5: =IFERROR( INDEX( _xlfn.TEXTSPLIT( SUBSTITUTE(SUBSTITUTE(B5, "，", ","), "、", ","), ",", ), 1, 4 ), "" ) | R5: =IFERROR( INDEX( _xlfn.TEXTSPLIT( SUBSTITUTE(SUBSTITUTE(B5, "，", ","), "、", ","), ",", ), 1, 5 ), "" )
A6: Y7-2 | B6: SEC,ｽﾘｯﾄ | C6: 46211 | D6: 1600 | E6: 16000 | F6: {=_xlfn.LET( _xlpm._完了日,_加工実績DATA[加工完了日], _xlpm._調整納期列,_t受注ﾌｧｲﾙ_総合計[調整納期], _xlpm._加工完了日,_xlfn.TAKE( _xlfn._xlws.FILTER(_xlpm._完了日, (A6=_加工実績DATA[依頼NO])* (YEAR(C6) = YEAR(_xlpm._完了日)) ),1), IF(_xlpm._加工完了日 = 0,NA(),_xlpm._加工完了日) )} -> 46209 | G6: {=_xlfn.LET( _xlpm._完了日列,#REF!, _xlpm._完了日, _xlfn.TAKE( _xlfn._xlws.FILTER(_xlpm._完了日列, (A6=#REF!)* (DATEVALUE("2025/1/1") < C6) ),1 ), IFERROR(_xlpm._完了日,"") )} | H6: {=_xlfn.LET( _xlpm.f, IFERROR(F6, 0), _xlpm.g, IFERROR(G6, 0), _xlpm.c, IFERROR(C6, 0), _xlfn.IFS( ISNUMBER(_xlpm.f)*(_xlpm.f>0), _xlpm.f, ISNUMBER(_xlpm.g)*(_xlpm.g>0), _xlpm.g, ISNUMBER(_xlpm.c)*(_xlpm.c>0), _xlpm.c, TRUE, "" ) )} -> 46209 | I6: {=_xlfn.LET( _xlpm._加工金額合計列,_t月次実績表[--合計--], _xlpm._月次年月日列,_t月次実績表[年月], _xlpm._依頼NO列,_t月次実績表[依頼NO(-1除外)], IFERROR( SUM( _xlfn._xlws.FILTER(_xlpm._加工金額合計列, (A6=_xlpm._依頼NO列) * (YEAR(_xlpm._月次年月日列) = YEAR(H6)) ) ), 0) )} -> 0 | J6: =IFERROR( IF( _t受注ﾌｧｲﾙ_総合計[[#This Row],[受注金額(修正)]] > _t受注ﾌｧｲﾙ_総合計[[#This Row],[加工金額合計(月次実績)]], _t受注ﾌｧｲﾙ_総合計[[#This Row],[受注金額(修正)]], _t受注ﾌｧｲﾙ_総合計[[#This Row],[加工金額合計(月次実績)]] ), 0 ) -> 16000 | K6: =IF(ISERROR(F6),0,E6) -> 16000 | L6: =_xlfn.LET( _xlpm._依頼NO, A6, _xlpm._集計年, YEAR(H6), _xlpm._依頼列, _t受注ﾌｧｲﾙ_TPI[依頼Ｎｏ], _xlpm._集計日列, _t受注ﾌｧｲﾙ_TPI[集計日], COUNTIFS( _xlpm._依頼列, _xlpm._依頼NO, _xlpm._集計日列, ">=" & DATE(_xlpm._集計年,1,1), _xlpm._集計日列, "<" & DATE(_xlpm._集計年+1,1,1) ) ) -> 0 | M6: =_xlfn.LET( _xlpm._依頼NO, A6, _xlpm._集計年, YEAR(H6), _xlpm._依頼列,_t受注ﾌｧｲﾙ_東レ[依頼Ｎｏ], _xlpm._集計日列, _t受注ﾌｧｲﾙ_東レ[集計日], COUNTIFS( _xlpm._依頼列, _xlpm._依頼NO, _xlpm._集計日列, ">=" & DATE(_xlpm._集計年,1,1), _xlpm._集計日列, "<" & DATE(_xlpm._集計年+1,1,1) ) ) -> 1 | N6: =IFERROR( INDEX( _xlfn.TEXTSPLIT( SUBSTITUTE(SUBSTITUTE(B6, "，", ","), "、", ","), ",", ), 1, 1 ), "" ) -> SEC | O6: =IFERROR( INDEX( _xlfn.TEXTSPLIT( SUBSTITUTE(SUBSTITUTE(B6, "，", ","), "、", ","), ",", ), 1, 2 ), "" ) -> ｽﾘｯﾄ | P6: =IFERROR( INDEX( _xlfn.TEXTSPLIT( SUBSTITUTE(SUBSTITUTE(B6, "，", ","), "、", ","), ",", ), 1, 3 ), "" ) | Q6: =IFERROR( INDEX( _xlfn.TEXTSPLIT( SUBSTITUTE(SUBSTITUTE(B6, "，", ","), "、", ","), ",", ), 1, 4 ), "" ) | R6: =IFERROR( INDEX( _xlfn.TEXTSPLIT( SUBSTITUTE(SUBSTITUTE(B6, "，", ","), "、", ","), ",", ), 1, 5 ), "" )
A7: Y7-3 | B7: SEC,ｽﾘｯﾄ | C7: 46211 | D7: 1200 | E7: 12000 | F7: {=_xlfn.LET( _xlpm._完了日,_加工実績DATA[加工完了日], _xlpm._調整納期列,_t受注ﾌｧｲﾙ_総合計[調整納期], _xlpm._加工完了日,_xlfn.TAKE( _xlfn._xlws.FILTER(_xlpm._完了日, (A7=_加工実績DATA[依頼NO])* (YEAR(C7) = YEAR(_xlpm._完了日)) ),1), IF(_xlpm._加工完了日 = 0,NA(),_xlpm._加工完了日) )} -> 46209 | G7: {=_xlfn.LET( _xlpm._完了日列,#REF!, _xlpm._完了日, _xlfn.TAKE( _xlfn._xlws.FILTER(_xlpm._完了日列, (A7=#REF!)* (DATEVALUE("2025/1/1") < C7) ),1 ), IFERROR(_xlpm._完了日,"") )} | H7: {=_xlfn.LET( _xlpm.f, IFERROR(F7, 0), _xlpm.g, IFERROR(G7, 0), _xlpm.c, IFERROR(C7, 0), _xlfn.IFS( ISNUMBER(_xlpm.f)*(_xlpm.f>0), _xlpm.f, ISNUMBER(_xlpm.g)*(_xlpm.g>0), _xlpm.g, ISNUMBER(_xlpm.c)*(_xlpm.c>0), _xlpm.c, TRUE, "" ) )} -> 46209 | I7: {=_xlfn.LET( _xlpm._加工金額合計列,_t月次実績表[--合計--], _xlpm._月次年月日列,_t月次実績表[年月], _xlpm._依頼NO列,_t月次実績表[依頼NO(-1除外)], IFERROR( SUM( _xlfn._xlws.FILTER(_xlpm._加工金額合計列, (A7=_xlpm._依頼NO列) * (YEAR(_xlpm._月次年月日列) = YEAR(H7)) ) ), 0) )} -> 0 | J7: =IFERROR( IF( _t受注ﾌｧｲﾙ_総合計[[#This Row],[受注金額(修正)]] > _t受注ﾌｧｲﾙ_総合計[[#This Row],[加工金額合計(月次実績)]], _t受注ﾌｧｲﾙ_総合計[[#This Row],[受注金額(修正)]], _t受注ﾌｧｲﾙ_総合計[[#This Row],[加工金額合計(月次実績)]] ), 0 ) -> 12000 | K7: =IF(ISERROR(F7),0,E7) -> 12000 | L7: =_xlfn.LET( _xlpm._依頼NO, A7, _xlpm._集計年, YEAR(H7), _xlpm._依頼列, _t受注ﾌｧｲﾙ_TPI[依頼Ｎｏ], _xlpm._集計日列, _t受注ﾌｧｲﾙ_TPI[集計日], COUNTIFS( _xlpm._依頼列, _xlpm._依頼NO, _xlpm._集計日列, ">=" & DATE(_xlpm._集計年,1,1), _xlpm._集計日列, "<" & DATE(_xlpm._集計年+1,1,1) ) ) -> 0 | M7: =_xlfn.LET( _xlpm._依頼NO, A7, _xlpm._集計年, YEAR(H7), _xlpm._依頼列,_t受注ﾌｧｲﾙ_東レ[依頼Ｎｏ], _xlpm._集計日列, _t受注ﾌｧｲﾙ_東レ[集計日], COUNTIFS( _xlpm._依頼列, _xlpm._依頼NO, _xlpm._集計日列, ">=" & DATE(_xlpm._集計年,1,1), _xlpm._集計日列, "<" & DATE(_xlpm._集計年+1,1,1) ) ) -> 1 | N7: =IFERROR( INDEX( _xlfn.TEXTSPLIT( SUBSTITUTE(SUBSTITUTE(B7, "，", ","), "、", ","), ",", ), 1, 1 ), "" ) -> SEC | O7: =IFERROR( INDEX( _xlfn.TEXTSPLIT( SUBSTITUTE(SUBSTITUTE(B7, "，", ","), "、", ","), ",", ), 1, 2 ), "" ) -> ｽﾘｯﾄ | P7: =IFERROR( INDEX( _xlfn.TEXTSPLIT( SUBSTITUTE(SUBSTITUTE(B7, "，", ","), "、", ","), ",", ), 1, 3 ), "" ) | Q7: =IFERROR( INDEX( _xlfn.TEXTSPLIT( SUBSTITUTE(SUBSTITUTE(B7, "，", ","), "、", ","), ",", ), 1, 4 ), "" ) | R7: =IFERROR( INDEX( _xlfn.TEXTSPLIT( SUBSTITUTE(SUBSTITUTE(B7, "，", ","), "、", ","), ",", ), 1, 5 ), "" )
A8: V6-16 | B8: ｽﾗｲｽ，巻き返し | C8: 46192 | D8: 100 | E8: 3500 | F8: {=_xlfn.LET( _xlpm._完了日,_加工実績DATA[加工完了日], _xlpm._調整納期列,_t受注ﾌｧｲﾙ_総合計[調整納期], _xlpm._加工完了日,_xlfn.TAKE( _xlfn._xlws.FILTER(_xlpm._完了日, (A8=_加工実績DATA[依頼NO])* (YEAR(C8) = YEAR(_xlpm._完了日)) ),1), IF(_xlpm._加工完了日 = 0,NA(),_xlpm._加工完了日) )} -> 46196 | G8: {=_xlfn.LET( _xlpm._完了日列,#REF!, _xlpm._完了日, _xlfn.TAKE( _xlfn._xlws.FILTER(_xlpm._完了日列, (A8=#REF!)* (DATEVALUE("2025/1/1") < C8) ),1 ), IFERROR(_xlpm._完了日,"") )} | H8: {=_xlfn.LET( _xlpm.f, IFERROR(F8, 0), _xlpm.g, IFERROR(G8, 0), _xlpm.c, IFERROR(C8, 0), _xlfn.IFS( ISNUMBER(_xlpm.f)*(_xlpm.f>0), _xlpm.f, ISNUMBER(_xlpm.g)*(_xlpm.g>0), _xlpm.g, ISNUMBER(_xlpm.c)*(_xlpm.c>0), _xlpm.c, TRUE, "" ) )} -> 46196 | I8: {=_xlfn.LET( _xlpm._加工金額合計列,_t月次実績表[--合計--], _xlpm._月次年月日列,_t月次実績表[年月], _xlpm._依頼NO列,_t月次実績表[依頼NO(-1除外)], IFERROR( SUM( _xlfn._xlws.FILTER(_xlpm._加工金額合計列, (A8=_xlpm._依頼NO列) * (YEAR(_xlpm._月次年月日列) = YEAR(H8)) ) ), 0) )} -> 0 | J8: =IFERROR( IF( _t受注ﾌｧｲﾙ_総合計[[#This Row],[受注金額(修正)]] > _t受注ﾌｧｲﾙ_総合計[[#This Row],[加工金額合計(月次実績)]], _t受注ﾌｧｲﾙ_総合計[[#This Row],[受注金額(修正)]], _t受注ﾌｧｲﾙ_総合計[[#This Row],[加工金額合計(月次実績)]] ), 0 ) -> 3500 | K8: =IF(ISERROR(F8),0,E8) -> 3500 | L8: =_xlfn.LET( _xlpm._依頼NO, A8, _xlpm._集計年, YEAR(H8), _xlpm._依頼列, _t受注ﾌｧｲﾙ_TPI[依頼Ｎｏ], _xlpm._集計日列, _t受注ﾌｧｲﾙ_TPI[集計日], COUNTIFS( _xlpm._依頼列, _xlpm._依頼NO, _xlpm._集計日列, ">=" & DATE(_xlpm._集計年,1,1), _xlpm._集計日列, "<" & DATE(_xlpm._集計年+1,1,1) ) ) -> 0 | M8: =_xlfn.LET( _xlpm._依頼NO, A8, _xlpm._集計年, YEAR(H8), _xlpm._依頼列,_t受注ﾌｧｲﾙ_東レ[依頼Ｎｏ], _xlpm._集計日列, _t受注ﾌｧｲﾙ_東レ[集計日], COUNTIFS( _xlpm._依頼列, _xlpm._依頼NO, _xlpm._集計日列, ">=" & DATE(_xlpm._集計年,1,1), _xlpm._集計日列, "<" & DATE(_xlpm._集計年+1,1,1) ) ) -> 1 | N8: =IFERROR( INDEX( _xlfn.TEXTSPLIT( SUBSTITUTE(SUBSTITUTE(B8, "，", ","), "、", ","), ",", ), 1, 1 ), "" ) -> ｽﾗｲｽ | O8: =IFERROR( INDEX( _xlfn.TEXTSPLIT( SUBSTITUTE(SUBSTITUTE(B8, "，", ","), "、", ","), ",", ), 1, 2 ), "" ) -> 巻き返し | P8: =IFERROR( INDEX( _xlfn.TEXTSPLIT( SUBSTITUTE(SUBSTITUTE(B8, "，", ","), "、", ","), ",", ), 1, 3 ), "" ) | Q8: =IFERROR( INDEX( _xlfn.TEXTSPLIT( SUBSTITUTE(SUBSTITUTE(B8, "，", ","), "、", ","), ",", ), 1, 4 ), "" ) | R8: =IFERROR( INDEX( _xlfn.TEXTSPLIT( SUBSTITUTE(SUBSTITUTE(B8, "，", ","), "、", ","), ",", ), 1, 5 ), "" ) | T8: =IF(_t受注ﾌｧｲﾙ_総合計[[#This Row],[加工金額]]=_t受注ﾌｧｲﾙ_総合計[[#This Row],[受注金額(修正)]],TRUE) -> TRUE
A9: W7-1 | B9: EC,ゴミ除去 | C9: 46212 | D9: 6000 | E9: 228000 | F9: {=_xlfn.LET( _xlpm._完了日,_加工実績DATA[加工完了日], _xlpm._調整納期列,_t受注ﾌｧｲﾙ_総合計[調整納期], _xlpm._加工完了日,_xlfn.TAKE( _xlfn._xlws.FILTER(_xlpm._完了日, (A9=_加工実績DATA[依頼NO])* (YEAR(C9) = YEAR(_xlpm._完了日)) ),1), IF(_xlpm._加工完了日 = 0,NA(),_xlpm._加工完了日) )} -> 46211 | G9: {=_xlfn.LET( _xlpm._完了日列,#REF!, _xlpm._完了日, _xlfn.TAKE( _xlfn._xlws.FILTER(_xlpm._完了日列, (A9=#REF!)* (DATEVALUE("2025/1/1") < C9) ),1 ), IFERROR(_xlpm._完了日,"") )} | H9: {=_xlfn.LET( _xlpm.f, IFERROR(F9, 0), _xlpm.g, IFERROR(G9, 0), _xlpm.c, IFERROR(C9, 0), _xlfn.IFS( ISNUMBER(_xlpm.f)*(_xlpm.f>0), _xlpm.f, ISNUMBER(_xlpm.g)*(_xlpm.g>0), _xlpm.g, ISNUMBER(_xlpm.c)*(_xlpm.c>0), _xlpm.c, TRUE, "" ) )} -> 46211 | I9: {=_xlfn.LET( _xlpm._加工金額合計列,_t月次実績表[--合計--], _xlpm._月次年月日列,_t月次実績表[年月], _xlpm._依頼NO列,_t月次実績表[依頼NO(-1除外)], IFERROR( SUM( _xlfn._xlws.FILTER(_xlpm._加工金額合計列, (A9=_xlpm._依頼NO列) * (YEAR(_xlpm._月次年月日列) = YEAR(H9)) ) ), 0) )} -> 0 | J9: =IFERROR( IF( _t受注ﾌｧｲﾙ_総合計[[#This Row],[受注金額(修正)]] > _t受注ﾌｧｲﾙ_総合計[[#This Row],[加工金額合計(月次実績)]], _t受注ﾌｧｲﾙ_総合計[[#This Row],[受注金額(修正)]], _t受注ﾌｧｲﾙ_総合計[[#This Row],[加工金額合計(月次実績)]] ), 0 ) -> 228000 | K9: =IF(ISERROR(F9),0,E9) -> 228000 | L9: =_xlfn.LET( _xlpm._依頼NO, A9, _xlpm._集計年, YEAR(H9), _xlpm._依頼列, _t受注ﾌｧｲﾙ_TPI[依頼Ｎｏ], _xlpm._集計日列, _t受注ﾌｧｲﾙ_TPI[集計日], COUNTIFS( _xlpm._依頼列, _xlpm._依頼NO, _xlpm._集計日列, ">=" & DATE(_xlpm._集計年,1,1), _xlpm._集計日列, "<" & DATE(_xlpm._集計年+1,1,1) ) ) -> 0 | M9: =_xlfn.LET( _xlpm._依頼NO, A9, _xlpm._集計年, YEAR(H9), _xlpm._依頼列,_t受注ﾌｧｲﾙ_東レ[依頼Ｎｏ], _xlpm._集計日列, _t受注ﾌｧｲﾙ_東レ[集計日], COUNTIFS( _xlpm._依頼列, _xlpm._依頼NO, _xlpm._集計日列, ">=" & DATE(_xlpm._集計年,1,1), _xlpm._集計日列, "<" & DATE(_xlpm._集計年+1,1,1) ) ) -> 1 | N9: =IFERROR( INDEX( _xlfn.TEXTSPLIT( SUBSTITUTE(SUBSTITUTE(B9, "，", ","), "、", ","), ",", ), 1, 1 ), "" ) -> EC | O9: =IFERROR( INDEX( _xlfn.TEXTSPLIT( SUBSTITUTE(SUBSTITUTE(B9, "，", ","), "、", ","), ",", ), 1, 2 ), "" ) -> ゴミ除去 | P9: =IFERROR( INDEX( _xlfn.TEXTSPLIT( SUBSTITUTE(SUBSTITUTE(B9, "，", ","), "、", ","), ",", ), 1, 3 ), "" ) | Q9: =IFERROR( INDEX( _xlfn.TEXTSPLIT( SUBSTITUTE(SUBSTITUTE(B9, "，", ","), "、", ","), ",", ), 1, 4 ), "" ) | R9: =IFERROR( INDEX( _xlfn.TEXTSPLIT( SUBSTITUTE(SUBSTITUTE(B9, "，", ","), "、", ","), ",", ), 1, 5 ), "" ) | T9: =IF(_t受注ﾌｧｲﾙ_総合計[[#This Row],[加工金額]]=_t受注ﾌｧｲﾙ_総合計[[#This Row],[受注金額(修正)]],TRUE) -> TRUE
A10: W7-2 | B10: EC,ゴミ除去 | C10: 46216 | D10: 6000 | E10: 228000 | F10: {=_xlfn.LET( _xlpm._完了日,_加工実績DATA[加工完了日], _xlpm._調整納期列,_t受注ﾌｧｲﾙ_総合計[調整納期], _xlpm._加工完了日,_xlfn.TAKE( _xlfn._xlws.FILTER(_xlpm._完了日, (A10=_加工実績DATA[依頼NO])* (YEAR(C10) = YEAR(_xlpm._完了日)) ),1), IF(_xlpm._加工完了日 = 0,NA(),_xlpm._加工完了日) )} -> 46213 | G10: {=_xlfn.LET( _xlpm._完了日列,#REF!, _xlpm._完了日, _xlfn.TAKE( _xlfn._xlws.FILTER(_xlpm._完了日列, (A10=#REF!)* (DATEVALUE("2025/1/1") < C10) ),1 ), IFERROR(_xlpm._完了日,"") )} | H10: {=_xlfn.LET( _xlpm.f, IFERROR(F10, 0), _xlpm.g, IFERROR(G10, 0), _xlpm.c, IFERROR(C10, 0), _xlfn.IFS( ISNUMBER(_xlpm.f)*(_xlpm.f>0), _xlpm.f, ISNUMBER(_xlpm.g)*(_xlpm.g>0), _xlpm.g, ISNUMBER(_xlpm.c)*(_xlpm.c>0), _xlpm.c, TRUE, "" ) )} -> 46213 | I10: {=_xlfn.LET( _xlpm._加工金額合計列,_t月次実績表[--合計--], _xlpm._月次年月日列,_t月次実績表[年月], _xlpm._依頼NO列,_t月次実績表[依頼NO(-1除外)], IFERROR( SUM( _xlfn._xlws.FILTER(_xlpm._加工金額合計列, (A10=_xlpm._依頼NO列) * (YEAR(_xlpm._月次年月日列) = YEAR(H10)) ) ), 0) )} -> 0 | J10: =IFERROR( IF( _t受注ﾌｧｲﾙ_総合計[[#This Row],[受注金額(修正)]] > _t受注ﾌｧｲﾙ_総合計[[#This Row],[加工金額合計(月次実績)]], _t受注ﾌｧｲﾙ_総合計[[#This Row],[受注金額(修正)]], _t受注ﾌｧｲﾙ_総合計[[#This Row],[加工金額合計(月次実績)]] ), 0 ) -> 228000 | K10: =IF(ISERROR(F10),0,E10) -> 228000 | L10: =_xlfn.LET( _xlpm._依頼NO, A10, _xlpm._集計年, YEAR(H10), _xlpm._依頼列, _t受注ﾌｧｲﾙ_TPI[依頼Ｎｏ], _xlpm._集計日列, _t受注ﾌｧｲﾙ_TPI[集計日], COUNTIFS( _xlpm._依頼列, _xlpm._依頼NO, _xlpm._集計日列, ">=" & DATE(_xlpm._集計年,1,1), _xlpm._集計日列, "<" & DATE(_xlpm._集計年+1,1,1) ) ) -> 0 | M10: =_xlfn.LET( _xlpm._依頼NO, A10, _xlpm._集計年, YEAR(H10), _xlpm._依頼列,_t受注ﾌｧｲﾙ_東レ[依頼Ｎｏ], _xlpm._集計日列, _t受注ﾌｧｲﾙ_東レ[集計日], COUNTIFS( _xlpm._依頼列, _xlpm._依頼NO, _xlpm._集計日列, ">=" & DATE(_xlpm._集計年,1,1), _xlpm._集計日列, "<" & DATE(_xlpm._集計年+1,1,1) ) ) -> 1 | N10: =IFERROR( INDEX( _xlfn.TEXTSPLIT( SUBSTITUTE(SUBSTITUTE(B10, "，", ","), "、", ","), ",", ), 1, 1 ), "" ) -> EC | O10: =IFERROR( INDEX( _xlfn.TEXTSPLIT( SUBSTITUTE(SUBSTITUTE(B10, "，", ","), "、", ","), ",", ), 1, 2 ), "" ) -> ゴミ除去 | P10: =IFERROR( INDEX( _xlfn.TEXTSPLIT( SUBSTITUTE(SUBSTITUTE(B10, "，", ","), "、", ","), ",", ), 1, 3 ), "" ) | Q10: =IFERROR( INDEX( _xlfn.TEXTSPLIT( SUBSTITUTE(SUBSTITUTE(B10, "，", ","), "、", ","), ",", ), 1, 4 ), "" ) | R10: =IFERROR( INDEX( _xlfn.TEXTSPLIT( SUBSTITUTE(SUBSTITUTE(B10, "，", ","), "、", ","), ",", ), 1, 5 ), "" ) | T10: =IF(_t受注ﾌｧｲﾙ_総合計[[#This Row],[加工金額]]=_t受注ﾌｧｲﾙ_総合計[[#This Row],[受注金額(修正)]],TRUE) -> TRUE
A11: W7-3 | B11: EC,ゴミ除去 | C11: 46217 | D11: 5400 | E11: 205200 | F11: {=_xlfn.LET( _xlpm._完了日,_加工実績DATA[加工完了日], _xlpm._調整納期列,_t受注ﾌｧｲﾙ_総合計[調整納期], _xlpm._加工完了日,_xlfn.TAKE( _xlfn._xlws.FILTER(_xlpm._完了日, (A11=_加工実績DATA[依頼NO])* (YEAR(C11) = YEAR(_xlpm._完了日)) ),1), IF(_xlpm._加工完了日 = 0,NA(),_xlpm._加工完了日) )} -> 46230 | G11: {=_xlfn.LET( _xlpm._完了日列,#REF!, _xlpm._完了日, _xlfn.TAKE( _xlfn._xlws.FILTER(_xlpm._完了日列, (A11=#REF!)* (DATEVALUE("2025/1/1") < C11) ),1 ), IFERROR(_xlpm._完了日,"") )} | H11: {=_xlfn.LET( _xlpm.f, IFERROR(F11, 0), _xlpm.g, IFERROR(G11, 0), _xlpm.c, IFERROR(C11, 0), _xlfn.IFS( ISNUMBER(_xlpm.f)*(_xlpm.f>0), _xlpm.f, ISNUMBER(_xlpm.g)*(_xlpm.g>0), _xlpm.g, ISNUMBER(_xlpm.c)*(_xlpm.c>0), _xlpm.c, TRUE, "" ) )} -> 46230 | I11: {=_xlfn.LET( _xlpm._加工金額合計列,_t月次実績表[--合計--], _xlpm._月次年月日列,_t月次実績表[年月], _xlpm._依頼NO列,_t月次実績表[依頼NO(-1除外)], IFERROR( SUM( _xlfn._xlws.FILTER(_xlpm._加工金額合計列, (A11=_xlpm._依頼NO列) * (YEAR(_xlpm._月次年月日列) = YEAR(H11)) ) ), 0) )} -> 0 | J11: =IFERROR( IF( _t受注ﾌｧｲﾙ_総合計[[#This Row],[受注金額(修正)]] > _t受注ﾌｧｲﾙ_総合計[[#This Row],[加工金額合計(月次実績)]], _t受注ﾌｧｲﾙ_総合計[[#This Row],[受注金額(修正)]], _t受注ﾌｧｲﾙ_総合計[[#This Row],[加工金額合計(月次実績)]] ), 0 ) -> 205200 | K11: =IF(ISERROR(F11),0,E11) -> 205200 | L11: =_xlfn.LET( _xlpm._依頼NO, A11, _xlpm._集計年, YEAR(H11), _xlpm._依頼列, _t受注ﾌｧｲﾙ_TPI[依頼Ｎｏ], _xlpm._集計日列, _t受注ﾌｧｲﾙ_TPI[集計日], COUNTIFS( _xlpm._依頼列, _xlpm._依頼NO, _xlpm._集計日列, ">=" & DATE(_xlpm._集計年,1,1), _xlpm._集計日列, "<" & DATE(_xlpm._集計年+1,1,1) ) ) -> 0 | M11: =_xlfn.LET( _xlpm._依頼NO, A11, _xlpm._集計年, YEAR(H11), _xlpm._依頼列,_t受注ﾌｧｲﾙ_東レ[依頼Ｎｏ], _xlpm._集計日列, _t受注ﾌｧｲﾙ_東レ[集計日], COUNTIFS( _xlpm._依頼列, _xlpm._依頼NO, _xlpm._集計日列, ">=" & DATE(_xlpm._集計年,1,1), _xlpm._集計日列, "<" & DATE(_xlpm._集計年+1,1,1) ) ) -> 1 | N11: =IFERROR( INDEX( _xlfn.TEXTSPLIT( SUBSTITUTE(SUBSTITUTE(B11, "，", ","), "、", ","), ",", ), 1, 1 ), "" ) -> EC | O11: =IFERROR( INDEX( _xlfn.TEXTSPLIT( SUBSTITUTE(SUBSTITUTE(B11, "，", ","), "、", ","), ",", ), 1, 2 ), "" ) -> ゴミ除去 | P11: =IFERROR( INDEX( _xlfn.TEXTSPLIT( SUBSTITUTE(SUBSTITUTE(B11, "，", ","), "、", ","), ",", ), 1, 3 ), "" ) | Q11: =IFERROR( INDEX( _xlfn.TEXTSPLIT( SUBSTITUTE(SUBSTITUTE(B11, "，", ","), "、", ","), ",", ), 1, 4 ), "" ) | R11: =IFERROR( INDEX( _xlfn.TEXTSPLIT( SUBSTITUTE(SUBSTITUTE(B11, "，", ","), "、", ","), ",", ), 1, 5 ), "" ) | T11: =IF(_t受注ﾌｧｲﾙ_総合計[[#This Row],[加工金額]]=_t受注ﾌｧｲﾙ_総合計[[#This Row],[受注金額(修正)]],TRUE) -> TRUE
A12: Y6-18 | B12: ｽﾗｲｽ | C12: 46198 | D12: 12000 | E12: 12000 | F12: {=_xlfn.LET( _xlpm._完了日,_加工実績DATA[加工完了日], _xlpm._調整納期列,_t受注ﾌｧｲﾙ_総合計[調整納期], _xlpm._加工完了日,_xlfn.TAKE( _xlfn._xlws.FILTER(_xlpm._完了日, (A12=_加工実績DATA[依頼NO])* (YEAR(C12) = YEAR(_xlpm._完了日)) ),1), IF(_xlpm._加工完了日 = 0,NA(),_xlpm._加工完了日) )} -> 46196 | G12: {=_xlfn.LET( _xlpm._完了日列,#REF!, _xlpm._完了日, _xlfn.TAKE( _xlfn._xlws.FILTER(_xlpm._完了日列, (A12=#REF!)* (DATEVALUE("2025/1/1") < C12) ),1 ), IFERROR(_xlpm._完了日,"") )} | H12: {=_xlfn.LET( _xlpm.f, IFERROR(F12, 0), _xlpm.g, IFERROR(G12, 0), _xlpm.c, IFERROR(C12, 0), _xlfn.IFS( ISNUMBER(_xlpm.f)*(_xlpm.f>0), _xlpm.f, ISNUMBER(_xlpm.g)*(_xlpm.g>0), _xlpm.g, ISNUMBER(_xlpm.c)*(_xlpm.c>0), _xlpm.c, TRUE, "" ) )} -> 46196 | I12: {=_xlfn.LET( _xlpm._加工金額合計列,_t月次実績表[--合計--], _xlpm._月次年月日列,_t月次実績表[年月], _xlpm._依頼NO列,_t月次実績表[依頼NO(-1除外)], IFERROR( SUM( _xlfn._xlws.FILTER(_xlpm._加工金額合計列, (A12=_xlpm._依頼NO列) * (YEAR(_xlpm._月次年月日列) = YEAR(H12)) ) ), 0) )} -> 0 | J12: =IFERROR( IF( _t受注ﾌｧｲﾙ_総合計[[#This Row],[受注金額(修正)]] > _t受注ﾌｧｲﾙ_総合計[[#This Row],[加工金額合計(月次実績)]], _t受注ﾌｧｲﾙ_総合計[[#This Row],[受注金額(修正)]], _t受注ﾌｧｲﾙ_総合計[[#This Row],[加工金額合計(月次実績)]] ), 0 ) -> 12000 | K12: =IF(ISERROR(F12),0,E12) -> 12000 | L12: =_xlfn.LET( _xlpm._依頼NO, A12, _xlpm._集計年, YEAR(H12), _xlpm._依頼列, _t受注ﾌｧｲﾙ_TPI[依頼Ｎｏ], _xlpm._集計日列, _t受注ﾌｧｲﾙ_TPI[集計日], COUNTIFS( _xlpm._依頼列, _xlpm._依頼NO, _xlpm._集計日列, ">=" & DATE(_xlpm._集計年,1,1), _xlpm._集計日列, "<" & DATE(_xlpm._集計年+1,1,1) ) ) -> 0 | M12: =_xlfn.LET( _xlpm._依頼NO, A12, _xlpm._集計年, YEAR(H12), _xlpm._依頼列,_t受注ﾌｧｲﾙ_東レ[依頼Ｎｏ], _xlpm._集計日列, _t受注ﾌｧｲﾙ_東レ[集計日], COUNTIFS( _xlpm._依頼列, _xlpm._依頼NO, _xlpm._集計日列, ">=" & DATE(_xlpm._集計年,1,1), _xlpm._集計日列, "<" & DATE(_xlpm._集計年+1,1,1) ) ) -> 1 | N12: =IFERROR( INDEX( _xlfn.TEXTSPLIT( SUBSTITUTE(SUBSTITUTE(B12, "，", ","), "、", ","), ",", ), 1, 1 ), "" ) -> ｽﾗｲｽ | O12: =IFERROR( INDEX( _xlfn.TEXTSPLIT( SUBSTITUTE(SUBSTITUTE(B12, "，", ","), "、", ","), ",", ), 1, 2 ), "" ) | P12: =IFERROR( INDEX( _xlfn.TEXTSPLIT( SUBSTITUTE(SUBSTITUTE(B12, "，", ","), "、", ","), ",", ), 1, 3 ), "" ) | Q12: =IFERROR( INDEX( _xlfn.TEXTSPLIT( SUBSTITUTE(SUBSTITUTE(B12, "，", ","), "、", ","), ",", ), 1, 4 ), "" ) | R12: =IFERROR( INDEX( _xlfn.TEXTSPLIT( SUBSTITUTE(SUBSTITUTE(B12, "，", ","), "、", ","), ",", ), 1, 5 ), "" ) | T12: =IF(_t受注ﾌｧｲﾙ_総合計[[#This Row],[加工金額]]=_t受注ﾌｧｲﾙ_総合計[[#This Row],[受注金額(修正)]],TRUE) -> TRUE
A13: Y6-19 | B13: ｽﾗｲｽ | C13: 46202 | D13: 20000 | E13: 220000 | F13: {=_xlfn.LET( _xlpm._完了日,_加工実績DATA[加工完了日], _xlpm._調整納期列,_t受注ﾌｧｲﾙ_総合計[調整納期], _xlpm._加工完了日,_xlfn.TAKE( _xlfn._xlws.FILTER(_xlpm._完了日, (A13=_加工実績DATA[依頼NO])* (YEAR(C13) = YEAR(_xlpm._完了日)) ),1), IF(_xlpm._加工完了日 = 0,NA(),_xlpm._加工完了日) )} -> 46198 | G13: {=_xlfn.LET( _xlpm._完了日列,#REF!, _xlpm._完了日, _xlfn.TAKE( _xlfn._xlws.FILTER(_xlpm._完了日列, (A13=#REF!)* (DATEVALUE("2025/1/1") < C13) ),1 ), IFERROR(_xlpm._完了日,"") )} | H13: {=_xlfn.LET( _xlpm.f, IFERROR(F13, 0), _xlpm.g, IFERROR(G13, 0), _xlpm.c, IFERROR(C13, 0), _xlfn.IFS( ISNUMBER(_xlpm.f)*(_xlpm.f>0), _xlpm.f, ISNUMBER(_xlpm.g)*(_xlpm.g>0), _xlpm.g, ISNUMBER(_xlpm.c)*(_xlpm.c>0), _xlpm.c, TRUE, "" ) )} -> 46198 | I13: {=_xlfn.LET( _xlpm._加工金額合計列,_t月次実績表[--合計--], _xlpm._月次年月日列,_t月次実績表[年月], _xlpm._依頼NO列,_t月次実績表[依頼NO(-1除外)], IFERROR( SUM( _xlfn._xlws.FILTER(_xlpm._加工金額合計列, (A13=_xlpm._依頼NO列) * (YEAR(_xlpm._月次年月日列) = YEAR(H13)) ) ), 0) )} -> 0 | J13: =IFERROR( IF( _t受注ﾌｧｲﾙ_総合計[[#This Row],[受注金額(修正)]] > _t受注ﾌｧｲﾙ_総合計[[#This Row],[加工金額合計(月次実績)]], _t受注ﾌｧｲﾙ_総合計[[#This Row],[受注金額(修正)]], _t受注ﾌｧｲﾙ_総合計[[#This Row],[加工金額合計(月次実績)]] ), 0 ) -> 220000 | K13: =IF(ISERROR(F13),0,E13) -> 220000 | L13: =_xlfn.LET( _xlpm._依頼NO, A13, _xlpm._集計年, YEAR(H13), _xlpm._依頼列, _t受注ﾌｧｲﾙ_TPI[依頼Ｎｏ], _xlpm._集計日列, _t受注ﾌｧｲﾙ_TPI[集計日], COUNTIFS( _xlpm._依頼列, _xlpm._依頼NO, _xlpm._集計日列, ">=" & DATE(_xlpm._集計年,1,1), _xlpm._集計日列, "<" & DATE(_xlpm._集計年+1,1,1) ) ) -> 0 | M13: =_xlfn.LET( _xlpm._依頼NO, A13, _xlpm._集計年, YEAR(H13), _xlpm._依頼列,_t受注ﾌｧｲﾙ_東レ[依頼Ｎｏ], _xlpm._集計日列, _t受注ﾌｧｲﾙ_東レ[集計日], COUNTIFS( _xlpm._依頼列, _xlpm._依頼NO, _xlpm._集計日列, ">=" & DATE(_xlpm._集計年,1,1), _xlpm._集計日列, "<" & DATE(_xlpm._集計年+1,1,1) ) ) -> 1 | N13: =IFERROR( INDEX( _xlfn.TEXTSPLIT( SUBSTITUTE(SUBSTITUTE(B13, "，", ","), "、", ","), ",", ), 1, 1 ), "" ) -> ｽﾗｲｽ | O13: =IFERROR( INDEX( _xlfn.TEXTSPLIT( SUBSTITUTE(SUBSTITUTE(B13, "，", ","), "、", ","), ",", ), 1, 2 ), "" ) | P13: =IFERROR( INDEX( _xlfn.TEXTSPLIT( SUBSTITUTE(SUBSTITUTE(B13, "，", ","), "、", ","), ",", ), 1, 3 ), "" ) | Q13: =IFERROR( INDEX( _xlfn.TEXTSPLIT( SUBSTITUTE(SUBSTITUTE(B13, "，", ","), "、", ","), ",", ), 1, 4 ), "" ) | R13: =IFERROR( INDEX( _xlfn.TEXTSPLIT( SUBSTITUTE(SUBSTITUTE(B13, "，", ","), "、", ","), ",", ), 1, 5 ), "" ) | T13: =IF(_t受注ﾌｧｲﾙ_総合計[[#This Row],[加工金額]]=_t受注ﾌｧｲﾙ_総合計[[#This Row],[受注金額(修正)]],TRUE) -> TRUE
A14: W6-21 | B14: EC,検査 | C14: 46202 | D14: 6000 | E14: 228000 | F14: {=_xlfn.LET( _xlpm._完了日,_加工実績DATA[加工完了日], _xlpm._調整納期列,_t受注ﾌｧｲﾙ_総合計[調整納期], _xlpm._加工完了日,_xlfn.TAKE( _xlfn._xlws.FILTER(_xlpm._完了日, (A14=_加工実績DATA[依頼NO])* (YEAR(C14) = YEAR(_xlpm._完了日)) ),1), IF(_xlpm._加工完了日 = 0,NA(),_xlpm._加工完了日) )} -> 46198 | G14: {=_xlfn.LET( _xlpm._完了日列,#REF!, _xlpm._完了日, _xlfn.TAKE( _xlfn._xlws.FILTER(_xlpm._完了日列, (A14=#REF!)* (DATEVALUE("2025/1/1") < C14) ),1 ), IFERROR(_xlpm._完了日,"") )} | H14: {=_xlfn.LET( _xlpm.f, IFERROR(F14, 0), _xlpm.g, IFERROR(G14, 0), _xlpm.c, IFERROR(C14, 0), _xlfn.IFS( ISNUMBER(_xlpm.f)*(_xlpm.f>0), _xlpm.f, ISNUMBER(_xlpm.g)*(_xlpm.g>0), _xlpm.g, ISNUMBER(_xlpm.c)*(_xlpm.c>0), _xlpm.c, TRUE, "" ) )} -> 46198 | I14: {=_xlfn.LET( _xlpm._加工金額合計列,_t月次実績表[--合計--], _xlpm._月次年月日列,_t月次実績表[年月], _xlpm._依頼NO列,_t月次実績表[依頼NO(-1除外)], IFERROR( SUM( _xlfn._xlws.FILTER(_xlpm._加工金額合計列, (A14=_xlpm._依頼NO列) * (YEAR(_xlpm._月次年月日列) = YEAR(H14)) ) ), 0) )} -> 0 | J14: =IFERROR( IF( _t受注ﾌｧｲﾙ_総合計[[#This Row],[受注金額(修正)]] > _t受注ﾌｧｲﾙ_総合計[[#This Row],[加工金額合計(月次実績)]], _t受注ﾌｧｲﾙ_総合計[[#This Row],[受注金額(修正)]], _t受注ﾌｧｲﾙ_総合計[[#This Row],[加工金額合計(月次実績)]] ), 0 ) -> 228000 | K14: =IF(ISERROR(F14),0,E14) -> 228000 | L14: =_xlfn.LET( _xlpm._依頼NO, A14, _xlpm._集計年, YEAR(H14), _xlpm._依頼列, _t受注ﾌｧｲﾙ_TPI[依頼Ｎｏ], _xlpm._集計日列, _t受注ﾌｧｲﾙ_TPI[集計日], COUNTIFS( _xlpm._依頼列, _xlpm._依頼NO, _xlpm._集計日列, ">=" & DATE(_xlpm._集計年,1,1), _xlpm._集計日列, "<" & DATE(_xlpm._集計年+1,1,1) ) ) -> 0 | M14: =_xlfn.LET( _xlpm._依頼NO, A14, _xlpm._集計年, YEAR(H14), _xlpm._依頼列,_t受注ﾌｧｲﾙ_東レ[依頼Ｎｏ], _xlpm._集計日列, _t受注ﾌｧｲﾙ_東レ[集計日], COUNTIFS( _xlpm._依頼列, _xlpm._依頼NO, _xlpm._集計日列, ">=" & DATE(_xlpm._集計年,1,1), _xlpm._集計日列, "<" & DATE(_xlpm._集計年+1,1,1) ) ) -> 1 | N14: =IFERROR( INDEX( _xlfn.TEXTSPLIT( SUBSTITUTE(SUBSTITUTE(B14, "，", ","), "、", ","), ",", ), 1, 1 ), "" ) -> EC | O14: =IFERROR( INDEX( _xlfn.TEXTSPLIT( SUBSTITUTE(SUBSTITUTE(B14, "，", ","), "、", ","), ",", ), 1, 2 ), "" ) -> 検査 | P14: =IFERROR( INDEX( _xlfn.TEXTSPLIT( SUBSTITUTE(SUBSTITUTE(B14, "，", ","), "、", ","), ",", ), 1, 3 ), "" ) | Q14: =IFERROR( INDEX( _xlfn.TEXTSPLIT( SUBSTITUTE(SUBSTITUTE(B14, "，", ","), "、", ","), ",", ), 1, 4 ), "" ) | R14: =IFERROR( INDEX( _xlfn.TEXTSPLIT( SUBSTITUTE(SUBSTITUTE(B14, "，", ","), "、", ","), ",", ), 1, 5 ), "" ) | T14: =IF(_t受注ﾌｧｲﾙ_総合計[[#This Row],[加工金額]]=_t受注ﾌｧｲﾙ_総合計[[#This Row],[受注金額(修正)]],TRUE) -> TRUE
A15: W6-22 | B15: EC,検査 | C15: 46203 | D15: 6000 | E15: 228000 | F15: {=_xlfn.LET( _xlpm._完了日,_加工実績DATA[加工完了日], _xlpm._調整納期列,_t受注ﾌｧｲﾙ_総合計[調整納期], _xlpm._加工完了日,_xlfn.TAKE( _xlfn._xlws.FILTER(_xlpm._完了日, (A15=_加工実績DATA[依頼NO])* (YEAR(C15) = YEAR(_xlpm._完了日)) ),1), IF(_xlpm._加工完了日 = 0,NA(),_xlpm._加工完了日) )} -> 46199 | G15: {=_xlfn.LET( _xlpm._完了日列,#REF!, _xlpm._完了日, _xlfn.TAKE( _xlfn._xlws.FILTER(_xlpm._完了日列, (A15=#REF!)* (DATEVALUE("2025/1/1") < C15) ),1 ), IFERROR(_xlpm._完了日,"") )} | H15: {=_xlfn.LET( _xlpm.f, IFERROR(F15, 0), _xlpm.g, IFERROR(G15, 0), _xlpm.c, IFERROR(C15, 0), _xlfn.IFS( ISNUMBER(_xlpm.f)*(_xlpm.f>0), _xlpm.f, ISNUMBER(_xlpm.g)*(_xlpm.g>0), _xlpm.g, ISNUMBER(_xlpm.c)*(_xlpm.c>0), _xlpm.c, TRUE, "" ) )} -> 46199 | I15: {=_xlfn.LET( _xlpm._加工金額合計列,_t月次実績表[--合計--], _xlpm._月次年月日列,_t月次実績表[年月], _xlpm._依頼NO列,_t月次実績表[依頼NO(-1除外)], IFERROR( SUM( _xlfn._xlws.FILTER(_xlpm._加工金額合計列, (A15=_xlpm._依頼NO列) * (YEAR(_xlpm._月次年月日列) = YEAR(H15)) ) ), 0) )} -> 0 | J15: =IFERROR( IF( _t受注ﾌｧｲﾙ_総合計[[#This Row],[受注金額(修正)]] > _t受注ﾌｧｲﾙ_総合計[[#This Row],[加工金額合計(月次実績)]], _t受注ﾌｧｲﾙ_総合計[[#This Row],[受注金額(修正)]], _t受注ﾌｧｲﾙ_総合計[[#This Row],[加工金額合計(月次実績)]] ), 0 ) -> 228000 | K15: =IF(ISERROR(F15),0,E15) -> 228000 | L15: =_xlfn.LET( _xlpm._依頼NO, A15, _xlpm._集計年, YEAR(H15), _xlpm._依頼列, _t受注ﾌｧｲﾙ_TPI[依頼Ｎｏ], _xlpm._集計日列, _t受注ﾌｧｲﾙ_TPI[集計日], COUNTIFS( _xlpm._依頼列, _xlpm._依頼NO, _xlpm._集計日列, ">=" & DATE(_xlpm._集計年,1,1), _xlpm._集計日列, "<" & DATE(_xlpm._集計年+1,1,1) ) ) -> 0 | M15: =_xlfn.LET( _xlpm._依頼NO, A15, _xlpm._集計年, YEAR(H15), _xlpm._依頼列,_t受注ﾌｧｲﾙ_東レ[依頼Ｎｏ], _xlpm._集計日列, _t受注ﾌｧｲﾙ_東レ[集計日], COUNTIFS( _xlpm._依頼列, _xlpm._依頼NO, _xlpm._集計日列, ">=" & DATE(_xlpm._集計年,1,1), _xlpm._集計日列, "<" & DATE(_xlpm._集計年+1,1,1) ) ) -> 1 | N15: =IFERROR( INDEX( _xlfn.TEXTSPLIT( SUBSTITUTE(SUBSTITUTE(B15, "，", ","), "、", ","), ",", ), 1, 1 ), "" ) -> EC | O15: =IFERROR( INDEX( _xlfn.TEXTSPLIT( SUBSTITUTE(SUBSTITUTE(B15, "，", ","), "、", ","), ",", ), 1, 2 ), "" ) -> 検査 | P15: =IFERROR( INDEX( _xlfn.TEXTSPLIT( SUBSTITUTE(SUBSTITUTE(B15, "，", ","), "、", ","), ",", ), 1, 3 ), "" ) | Q15: =IFERROR( INDEX( _xlfn.TEXTSPLIT( SUBSTITUTE(SUBSTITUTE(B15, "，", ","), "、", ","), ",", ), 1, 4 ), "" ) | R15: =IFERROR( INDEX( _xlfn.TEXTSPLIT( SUBSTITUTE(SUBSTITUTE(B15, "，", ","), "、", ","), ",", ), 1, 5 ), "" ) | T15: =IF(_t受注ﾌｧｲﾙ_総合計[[#This Row],[加工金額]]=_t受注ﾌｧｲﾙ_総合計[[#This Row],[受注金額(修正)]],TRUE) -> TRUE
A16: W6-23 | B16: ｽﾘｯﾄ | C16: 46197 | D16: 2400 297 289 | E16: 50762 | F16: {=_xlfn.LET( _xlpm._完了日,_加工実績DATA[加工完了日], _xlpm._調整納期列,_t受注ﾌｧｲﾙ_総合計[調整納期], _xlpm._加工完了日,_xlfn.TAKE( _xlfn._xlws.FILTER(_xlpm._完了日, (A16=_加工実績DATA[依頼NO])* (YEAR(C16) = YEAR(_xlpm._完了日)) ),1), IF(_xlpm._加工完了日 = 0,NA(),_xlpm._加工完了日) )} -> 46196 | G16: {=_xlfn.LET( _xlpm._完了日列,#REF!, _xlpm._完了日, _xlfn.TAKE( _xlfn._xlws.FILTER(_xlpm._完了日列, (A16=#REF!)* (DATEVALUE("2025/1/1") < C16) ),1 ), IFERROR(_xlpm._完了日,"") )} | H16: {=_xlfn.LET( _xlpm.f, IFERROR(F16, 0), _xlpm.g, IFERROR(G16, 0), _xlpm.c, IFERROR(C16, 0), _xlfn.IFS( ISNUMBER(_xlpm.f)*(_xlpm.f>0), _xlpm.f, ISNUMBER(_xlpm.g)*(_xlpm.g>0), _xlpm.g, ISNUMBER(_xlpm.c)*(_xlpm.c>0), _xlpm.c, TRUE, "" ) )} -> 46196 | I16: {=_xlfn.LET( _xlpm._加工金額合計列,_t月次実績表[--合計--], _xlpm._月次年月日列,_t月次実績表[年月], _xlpm._依頼NO列,_t月次実績表[依頼NO(-1除外)], IFERROR( SUM( _xlfn._xlws.FILTER(_xlpm._加工金額合計列, (A16=_xlpm._依頼NO列) * (YEAR(_xlpm._月次年月日列) = YEAR(H16)) ) ), 0) )} -> 0 | J16: =IFERROR( IF( _t受注ﾌｧｲﾙ_総合計[[#This Row],[受注金額(修正)]] > _t受注ﾌｧｲﾙ_総合計[[#This Row],[加工金額合計(月次実績)]], _t受注ﾌｧｲﾙ_総合計[[#This Row],[受注金額(修正)]], _t受注ﾌｧｲﾙ_総合計[[#This Row],[加工金額合計(月次実績)]] ), 0 ) -> 50762 | K16: =IF(ISERROR(F16),0,E16) -> 50762 | L16: =_xlfn.LET( _xlpm._依頼NO, A16, _xlpm._集計年, YEAR(H16), _xlpm._依頼列, _t受注ﾌｧｲﾙ_TPI[依頼Ｎｏ], _xlpm._集計日列, _t受注ﾌｧｲﾙ_TPI[集計日], COUNTIFS( _xlpm._依頼列, _xlpm._依頼NO, _xlpm._集計日列, ">=" & DATE(_xlpm._集計年,1,1), _xlpm._集計日列, "<" & DATE(_xlpm._集計年+1,1,1) ) ) -> 0 | M16: =_xlfn.LET( _xlpm._依頼NO, A16, _xlpm._集計年, YEAR(H16), _xlpm._依頼列,_t受注ﾌｧｲﾙ_東レ[依頼Ｎｏ], _xlpm._集計日列, _t受注ﾌｧｲﾙ_東レ[集計日], COUNTIFS( _xlpm._依頼列, _xlpm._依頼NO, _xlpm._集計日列, ">=" & DATE(_xlpm._集計年,1,1), _xlpm._集計日列, "<" & DATE(_xlpm._集計年+1,1,1) ) ) -> 1 | N16: =IFERROR( INDEX( _xlfn.TEXTSPLIT( SUBSTITUTE(SUBSTITUTE(B16, "，", ","), "、", ","), ",", ), 1, 1 ), "" ) -> ｽﾘｯﾄ | O16: =IFERROR( INDEX( _xlfn.TEXTSPLIT( SUBSTITUTE(SUBSTITUTE(B16, "，", ","), "、", ","), ",", ), 1, 2 ), "" ) | P16: =IFERROR( INDEX( _xlfn.TEXTSPLIT( SUBSTITUTE(SUBSTITUTE(B16, "，", ","), "、", ","), ",", ), 1, 3 ), "" ) | Q16: =IFERROR( INDEX( _xlfn.TEXTSPLIT( SUBSTITUTE(SUBSTITUTE(B16, "，", ","), "、", ","), ",", ), 1, 4 ), "" ) | R16: =IFERROR( INDEX( _xlfn.TEXTSPLIT( SUBSTITUTE(SUBSTITUTE(B16, "，", ","), "、", ","), ",", ), 1, 5 ), "" ) | T16: =IF(_t受注ﾌｧｲﾙ_総合計[[#This Row],[加工金額]]=_t受注ﾌｧｲﾙ_総合計[[#This Row],[受注金額(修正)]],TRUE) -> TRUE
A17: C6-9 | B17: SEC,巻き返し | C17: 46198 | D17: 400 | E17: 10400 | F17: {=_xlfn.LET( _xlpm._完了日,_加工実績DATA[加工完了日], _xlpm._調整納期列,_t受注ﾌｧｲﾙ_総合計[調整納期], _xlpm._加工完了日,_xlfn.TAKE( _xlfn._xlws.FILTER(_xlpm._完了日, (A17=_加工実績DATA[依頼NO])* (YEAR(C17) = YEAR(_xlpm._完了日)) ),1), IF(_xlpm._加工完了日 = 0,NA(),_xlpm._加工完了日) )} -> 46197 | G17: {=_xlfn.LET( _xlpm._完了日列,#REF!, _xlpm._完了日, _xlfn.TAKE( _xlfn._xlws.FILTER(_xlpm._完了日列, (A17=#REF!)* (DATEVALUE("2025/1/1") < C17) ),1 ), IFERROR(_xlpm._完了日,"") )} | H17: {=_xlfn.LET( _xlpm.f, IFERROR(F17, 0), _xlpm.g, IFERROR(G17, 0), _xlpm.c, IFERROR(C17, 0), _xlfn.IFS( ISNUMBER(_xlpm.f)*(_xlpm.f>0), _xlpm.f, ISNUMBER(_xlpm.g)*(_xlpm.g>0), _xlpm.g, ISNUMBER(_xlpm.c)*(_xlpm.c>0), _xlpm.c, TRUE, "" ) )} -> 46197 | I17: {=_xlfn.LET( _xlpm._加工金額合計列,_t月次実績表[--合計--], _xlpm._月次年月日列,_t月次実績表[年月], _xlpm._依頼NO列,_t月次実績表[依頼NO(-1除外)], IFERROR( SUM( _xlfn._xlws.FILTER(_xlpm._加工金額合計列, (A17=_xlpm._依頼NO列) * (YEAR(_xlpm._月次年月日列) = YEAR(H17)) ) ), 0) )} -> 0 | J17: =IFERROR( IF( _t受注ﾌｧｲﾙ_総合計[[#This Row],[受注金額(修正)]] > _t受注ﾌｧｲﾙ_総合計[[#This Row],[加工金額合計(月次実績)]], _t受注ﾌｧｲﾙ_総合計[[#This Row],[受注金額(修正)]], _t受注ﾌｧｲﾙ_総合計[[#This Row],[加工金額合計(月次実績)]] ), 0 ) -> 10400 | K17: =IF(ISERROR(F17),0,E17) -> 10400 | L17: =_xlfn.LET( _xlpm._依頼NO, A17, _xlpm._集計年, YEAR(H17), _xlpm._依頼列, _t受注ﾌｧｲﾙ_TPI[依頼Ｎｏ], _xlpm._集計日列, _t受注ﾌｧｲﾙ_TPI[集計日], COUNTIFS( _xlpm._依頼列, _xlpm._依頼NO, _xlpm._集計日列, ">=" & DATE(_xlpm._集計年,1,1), _xlpm._集計日列, "<" & DATE(_xlpm._集計年+1,1,1) ) ) -> 0 | M17: =_xlfn.LET( _xlpm._依頼NO, A17, _xlpm._集計年, YEAR(H17), _xlpm._依頼列,_t受注ﾌｧｲﾙ_東レ[依頼Ｎｏ], _xlpm._集計日列, _t受注ﾌｧｲﾙ_東レ[集計日], COUNTIFS( _xlpm._依頼列, _xlpm._依頼NO, _xlpm._集計日列, ">=" & DATE(_xlpm._集計年,1,1), _xlpm._集計日列, "<" & DATE(_xlpm._集計年+1,1,1) ) ) -> 1 | N17: =IFERROR( INDEX( _xlfn.TEXTSPLIT( SUBSTITUTE(SUBSTITUTE(B17, "，", ","), "、", ","), ",", ), 1, 1 ), "" ) -> SEC | O17: =IFERROR( INDEX( _xlfn.TEXTSPLIT( SUBSTITUTE(SUBSTITUTE(B17, "，", ","), "、", ","), ",", ), 1, 2 ), "" ) -> 巻き返し | P17: =IFERROR( INDEX( _xlfn.TEXTSPLIT( SUBSTITUTE(SUBSTITUTE(B17, "，", ","), "、", ","), ",", ), 1, 3 ), "" ) | Q17: =IFERROR( INDEX( _xlfn.TEXTSPLIT( SUBSTITUTE(SUBSTITUTE(B17, "，", ","), "、", ","), ",", ), 1, 4 ), "" ) | R17: =IFERROR( INDEX( _xlfn.TEXTSPLIT( SUBSTITUTE(SUBSTITUTE(B17, "，", ","), "、", ","), ",", ), 1, 5 ), "" ) | T17: =IF(_t受注ﾌｧｲﾙ_総合計[[#This Row],[加工金額]]=_t受注ﾌｧｲﾙ_総合計[[#This Row],[受注金額(修正)]],TRUE) -> TRUE
A18: C6-10 | B18: ＳＥＣ | C18: 46206 | D18: 1600 1600 | E18: 41600 | F18: {=_xlfn.LET( _xlpm._完了日,_加工実績DATA[加工完了日], _xlpm._調整納期列,_t受注ﾌｧｲﾙ_総合計[調整納期], _xlpm._加工完了日,_xlfn.TAKE( _xlfn._xlws.FILTER(_xlpm._完了日, (A18=_加工実績DATA[依頼NO])* (YEAR(C18) = YEAR(_xlpm._完了日)) ),1), IF(_xlpm._加工完了日 = 0,NA(),_xlpm._加工完了日) )} -> 46205 | G18: {=_xlfn.LET( _xlpm._完了日列,#REF!, _xlpm._完了日, _xlfn.TAKE( _xlfn._xlws.FILTER(_xlpm._完了日列, (A18=#REF!)* (DATEVALUE("2025/1/1") < C18) ),1 ), IFERROR(_xlpm._完了日,"") )} | H18: {=_xlfn.LET( _xlpm.f, IFERROR(F18, 0), _xlpm.g, IFERROR(G18, 0), _xlpm.c, IFERROR(C18, 0), _xlfn.IFS( ISNUMBER(_xlpm.f)*(_xlpm.f>0), _xlpm.f, ISNUMBER(_xlpm.g)*(_xlpm.g>0), _xlpm.g, ISNUMBER(_xlpm.c)*(_xlpm.c>0), _xlpm.c, TRUE, "" ) )} -> 46205 | I18: {=_xlfn.LET( _xlpm._加工金額合計列,_t月次実績表[--合計--], _xlpm._月次年月日列,_t月次実績表[年月], _xlpm._依頼NO列,_t月次実績表[依頼NO(-1除外)], IFERROR( SUM( _xlfn._xlws.FILTER(_xlpm._加工金額合計列, (A18=_xlpm._依頼NO列) * (YEAR(_xlpm._月次年月日列) = YEAR(H18)) ) ), 0) )} -> 0 | J18: =IFERROR( IF( _t受注ﾌｧｲﾙ_総合計[[#This Row],[受注金額(修正)]] > _t受注ﾌｧｲﾙ_総合計[[#This Row],[加工金額合計(月次実績)]], _t受注ﾌｧｲﾙ_総合計[[#This Row],[受注金額(修正)]], _t受注ﾌｧｲﾙ_総合計[[#This Row],[加工金額合計(月次実績)]] ), 0 ) -> 41600 | K18: =IF(ISERROR(F18),0,E18) -> 41600 | L18: =_xlfn.LET( _xlpm._依頼NO, A18, _xlpm._集計年, YEAR(H18), _xlpm._依頼列, _t受注ﾌｧｲﾙ_TPI[依頼Ｎｏ], _xlpm._集計日列, _t受注ﾌｧｲﾙ_TPI[集計日], COUNTIFS( _xlpm._依頼列, _xlpm._依頼NO, _xlpm._集計日列, ">=" & DATE(_xlpm._集計年,1,1), _xlpm._集計日列, "<" & DATE(_xlpm._集計年+1,1,1) ) ) -> 0 | M18: =_xlfn.LET( _xlpm._依頼NO, A18, _xlpm._集計年, YEAR(H18), _xlpm._依頼列,_t受注ﾌｧｲﾙ_東レ[依頼Ｎｏ], _xlpm._集計日列, _t受注ﾌｧｲﾙ_東レ[集計日], COUNTIFS( _xlpm._依頼列, _xlpm._依頼NO, _xlpm._集計日列, ">=" & DATE(_xlpm._集計年,1,1), _xlpm._集計日列, "<" & DATE(_xlpm._集計年+1,1,1) ) ) -> 1 | N18: =IFERROR( INDEX( _xlfn.TEXTSPLIT( SUBSTITUTE(SUBSTITUTE(B18, "，", ","), "、", ","), ",", ), 1, 1 ), "" ) -> ＳＥＣ | O18: =IFERROR( INDEX( _xlfn.TEXTSPLIT( SUBSTITUTE(SUBSTITUTE(B18, "，", ","), "、", ","), ",", ), 1, 2 ), "" ) | P18: =IFERROR( INDEX( _xlfn.TEXTSPLIT( SUBSTITUTE(SUBSTITUTE(B18, "，", ","), "、", ","), ",", ), 1, 3 ), "" ) | Q18: =IFERROR( INDEX( _xlfn.TEXTSPLIT( SUBSTITUTE(SUBSTITUTE(B18, "，", ","), "、", ","), ",", ), 1, 4 ), "" ) | R18: =IFERROR( INDEX( _xlfn.TEXTSPLIT( SUBSTITUTE(SUBSTITUTE(B18, "，", ","), "、", ","), ",", ), 1, 5 ), "" ) | T18: =IF(_t受注ﾌｧｲﾙ_総合計[[#This Row],[加工金額]]=_t受注ﾌｧｲﾙ_総合計[[#This Row],[受注金額(修正)]],TRUE) -> TRUE
A19: C6-11 | B19: SEC | C19: 46209 | D19: 18800 | E19: 244400 | F19: {=_xlfn.LET( _xlpm._完了日,_加工実績DATA[加工完了日], _xlpm._調整納期列,_t受注ﾌｧｲﾙ_総合計[調整納期], _xlpm._加工完了日,_xlfn.TAKE( _xlfn._xlws.FILTER(_xlpm._完了日, (A19=_加工実績DATA[依頼NO])* (YEAR(C19) = YEAR(_xlpm._完了日)) ),1), IF(_xlpm._加工完了日 = 0,NA(),_xlpm._加工完了日) )} -> 46205 | G19: {=_xlfn.LET( _xlpm._完了日列,#REF!, _xlpm._完了日, _xlfn.TAKE( _xlfn._xlws.FILTER(_xlpm._完了日列, (A19=#REF!)* (DATEVALUE("2025/1/1") < C19) ),1 ), IFERROR(_xlpm._完了日,"") )} | H19: {=_xlfn.LET( _xlpm.f, IFERROR(F19, 0), _xlpm.g, IFERROR(G19, 0), _xlpm.c, IFERROR(C19, 0), _xlfn.IFS( ISNUMBER(_xlpm.f)*(_xlpm.f>0), _xlpm.f, ISNUMBER(_xlpm.g)*(_xlpm.g>0), _xlpm.g, ISNUMBER(_xlpm.c)*(_xlpm.c>0), _xlpm.c, TRUE, "" ) )} -> 46205 | I19: {=_xlfn.LET( _xlpm._加工金額合計列,_t月次実績表[--合計--], _xlpm._月次年月日列,_t月次実績表[年月], _xlpm._依頼NO列,_t月次実績表[依頼NO(-1除外)], IFERROR( SUM( _xlfn._xlws.FILTER(_xlpm._加工金額合計列, (A19=_xlpm._依頼NO列) * (YEAR(_xlpm._月次年月日列) = YEAR(H19)) ) ), 0) )} -> 0 | J19: =IFERROR( IF( _t受注ﾌｧｲﾙ_総合計[[#This Row],[受注金額(修正)]] > _t受注ﾌｧｲﾙ_総合計[[#This Row],[加工金額合計(月次実績)]], _t受注ﾌｧｲﾙ_総合計[[#This Row],[受注金額(修正)]], _t受注ﾌｧｲﾙ_総合計[[#This Row],[加工金額合計(月次実績)]] ), 0 ) -> 244400 | K19: =IF(ISERROR(F19),0,E19) -> 244400 | L19: =_xlfn.LET( _xlpm._依頼NO, A19, _xlpm._集計年, YEAR(H19), _xlpm._依頼列, _t受注ﾌｧｲﾙ_TPI[依頼Ｎｏ], _xlpm._集計日列, _t受注ﾌｧｲﾙ_TPI[集計日], COUNTIFS( _xlpm._依頼列, _xlpm._依頼NO, _xlpm._集計日列, ">=" & DATE(_xlpm._集計年,1,1), _xlpm._集計日列, "<" & DATE(_xlpm._集計年+1,1,1) ) ) -> 0 | M19: =_xlfn.LET( _xlpm._依頼NO, A19, _xlpm._集計年, YEAR(H19), _xlpm._依頼列,_t受注ﾌｧｲﾙ_東レ[依頼Ｎｏ], _xlpm._集計日列, _t受注ﾌｧｲﾙ_東レ[集計日], COUNTIFS( _xlpm._依頼列, _xlpm._依頼NO, _xlpm._集計日列, ">=" & DATE(_xlpm._集計年,1,1), _xlpm._集計日列, "<" & DATE(_xlpm._集計年+1,1,1) ) ) -> 1 | N19: =IFERROR( INDEX( _xlfn.TEXTSPLIT( SUBSTITUTE(SUBSTITUTE(B19, "，", ","), "、", ","), ",", ), 1, 1 ), "" ) -> SEC | O19: =IFERROR( INDEX( _xlfn.TEXTSPLIT( SUBSTITUTE(SUBSTITUTE(B19, "，", ","), "、", ","), ",", ), 1, 2 ), "" ) | P19: =IFERROR( INDEX( _xlfn.TEXTSPLIT( SUBSTITUTE(SUBSTITUTE(B19, "，", ","), "、", ","), ",", ), 1, 3 ), "" ) | Q19: =IFERROR( INDEX( _xlfn.TEXTSPLIT( SUBSTITUTE(SUBSTITUTE(B19, "，", ","), "、", ","), ",", ), 1, 4 ), "" ) | R19: =IFERROR( INDEX( _xlfn.TEXTSPLIT( SUBSTITUTE(SUBSTITUTE(B19, "，", ","), "、", ","), ",", ), 1, 5 ), "" ) | T19: =IF(_t受注ﾌｧｲﾙ_総合計[[#This Row],[加工金額]]=_t受注ﾌｧｲﾙ_総合計[[#This Row],[受注金額(修正)]],TRUE) -> TRUE
A20: C6-12 | B20: SEC | C20: 46180 | D20: 24000 | E20: 312000 | F20: {=_xlfn.LET( _xlpm._完了日,_加工実績DATA[加工完了日], _xlpm._調整納期列,_t受注ﾌｧｲﾙ_総合計[調整納期], _xlpm._加工完了日,_xlfn.TAKE( _xlfn._xlws.FILTER(_xlpm._完了日, (A20=_加工実績DATA[依頼NO])* (YEAR(C20) = YEAR(_xlpm._完了日)) ),1), IF(_xlpm._加工完了日 = 0,NA(),_xlpm._加工完了日) )} -> 46209 | G20: {=_xlfn.LET( _xlpm._完了日列,#REF!, _xlpm._完了日, _xlfn.TAKE( _xlfn._xlws.FILTER(_xlpm._完了日列, (A20=#REF!)* (DATEVALUE("2025/1/1") < C20) ),1 ), IFERROR(_xlpm._完了日,"") )} | H20: {=_xlfn.LET( _xlpm.f, IFERROR(F20, 0), _xlpm.g, IFERROR(G20, 0), _xlpm.c, IFERROR(C20, 0), _xlfn.IFS( ISNUMBER(_xlpm.f)*(_xlpm.f>0), _xlpm.f, ISNUMBER(_xlpm.g)*(_xlpm.g>0), _xlpm.g, ISNUMBER(_xlpm.c)*(_xlpm.c>0), _xlpm.c, TRUE, "" ) )} -> 46209 | I20: {=_xlfn.LET( _xlpm._加工金額合計列,_t月次実績表[--合計--], _xlpm._月次年月日列,_t月次実績表[年月], _xlpm._依頼NO列,_t月次実績表[依頼NO(-1除外)], IFERROR( SUM( _xlfn._xlws.FILTER(_xlpm._加工金額合計列, (A20=_xlpm._依頼NO列) * (YEAR(_xlpm._月次年月日列) = YEAR(H20)) ) ), 0) )} -> 0 | J20: =IFERROR( IF( _t受注ﾌｧｲﾙ_総合計[[#This Row],[受注金額(修正)]] > _t受注ﾌｧｲﾙ_総合計[[#This Row],[加工金額合計(月次実績)]], _t受注ﾌｧｲﾙ_総合計[[#This Row],[受注金額(修正)]], _t受注ﾌｧｲﾙ_総合計[[#This Row],[加工金額合計(月次実績)]] ), 0 ) -> 312000 | K20: =IF(ISERROR(F20),0,E20) -> 312000 | L20: =_xlfn.LET( _xlpm._依頼NO, A20, _xlpm._集計年, YEAR(H20), _xlpm._依頼列, _t受注ﾌｧｲﾙ_TPI[依頼Ｎｏ], _xlpm._集計日列, _t受注ﾌｧｲﾙ_TPI[集計日], COUNTIFS( _xlpm._依頼列, _xlpm._依頼NO, _xlpm._集計日列, ">=" & DATE(_xlpm._集計年,1,1), _xlpm._集計日列, "<" & DATE(_xlpm._集計年+1,1,1) ) ) -> 0 | M20: =_xlfn.LET( _xlpm._依頼NO, A20, _xlpm._集計年, YEAR(H20), _xlpm._依頼列,_t受注ﾌｧｲﾙ_東レ[依頼Ｎｏ], _xlpm._集計日列, _t受注ﾌｧｲﾙ_東レ[集計日], COUNTIFS( _xlpm._依頼列, _xlpm._依頼NO, _xlpm._集計日列, ">=" & DATE(_xlpm._集計年,1,1), _xlpm._集計日列, "<" & DATE(_xlpm._集計年+1,1,1) ) ) -> 1 | N20: =IFERROR( INDEX( _xlfn.TEXTSPLIT( SUBSTITUTE(SUBSTITUTE(B20, "，", ","), "、", ","), ",", ), 1, 1 ), "" ) -> SEC | O20: =IFERROR( INDEX( _xlfn.TEXTSPLIT( SUBSTITUTE(SUBSTITUTE(B20, "，", ","), "、", ","), ",", ), 1, 2 ), "" ) | P20: =IFERROR( INDEX( _xlfn.TEXTSPLIT( SUBSTITUTE(SUBSTITUTE(B20, "，", ","), "、", ","), ",", ), 1, 3 ), "" ) | Q20: =IFERROR( INDEX( _xlfn.TEXTSPLIT( SUBSTITUTE(SUBSTITUTE(B20, "，", ","), "、", ","), ",", ), 1, 4 ), "" ) | R20: =IFERROR( INDEX( _xlfn.TEXTSPLIT( SUBSTITUTE(SUBSTITUTE(B20, "，", ","), "、", ","), ",", ), 1, 5 ), "" ) | T20: =IF(_t受注ﾌｧｲﾙ_総合計[[#This Row],[加工金額]]=_t受注ﾌｧｲﾙ_総合計[[#This Row],[受注金額(修正)]],TRUE) -> TRUE
A21: JR260605 | B21: SEC,ｽﾘｯﾄ | C21: 46199 | D21: 190 | E21: 8170 | F21: {=_xlfn.LET( _xlpm._完了日,_加工実績DATA[加工完了日], _xlpm._調整納期列,_t受注ﾌｧｲﾙ_総合計[調整納期], _xlpm._加工完了日,_xlfn.TAKE( _xlfn._xlws.FILTER(_xlpm._完了日, (A21=_加工実績DATA[依頼NO])* (YEAR(C21) = YEAR(_xlpm._完了日)) ),1), IF(_xlpm._加工完了日 = 0,NA(),_xlpm._加工完了日) )} -> 46197 | G21: {=_xlfn.LET( _xlpm._完了日列,#REF!, _xlpm._完了日, _xlfn.TAKE( _xlfn._xlws.FILTER(_xlpm._完了日列, (A21=#REF!)* (DATEVALUE("2025/1/1") < C21) ),1 ), IFERROR(_xlpm._完了日,"") )} | H21: {=_xlfn.LET( _xlpm.f, IFERROR(F21, 0), _xlpm.g, IFERROR(G21, 0), _xlpm.c, IFERROR(C21, 0), _xlfn.IFS( ISNUMBER(_xlpm.f)*(_xlpm.f>0), _xlpm.f, ISNUMBER(_xlpm.g)*(_xlpm.g>0), _xlpm.g, ISNUMBER(_xlpm.c)*(_xlpm.c>0), _xlpm.c, TRUE, "" ) )} -> 46197 | I21: {=_xlfn.LET( _xlpm._加工金額合計列,_t月次実績表[--合計--], _xlpm._月次年月日列,_t月次実績表[年月], _xlpm._依頼NO列,_t月次実績表[依頼NO(-1除外)], IFERROR( SUM( _xlfn._xlws.FILTER(_xlpm._加工金額合計列, (A21=_xlpm._依頼NO列) * (YEAR(_xlpm._月次年月日列) = YEAR(H21)) ) ), 0) )} -> 0 | J21: =IFERROR( IF( _t受注ﾌｧｲﾙ_総合計[[#This Row],[受注金額(修正)]] > _t受注ﾌｧｲﾙ_総合計[[#This Row],[加工金額合計(月次実績)]], _t受注ﾌｧｲﾙ_総合計[[#This Row],[受注金額(修正)]], _t受注ﾌｧｲﾙ_総合計[[#This Row],[加工金額合計(月次実績)]] ), 0 ) -> 8170 | K21: =IF(ISERROR(F21),0,E21) -> 8170 | L21: =_xlfn.LET( _xlpm._依頼NO, A21, _xlpm._集計年, YEAR(H21), _xlpm._依頼列, _t受注ﾌｧｲﾙ_TPI[依頼Ｎｏ], _xlpm._集計日列, _t受注ﾌｧｲﾙ_TPI[集計日], COUNTIFS( _xlpm._依頼列, _xlpm._依頼NO, _xlpm._集計日列, ">=" & DATE(_xlpm._集計年,1,1), _xlpm._集計日列, "<" & DATE(_xlpm._集計年+1,1,1) ) ) -> 1 | M21: =_xlfn.LET( _xlpm._依頼NO, A21, _xlpm._集計年, YEAR(H21), _xlpm._依頼列,_t受注ﾌｧｲﾙ_東レ[依頼Ｎｏ], _xlpm._集計日列, _t受注ﾌｧｲﾙ_東レ[集計日], COUNTIFS( _xlpm._依頼列, _xlpm._依頼NO, _xlpm._集計日列, ">=" & DATE(_xlpm._集計年,1,1), _xlpm._集計日列, "<" & DATE(_xlpm._集計年+1,1,1) ) ) -> 0 | N21: =IFERROR( INDEX( _xlfn.TEXTSPLIT( SUBSTITUTE(SUBSTITUTE(B21, "，", ","), "、", ","), ",", ), 1, 1 ), "" ) -> SEC | O21: =IFERROR( INDEX( _xlfn.TEXTSPLIT( SUBSTITUTE(SUBSTITUTE(B21, "，", ","), "、", ","), ",", ), 1, 2 ), "" ) -> ｽﾘｯﾄ | P21: =IFERROR( INDEX( _xlfn.TEXTSPLIT( SUBSTITUTE(SUBSTITUTE(B21, "，", ","), "、", ","), ",", ), 1, 3 ), "" ) | Q21: =IFERROR( INDEX( _xlfn.TEXTSPLIT( SUBSTITUTE(SUBSTITUTE(B21, "，", ","), "、", ","), ",", ), 1, 4 ), "" ) | R21: =IFERROR( INDEX( _xlfn.TEXTSPLIT( SUBSTITUTE(SUBSTITUTE(B21, "，", ","), "、", ","), ",", ), 1, 5 ), "" ) | T21: =IF(_t受注ﾌｧｲﾙ_総合計[[#This Row],[加工金額]]=_t受注ﾌｧｲﾙ_総合計[[#This Row],[受注金額(修正)]],TRUE) -> TRUE
A22: GB60603 | B22: EC | C22: 46196 | D22: 3 | E22: 27 | F22: {=_xlfn.LET( _xlpm._完了日,_加工実績DATA[加工完了日], _xlpm._調整納期列,_t受注ﾌｧｲﾙ_総合計[調整納期], _xlpm._加工完了日,_xlfn.TAKE( _xlfn._xlws.FILTER(_xlpm._完了日, (A22=_加工実績DATA[依頼NO])* (YEAR(C22) = YEAR(_xlpm._完了日)) ),1), IF(_xlpm._加工完了日 = 0,NA(),_xlpm._加工完了日) )} -> 46196 | G22: {=_xlfn.LET( _xlpm._完了日列,#REF!, _xlpm._完了日, _xlfn.TAKE( _xlfn._xlws.FILTER(_xlpm._完了日列, (A22=#REF!)* (DATEVALUE("2025/1/1") < C22) ),1 ), IFERROR(_xlpm._完了日,"") )} | H22: {=_xlfn.LET( _xlpm.f, IFERROR(F22, 0), _xlpm.g, IFERROR(G22, 0), _xlpm.c, IFERROR(C22, 0), _xlfn.IFS( ISNUMBER(_xlpm.f)*(_xlpm.f>0), _xlpm.f, ISNUMBER(_xlpm.g)*(_xlpm.g>0), _xlpm.g, ISNUMBER(_xlpm.c)*(_xlpm.c>0), _xlpm.c, TRUE, "" ) )} -> 46196 | I22: {=_xlfn.LET( _xlpm._加工金額合計列,_t月次実績表[--合計--], _xlpm._月次年月日列,_t月次実績表[年月], _xlpm._依頼NO列,_t月次実績表[依頼NO(-1除外)], IFERROR( SUM( _xlfn._xlws.FILTER(_xlpm._加工金額合計列, (A22=_xlpm._依頼NO列) * (YEAR(_xlpm._月次年月日列) = YEAR(H22)) ) ), 0) )} -> 0 | J22: =IFERROR( IF( _t受注ﾌｧｲﾙ_総合計[[#This Row],[受注金額(修正)]] > _t受注ﾌｧｲﾙ_総合計[[#This Row],[加工金額合計(月次実績)]], _t受注ﾌｧｲﾙ_総合計[[#This Row],[受注金額(修正)]], _t受注ﾌｧｲﾙ_総合計[[#This Row],[加工金額合計(月次実績)]] ), 0 ) -> 27 | K22: =IF(ISERROR(F22),0,E22) -> 27 | L22: =_xlfn.LET( _xlpm._依頼NO, A22, _xlpm._集計年, YEAR(H22), _xlpm._依頼列, _t受注ﾌｧｲﾙ_TPI[依頼Ｎｏ], _xlpm._集計日列, _t受注ﾌｧｲﾙ_TPI[集計日], COUNTIFS( _xlpm._依頼列, _xlpm._依頼NO, _xlpm._集計日列, ">=" & DATE(_xlpm._集計年,1,1), _xlpm._集計日列, "<" & DATE(_xlpm._集計年+1,1,1) ) ) -> 1 | M22: =_xlfn.LET( _xlpm._依頼NO, A22, _xlpm._集計年, YEAR(H22), _xlpm._依頼列,_t受注ﾌｧｲﾙ_東レ[依頼Ｎｏ], _xlpm._集計日列, _t受注ﾌｧｲﾙ_東レ[集計日], COUNTIFS( _xlpm._依頼列, _xlpm._依頼NO, _xlpm._集計日列, ">=" & DATE(_xlpm._集計年,1,1), _xlpm._集計日列, "<" & DATE(_xlpm._集計年+1,1,1) ) ) -> 0 | N22: =IFERROR( INDEX( _xlfn.TEXTSPLIT( SUBSTITUTE(SUBSTITUTE(B22, "，", ","), "、", ","), ",", ), 1, 1 ), "" ) -> EC | O22: =IFERROR( INDEX( _xlfn.TEXTSPLIT( SUBSTITUTE(SUBSTITUTE(B22, "，", ","), "、", ","), ",", ), 1, 2 ), "" ) | P22: =IFERROR( INDEX( _xlfn.TEXTSPLIT( SUBSTITUTE(SUBSTITUTE(B22, "，", ","), "、", ","), ",", ), 1, 3 ), "" ) | Q22: =IFERROR( INDEX( _xlfn.TEXTSPLIT( SUBSTITUTE(SUBSTITUTE(B22, "，", ","), "、", ","), ",", ), 1, 4 ), "" ) | R22: =IFERROR( INDEX( _xlfn.TEXTSPLIT( SUBSTITUTE(SUBSTITUTE(B22, "，", ","), "、", ","), ",", ), 1, 5 ), "" ) | T22: =IF(_t受注ﾌｧｲﾙ_総合計[[#This Row],[加工金額]]=_t受注ﾌｧｲﾙ_総合計[[#This Row],[受注金額(修正)]],TRUE) -> TRUE
A23: C6-6 | B23: SEC | C23: 46202 | D23: 19600 394 | E23: 259922 | F23: {=_xlfn.LET( _xlpm._完了日,_加工実績DATA[加工完了日], _xlpm._調整納期列,_t受注ﾌｧｲﾙ_総合計[調整納期], _xlpm._加工完了日,_xlfn.TAKE( _xlfn._xlws.FILTER(_xlpm._完了日, (A23=_加工実績DATA[依頼NO])* (YEAR(C23) = YEAR(_xlpm._完了日)) ),1), IF(_xlpm._加工完了日 = 0,NA(),_xlpm._加工完了日) )} -> 46202 | G23: {=_xlfn.LET( _xlpm._完了日列,#REF!, _xlpm._完了日, _xlfn.TAKE( _xlfn._xlws.FILTER(_xlpm._完了日列, (A23=#REF!)* (DATEVALUE("2025/1/1") < C23) ),1 ), IFERROR(_xlpm._完了日,"") )} | H23: {=_xlfn.LET( _xlpm.f, IFERROR(F23, 0), _xlpm.g, IFERROR(G23, 0), _xlpm.c, IFERROR(C23, 0), _xlfn.IFS( ISNUMBER(_xlpm.f)*(_xlpm.f>0), _xlpm.f, ISNUMBER(_xlpm.g)*(_xlpm.g>0), _xlpm.g, ISNUMBER(_xlpm.c)*(_xlpm.c>0), _xlpm.c, TRUE, "" ) )} -> 46202 | I23: {=_xlfn.LET( _xlpm._加工金額合計列,_t月次実績表[--合計--], _xlpm._月次年月日列,_t月次実績表[年月], _xlpm._依頼NO列,_t月次実績表[依頼NO(-1除外)], IFERROR( SUM( _xlfn._xlws.FILTER(_xlpm._加工金額合計列, (A23=_xlpm._依頼NO列) * (YEAR(_xlpm._月次年月日列) = YEAR(H23)) ) ), 0) )} -> 0 | J23: =IFERROR( IF( _t受注ﾌｧｲﾙ_総合計[[#This Row],[受注金額(修正)]] > _t受注ﾌｧｲﾙ_総合計[[#This Row],[加工金額合計(月次実績)]], _t受注ﾌｧｲﾙ_総合計[[#This Row],[受注金額(修正)]], _t受注ﾌｧｲﾙ_総合計[[#This Row],[加工金額合計(月次実績)]] ), 0 ) -> 259922 | K23: =IF(ISERROR(F23),0,E23) -> 259922 | L23: =_xlfn.LET( _xlpm._依頼NO, A23, _xlpm._集計年, YEAR(H23), _xlpm._依頼列, _t受注ﾌｧｲﾙ_TPI[依頼Ｎｏ], _xlpm._集計日列, _t受注ﾌｧｲﾙ_TPI[集計日], COUNTIFS( _xlpm._依頼列, _xlpm._依頼NO, _xlpm._集計日列, ">=" & DATE(_xlpm._集計年,1,1), _xlpm._集計日列, "<" & DATE(_xlpm._集計年+1,1,1) ) ) -> 0 | M23: =_xlfn.LET( _xlpm._依頼NO, A23, _xlpm._集計年, YEAR(H23), _xlpm._依頼列,_t受注ﾌｧｲﾙ_東レ[依頼Ｎｏ], _xlpm._集計日列, _t受注ﾌｧｲﾙ_東レ[集計日], COUNTIFS( _xlpm._依頼列, _xlpm._依頼NO, _xlpm._集計日列, ">=" & DATE(_xlpm._集計年,1,1), _xlpm._集計日列, "<" & DATE(_xlpm._集計年+1,1,1) ) ) -> 1 | N23: =IFERROR( INDEX( _xlfn.TEXTSPLIT( SUBSTITUTE(SUBSTITUTE(B23, "，", ","), "、", ","), ",", ), 1, 1 ), "" ) -> SEC | O23: =IFERROR( INDEX( _xlfn.TEXTSPLIT( SUBSTITUTE(SUBSTITUTE(B23, "，", ","), "、", ","), ",", ), 1, 2 ), "" ) | P23: =IFERROR( INDEX( _xlfn.TEXTSPLIT( SUBSTITUTE(SUBSTITUTE(B23, "，", ","), "、", ","), ",", ), 1, 3 ), "" ) | Q23: =IFERROR( INDEX( _xlfn.TEXTSPLIT( SUBSTITUTE(SUBSTITUTE(B23, "，", ","), "、", ","), ",", ), 1, 4 ), "" ) | R23: =IFERROR( INDEX( _xlfn.TEXTSPLIT( SUBSTITUTE(SUBSTITUTE(B23, "，", ","), "、", ","), ",", ), 1, 5 ), "" ) | T23: =IF(_t受注ﾌｧｲﾙ_総合計[[#This Row],[加工金額]]=_t受注ﾌｧｲﾙ_総合計[[#This Row],[受注金額(修正)]],TRUE) -> TRUE
A24: C6-7 | B24: SEC | C24: 46203 | D24: 9800 9800 196 196 | E24: 259896 | F24: {=_xlfn.LET( _xlpm._完了日,_加工実績DATA[加工完了日], _xlpm._調整納期列,_t受注ﾌｧｲﾙ_総合計[調整納期], _xlpm._加工完了日,_xlfn.TAKE( _xlfn._xlws.FILTER(_xlpm._完了日, (A24=_加工実績DATA[依頼NO])* (YEAR(C24) = YEAR(_xlpm._完了日)) ),1), IF(_xlpm._加工完了日 = 0,NA(),_xlpm._加工完了日) )} -> 46203 | G24: {=_xlfn.LET( _xlpm._完了日列,#REF!, _xlpm._完了日, _xlfn.TAKE( _xlfn._xlws.FILTER(_xlpm._完了日列, (A24=#REF!)* (DATEVALUE("2025/1/1") < C24) ),1 ), IFERROR(_xlpm._完了日,"") )} | H24: {=_xlfn.LET( _xlpm.f, IFERROR(F24, 0), _xlpm.g, IFERROR(G24, 0), _xlpm.c, IFERROR(C24, 0), _xlfn.IFS( ISNUMBER(_xlpm.f)*(_xlpm.f>0), _xlpm.f, ISNUMBER(_xlpm.g)*(_xlpm.g>0), _xlpm.g, ISNUMBER(_xlpm.c)*(_xlpm.c>0), _xlpm.c, TRUE, "" ) )} -> 46203 | I24: {=_xlfn.LET( _xlpm._加工金額合計列,_t月次実績表[--合計--], _xlpm._月次年月日列,_t月次実績表[年月], _xlpm._依頼NO列,_t月次実績表[依頼NO(-1除外)], IFERROR( SUM( _xlfn._xlws.FILTER(_xlpm._加工金額合計列, (A24=_xlpm._依頼NO列) * (YEAR(_xlpm._月次年月日列) = YEAR(H24)) ) ), 0) )} -> 0 | J24: =IFERROR( IF( _t受注ﾌｧｲﾙ_総合計[[#This Row],[受注金額(修正)]] > _t受注ﾌｧｲﾙ_総合計[[#This Row],[加工金額合計(月次実績)]], _t受注ﾌｧｲﾙ_総合計[[#This Row],[受注金額(修正)]], _t受注ﾌｧｲﾙ_総合計[[#This Row],[加工金額合計(月次実績)]] ), 0 ) -> 259896 | K24: =IF(ISERROR(F24),0,E24) -> 259896 | L24: =_xlfn.LET( _xlpm._依頼NO, A24, _xlpm._集計年, YEAR(H24), _xlpm._依頼列, _t受注ﾌｧｲﾙ_TPI[依頼Ｎｏ], _xlpm._集計日列, _t受注ﾌｧｲﾙ_TPI[集計日], COUNTIFS( _xlpm._依頼列, _xlpm._依頼NO, _xlpm._集計日列, ">=" & DATE(_xlpm._集計年,1,1), _xlpm._集計日列, "<" & DATE(_xlpm._集計年+1,1,1) ) ) -> 0 | M24: =_xlfn.LET( _xlpm._依頼NO, A24, _xlpm._集計年, YEAR(H24), _xlpm._依頼列,_t受注ﾌｧｲﾙ_東レ[依頼Ｎｏ], _xlpm._集計日列, _t受注ﾌｧｲﾙ_東レ[集計日], COUNTIFS( _xlpm._依頼列, _xlpm._依頼NO, _xlpm._集計日列, ">=" & DATE(_xlpm._集計年,1,1), _xlpm._集計日列, "<" & DATE(_xlpm._集計年+1,1,1) ) ) -> 1 | N24: =IFERROR( INDEX( _xlfn.TEXTSPLIT( SUBSTITUTE(SUBSTITUTE(B24, "，", ","), "、", ","), ",", ), 1, 1 ), "" ) -> SEC | O24: =IFERROR( INDEX( _xlfn.TEXTSPLIT( SUBSTITUTE(SUBSTITUTE(B24, "，", ","), "、", ","), ",", ), 1, 2 ), "" ) | P24: =IFERROR( INDEX( _xlfn.TEXTSPLIT( SUBSTITUTE(SUBSTITUTE(B24, "，", ","), "、", ","), ",", ), 1, 3 ), "" ) | Q24: =IFERROR( INDEX( _xlfn.TEXTSPLIT( SUBSTITUTE(SUBSTITUTE(B24, "，", ","), "、", ","), ",", ), 1, 4 ), "" ) | R24: =IFERROR( INDEX( _xlfn.TEXTSPLIT( SUBSTITUTE(SUBSTITUTE(B24, "，", ","), "、", ","), ",", ), 1, 5 ), "" ) | T24: =IF(_t受注ﾌｧｲﾙ_総合計[[#This Row],[加工金額]]=_t受注ﾌｧｲﾙ_総合計[[#This Row],[受注金額(修正)]],TRUE) -> TRUE
A25: C6-8 | B25: ｽﾘｯﾄ | C25: 46188 | D25: 1400 197 198 199 | E25: 33898 | F25: {=_xlfn.LET( _xlpm._完了日,_加工実績DATA[加工完了日], _xlpm._調整納期列,_t受注ﾌｧｲﾙ_総合計[調整納期], _xlpm._加工完了日,_xlfn.TAKE( _xlfn._xlws.FILTER(_xlpm._完了日, (A25=_加工実績DATA[依頼NO])* (YEAR(C25) = YEAR(_xlpm._完了日)) ),1), IF(_xlpm._加工完了日 = 0,NA(),_xlpm._加工完了日) )} -> 46191 | G25: {=_xlfn.LET( _xlpm._完了日列,#REF!, _xlpm._完了日, _xlfn.TAKE( _xlfn._xlws.FILTER(_xlpm._完了日列, (A25=#REF!)* (DATEVALUE("2025/1/1") < C25) ),1 ), IFERROR(_xlpm._完了日,"") )} | H25: {=_xlfn.LET( _xlpm.f, IFERROR(F25, 0), _xlpm.g, IFERROR(G25, 0), _xlpm.c, IFERROR(C25, 0), _xlfn.IFS( ISNUMBER(_xlpm.f)*(_xlpm.f>0), _xlpm.f, ISNUMBER(_xlpm.g)*(_xlpm.g>0), _xlpm.g, ISNUMBER(_xlpm.c)*(_xlpm.c>0), _xlpm.c, TRUE, "" ) )} -> 46191 | I25: {=_xlfn.LET( _xlpm._加工金額合計列,_t月次実績表[--合計--], _xlpm._月次年月日列,_t月次実績表[年月], _xlpm._依頼NO列,_t月次実績表[依頼NO(-1除外)], IFERROR( SUM( _xlfn._xlws.FILTER(_xlpm._加工金額合計列, (A25=_xlpm._依頼NO列) * (YEAR(_xlpm._月次年月日列) = YEAR(H25)) ) ), 0) )} -> 0 | J25: =IFERROR( IF( _t受注ﾌｧｲﾙ_総合計[[#This Row],[受注金額(修正)]] > _t受注ﾌｧｲﾙ_総合計[[#This Row],[加工金額合計(月次実績)]], _t受注ﾌｧｲﾙ_総合計[[#This Row],[受注金額(修正)]], _t受注ﾌｧｲﾙ_総合計[[#This Row],[加工金額合計(月次実績)]] ), 0 ) -> 33898 | K25: =IF(ISERROR(F25),0,E25) -> 33898 | L25: =_xlfn.LET( _xlpm._依頼NO, A25, _xlpm._集計年, YEAR(H25), _xlpm._依頼列, _t受注ﾌｧｲﾙ_TPI[依頼Ｎｏ], _xlpm._集計日列, _t受注ﾌｧｲﾙ_TPI[集計日], COUNTIFS( _xlpm._依頼列, _xlpm._依頼NO, _xlpm._集計日列, ">=" & DATE(_xlpm._集計年,1,1), _xlpm._集計日列, "<" & DATE(_xlpm._集計年+1,1,1) ) ) -> 0 | M25: =_xlfn.LET( _xlpm._依頼NO, A25, _xlpm._集計年, YEAR(H25), _xlpm._依頼列,_t受注ﾌｧｲﾙ_東レ[依頼Ｎｏ], _xlpm._集計日列, _t受注ﾌｧｲﾙ_東レ[集計日], COUNTIFS( _xlpm._依頼列, _xlpm._依頼NO, _xlpm._集計日列, ">=" & DATE(_xlpm._集計年,1,1), _xlpm._集計日列, "<" & DATE(_xlpm._集計年+1,1,1) ) ) -> 1 | N25: =IFERROR( INDEX( _xlfn.TEXTSPLIT( SUBSTITUTE(SUBSTITUTE(B25, "，", ","), "、", ","), ",", ), 1, 1 ), "" ) -> ｽﾘｯﾄ | O25: =IFERROR( INDEX( _xlfn.TEXTSPLIT( SUBSTITUTE(SUBSTITUTE(B25, "，", ","), "、", ","), ",", ), 1, 2 ), "" ) | P25: =IFERROR( INDEX( _xlfn.TEXTSPLIT( SUBSTITUTE(SUBSTITUTE(B25, "，", ","), "、", ","), ",", ), 1, 3 ), "" ) | Q25: =IFERROR( INDEX( _xlfn.TEXTSPLIT( SUBSTITUTE(SUBSTITUTE(B25, "，", ","), "、", ","), ",", ), 1, 4 ), "" ) | R25: =IFERROR( INDEX( _xlfn.TEXTSPLIT( SUBSTITUTE(SUBSTITUTE(B25, "，", ","), "、", ","), ",", ), 1, 5 ), "" ) | T25: =IF(_t受注ﾌｧｲﾙ_総合計[[#This Row],[加工金額]]=_t受注ﾌｧｲﾙ_総合計[[#This Row],[受注金額(修正)]],TRUE) -> TRUE
A26: W6-18 | B26: スリット、分割 | C26: 46190 | D26: 60 240 | E26: 9600 | F26: {=_xlfn.LET( _xlpm._完了日,_加工実績DATA[加工完了日], _xlpm._調整納期列,_t受注ﾌｧｲﾙ_総合計[調整納期], _xlpm._加工完了日,_xlfn.TAKE( _xlfn._xlws.FILTER(_xlpm._完了日, (A26=_加工実績DATA[依頼NO])* (YEAR(C26) = YEAR(_xlpm._完了日)) ),1), IF(_xlpm._加工完了日 = 0,NA(),_xlpm._加工完了日) )} -> 46190 | G26: {=_xlfn.LET( _xlpm._完了日列,#REF!, _xlpm._完了日, _xlfn.TAKE( _xlfn._xlws.FILTER(_xlpm._完了日列, (A26=#REF!)* (DATEVALUE("2025/1/1") < C26) ),1 ), IFERROR(_xlpm._完了日,"") )} | H26: {=_xlfn.LET( _xlpm.f, IFERROR(F26, 0), _xlpm.g, IFERROR(G26, 0), _xlpm.c, IFERROR(C26, 0), _xlfn.IFS( ISNUMBER(_xlpm.f)*(_xlpm.f>0), _xlpm.f, ISNUMBER(_xlpm.g)*(_xlpm.g>0), _xlpm.g, ISNUMBER(_xlpm.c)*(_xlpm.c>0), _xlpm.c, TRUE, "" ) )} -> 46190 | I26: {=_xlfn.LET( _xlpm._加工金額合計列,_t月次実績表[--合計--], _xlpm._月次年月日列,_t月次実績表[年月], _xlpm._依頼NO列,_t月次実績表[依頼NO(-1除外)], IFERROR( SUM( _xlfn._xlws.FILTER(_xlpm._加工金額合計列, (A26=_xlpm._依頼NO列) * (YEAR(_xlpm._月次年月日列) = YEAR(H26)) ) ), 0) )} -> 0 | J26: =IFERROR( IF( _t受注ﾌｧｲﾙ_総合計[[#This Row],[受注金額(修正)]] > _t受注ﾌｧｲﾙ_総合計[[#This Row],[加工金額合計(月次実績)]], _t受注ﾌｧｲﾙ_総合計[[#This Row],[受注金額(修正)]], _t受注ﾌｧｲﾙ_総合計[[#This Row],[加工金額合計(月次実績)]] ), 0 ) -> 9600 | K26: =IF(ISERROR(F26),0,E26) -> 9600 | L26: =_xlfn.LET( _xlpm._依頼NO, A26, _xlpm._集計年, YEAR(H26), _xlpm._依頼列, _t受注ﾌｧｲﾙ_TPI[依頼Ｎｏ], _xlpm._集計日列, _t受注ﾌｧｲﾙ_TPI[集計日], COUNTIFS( _xlpm._依頼列, _xlpm._依頼NO, _xlpm._集計日列, ">=" & DATE(_xlpm._集計年,1,1), _xlpm._集計日列, "<" & DATE(_xlpm._集計年+1,1,1) ) ) -> 0 | M26: =_xlfn.LET( _xlpm._依頼NO, A26, _xlpm._集計年, YEAR(H26), _xlpm._依頼列,_t受注ﾌｧｲﾙ_東レ[依頼Ｎｏ], _xlpm._集計日列, _t受注ﾌｧｲﾙ_東レ[集計日], COUNTIFS( _xlpm._依頼列, _xlpm._依頼NO, _xlpm._集計日列, ">=" & DATE(_xlpm._集計年,1,1), _xlpm._集計日列, "<" & DATE(_xlpm._集計年+1,1,1) ) ) -> 1 | N26: =IFERROR( INDEX( _xlfn.TEXTSPLIT( SUBSTITUTE(SUBSTITUTE(B26, "，", ","), "、", ","), ",", ), 1, 1 ), "" ) -> スリット | O26: =IFERROR( INDEX( _xlfn.TEXTSPLIT( SUBSTITUTE(SUBSTITUTE(B26, "，", ","), "、", ","), ",", ), 1, 2 ), "" ) -> 分割 | P26: =IFERROR( INDEX( _xlfn.TEXTSPLIT( SUBSTITUTE(SUBSTITUTE(B26, "，", ","), "、", ","), ",", ), 1, 3 ), "" ) | Q26: =IFERROR( INDEX( _xlfn.TEXTSPLIT( SUBSTITUTE(SUBSTITUTE(B26, "，", ","), "、", ","), ",", ), 1, 4 ), "" ) | R26: =IFERROR( INDEX( _xlfn.TEXTSPLIT( SUBSTITUTE(SUBSTITUTE(B26, "，", ","), "、", ","), ",", ), 1, 5 ), "" ) | T26: =IF(_t受注ﾌｧｲﾙ_総合計[[#This Row],[加工金額]]=_t受注ﾌｧｲﾙ_総合計[[#This Row],[受注金額(修正)]],TRUE) -> TRUE
A27: E6-5 | B27: EC,巻き返し | C27: 46202 | D27: 3250 | E27: 100750 | F27: {=_xlfn.LET( _xlpm._完了日,_加工実績DATA[加工完了日], _xlpm._調整納期列,_t受注ﾌｧｲﾙ_総合計[調整納期], _xlpm._加工完了日,_xlfn.TAKE( _xlfn._xlws.FILTER(_xlpm._完了日, (A27=_加工実績DATA[依頼NO])* (YEAR(C27) = YEAR(_xlpm._完了日)) ),1), IF(_xlpm._加工完了日 = 0,NA(),_xlpm._加工完了日) )} -> 46192 | G27: {=_xlfn.LET( _xlpm._完了日列,#REF!, _xlpm._完了日, _xlfn.TAKE( _xlfn._xlws.FILTER(_xlpm._完了日列, (A27=#REF!)* (DATEVALUE("2025/1/1") < C27) ),1 ), IFERROR(_xlpm._完了日,"") )} | H27: {=_xlfn.LET( _xlpm.f, IFERROR(F27, 0), _xlpm.g, IFERROR(G27, 0), _xlpm.c, IFERROR(C27, 0), _xlfn.IFS( ISNUMBER(_xlpm.f)*(_xlpm.f>0), _xlpm.f, ISNUMBER(_xlpm.g)*(_xlpm.g>0), _xlpm.g, ISNUMBER(_xlpm.c)*(_xlpm.c>0), _xlpm.c, TRUE, "" ) )} -> 46192 | I27: {=_xlfn.LET( _xlpm._加工金額合計列,_t月次実績表[--合計--], _xlpm._月次年月日列,_t月次実績表[年月], _xlpm._依頼NO列,_t月次実績表[依頼NO(-1除外)], IFERROR( SUM( _xlfn._xlws.FILTER(_xlpm._加工金額合計列, (A27=_xlpm._依頼NO列) * (YEAR(_xlpm._月次年月日列) = YEAR(H27)) ) ), 0) )} -> 0 | J27: =IFERROR( IF( _t受注ﾌｧｲﾙ_総合計[[#This Row],[受注金額(修正)]] > _t受注ﾌｧｲﾙ_総合計[[#This Row],[加工金額合計(月次実績)]], _t受注ﾌｧｲﾙ_総合計[[#This Row],[受注金額(修正)]], _t受注ﾌｧｲﾙ_総合計[[#This Row],[加工金額合計(月次実績)]] ), 0 ) -> 100750 | K27: =IF(ISERROR(F27),0,E27) -> 100750 | L27: =_xlfn.LET( _xlpm._依頼NO, A27, _xlpm._集計年, YEAR(H27), _xlpm._依頼列, _t受注ﾌｧｲﾙ_TPI[依頼Ｎｏ], _xlpm._集計日列, _t受注ﾌｧｲﾙ_TPI[集計日], COUNTIFS( _xlpm._依頼列, _xlpm._依頼NO, _xlpm._集計日列, ">=" & DATE(_xlpm._集計年,1,1), _xlpm._集計日列, "<" & DATE(_xlpm._集計年+1,1,1) ) ) -> 0 | M27: =_xlfn.LET( _xlpm._依頼NO, A27, _xlpm._集計年, YEAR(H27), _xlpm._依頼列,_t受注ﾌｧｲﾙ_東レ[依頼Ｎｏ], _xlpm._集計日列, _t受注ﾌｧｲﾙ_東レ[集計日], COUNTIFS( _xlpm._依頼列, _xlpm._依頼NO, _xlpm._集計日列, ">=" & DATE(_xlpm._集計年,1,1), _xlpm._集計日列, "<" & DATE(_xlpm._集計年+1,1,1) ) ) -> 1 | N27: =IFERROR( INDEX( _xlfn.TEXTSPLIT( SUBSTITUTE(SUBSTITUTE(B27, "，", ","), "、", ","), ",", ), 1, 1 ), "" ) -> EC | O27: =IFERROR( INDEX( _xlfn.TEXTSPLIT( SUBSTITUTE(SUBSTITUTE(B27, "，", ","), "、", ","), ",", ), 1, 2 ), "" ) -> 巻き返し | P27: =IFERROR( INDEX( _xlfn.TEXTSPLIT( SUBSTITUTE(SUBSTITUTE(B27, "，", ","), "、", ","), ",", ), 1, 3 ), "" ) | Q27: =IFERROR( INDEX( _xlfn.TEXTSPLIT( SUBSTITUTE(SUBSTITUTE(B27, "，", ","), "、", ","), ",", ), 1, 4 ), "" ) | R27: =IFERROR( INDEX( _xlfn.TEXTSPLIT( SUBSTITUTE(SUBSTITUTE(B27, "，", ","), "、", ","), ",", ), 1, 5 ), "" ) | T27: =IF(_t受注ﾌｧｲﾙ_総合計[[#This Row],[加工金額]]=_t受注ﾌｧｲﾙ_総合計[[#This Row],[受注金額(修正)]],TRUE) -> TRUE
A28: Y6-29 | B28: ｴﾝﾎﾞｽ | C28: 46191 | D28: 200 | E28: 200 | F28: {=_xlfn.LET( _xlpm._完了日,_加工実績DATA[加工完了日], _xlpm._調整納期列,_t受注ﾌｧｲﾙ_総合計[調整納期], _xlpm._加工完了日,_xlfn.TAKE( _xlfn._xlws.FILTER(_xlpm._完了日, (A28=_加工実績DATA[依頼NO])* (YEAR(C28) = YEAR(_xlpm._完了日)) ),1), IF(_xlpm._加工完了日 = 0,NA(),_xlpm._加工完了日) )} -> 46190 | G28: {=_xlfn.LET( _xlpm._完了日列,#REF!, _xlpm._完了日, _xlfn.TAKE( _xlfn._xlws.FILTER(_xlpm._完了日列, (A28=#REF!)* (DATEVALUE("2025/1/1") < C28) ),1 ), IFERROR(_xlpm._完了日,"") )} | H28: {=_xlfn.LET( _xlpm.f, IFERROR(F28, 0), _xlpm.g, IFERROR(G28, 0), _xlpm.c, IFERROR(C28, 0), _xlfn.IFS( ISNUMBER(_xlpm.f)*(_xlpm.f>0), _xlpm.f, ISNUMBER(_xlpm.g)*(_xlpm.g>0), _xlpm.g, ISNUMBER(_xlpm.c)*(_xlpm.c>0), _xlpm.c, TRUE, "" ) )} -> 46190 | I28: {=_xlfn.LET( _xlpm._加工金額合計列,_t月次実績表[--合計--], _xlpm._月次年月日列,_t月次実績表[年月], _xlpm._依頼NO列,_t月次実績表[依頼NO(-1除外)], IFERROR( SUM( _xlfn._xlws.FILTER(_xlpm._加工金額合計列, (A28=_xlpm._依頼NO列) * (YEAR(_xlpm._月次年月日列) = YEAR(H28)) ) ), 0) )} -> 0 | J28: =IFERROR( IF( _t受注ﾌｧｲﾙ_総合計[[#This Row],[受注金額(修正)]] > _t受注ﾌｧｲﾙ_総合計[[#This Row],[加工金額合計(月次実績)]], _t受注ﾌｧｲﾙ_総合計[[#This Row],[受注金額(修正)]], _t受注ﾌｧｲﾙ_総合計[[#This Row],[加工金額合計(月次実績)]] ), 0 ) -> 200 | K28: =IF(ISERROR(F28),0,E28) -> 200 | L28: =_xlfn.LET( _xlpm._依頼NO, A28, _xlpm._集計年, YEAR(H28), _xlpm._依頼列, _t受注ﾌｧｲﾙ_TPI[依頼Ｎｏ], _xlpm._集計日列, _t受注ﾌｧｲﾙ_TPI[集計日], COUNTIFS( _xlpm._依頼列, _xlpm._依頼NO, _xlpm._集計日列, ">=" & DATE(_xlpm._集計年,1,1), _xlpm._集計日列, "<" & DATE(_xlpm._集計年+1,1,1) ) ) -> 0 | M28: =_xlfn.LET( _xlpm._依頼NO, A28, _xlpm._集計年, YEAR(H28), _xlpm._依頼列,_t受注ﾌｧｲﾙ_東レ[依頼Ｎｏ], _xlpm._集計日列, _t受注ﾌｧｲﾙ_東レ[集計日], COUNTIFS( _xlpm._依頼列, _xlpm._依頼NO, _xlpm._集計日列, ">=" & DATE(_xlpm._集計年,1,1), _xlpm._集計日列, "<" & DATE(_xlpm._集計年+1,1,1) ) ) -> 1 | N28: =IFERROR( INDEX( _xlfn.TEXTSPLIT( SUBSTITUTE(SUBSTITUTE(B28, "，", ","), "、", ","), ",", ), 1, 1 ), "" ) -> ｴﾝﾎﾞｽ | O28: =IFERROR( INDEX( _xlfn.TEXTSPLIT( SUBSTITUTE(SUBSTITUTE(B28, "，", ","), "、", ","), ",", ), 1, 2 ), "" ) | P28: =IFERROR( INDEX( _xlfn.TEXTSPLIT( SUBSTITUTE(SUBSTITUTE(B28, "，", ","), "、", ","), ",", ), 1, 3 ), "" ) | Q28: =IFERROR( INDEX( _xlfn.TEXTSPLIT( SUBSTITUTE(SUBSTITUTE(B28, "，", ","), "、", ","), ",", ), 1, 4 ), "" ) | R28: =IFERROR( INDEX( _xlfn.TEXTSPLIT( SUBSTITUTE(SUBSTITUTE(B28, "，", ","), "、", ","), ",", ), 1, 5 ), "" ) | T28: =IF(_t受注ﾌｧｲﾙ_総合計[[#This Row],[加工金額]]=_t受注ﾌｧｲﾙ_総合計[[#This Row],[受注金額(修正)]],TRUE) -> TRUE
A29: W6-19 | B29: ｽﾘｯﾄ，EC，検査 | C29: 46196 | D29: 2400 | E29: 132000 | F29: {=_xlfn.LET( _xlpm._完了日,_加工実績DATA[加工完了日], _xlpm._調整納期列,_t受注ﾌｧｲﾙ_総合計[調整納期], _xlpm._加工完了日,_xlfn.TAKE( _xlfn._xlws.FILTER(_xlpm._完了日, (A29=_加工実績DATA[依頼NO])* (YEAR(C29) = YEAR(_xlpm._完了日)) ),1), IF(_xlpm._加工完了日 = 0,NA(),_xlpm._加工完了日) )} -> 46192 | G29: {=_xlfn.LET( _xlpm._完了日列,#REF!, _xlpm._完了日, _xlfn.TAKE( _xlfn._xlws.FILTER(_xlpm._完了日列, (A29=#REF!)* (DATEVALUE("2025/1/1") < C29) ),1 ), IFERROR(_xlpm._完了日,"") )} | H29: {=_xlfn.LET( _xlpm.f, IFERROR(F29, 0), _xlpm.g, IFERROR(G29, 0), _xlpm.c, IFERROR(C29, 0), _xlfn.IFS( ISNUMBER(_xlpm.f)*(_xlpm.f>0), _xlpm.f, ISNUMBER(_xlpm.g)*(_xlpm.g>0), _xlpm.g, ISNUMBER(_xlpm.c)*(_xlpm.c>0), _xlpm.c, TRUE, "" ) )} -> 46192 | I29: {=_xlfn.LET( _xlpm._加工金額合計列,_t月次実績表[--合計--], _xlpm._月次年月日列,_t月次実績表[年月], _xlpm._依頼NO列,_t月次実績表[依頼NO(-1除外)], IFERROR( SUM( _xlfn._xlws.FILTER(_xlpm._加工金額合計列, (A29=_xlpm._依頼NO列) * (YEAR(_xlpm._月次年月日列) = YEAR(H29)) ) ), 0) )} -> 0 | J29: =IFERROR( IF( _t受注ﾌｧｲﾙ_総合計[[#This Row],[受注金額(修正)]] > _t受注ﾌｧｲﾙ_総合計[[#This Row],[加工金額合計(月次実績)]], _t受注ﾌｧｲﾙ_総合計[[#This Row],[受注金額(修正)]], _t受注ﾌｧｲﾙ_総合計[[#This Row],[加工金額合計(月次実績)]] ), 0 ) -> 132000 | K29: =IF(ISERROR(F29),0,E29) -> 132000 | L29: =_xlfn.LET( _xlpm._依頼NO, A29, _xlpm._集計年, YEAR(H29), _xlpm._依頼列, _t受注ﾌｧｲﾙ_TPI[依頼Ｎｏ], _xlpm._集計日列, _t受注ﾌｧｲﾙ_TPI[集計日], COUNTIFS( _xlpm._依頼列, _xlpm._依頼NO, _xlpm._集計日列, ">=" & DATE(_xlpm._集計年,1,1), _xlpm._集計日列, "<" & DATE(_xlpm._集計年+1,1,1) ) ) -> 0 | M29: =_xlfn.LET( _xlpm._依頼NO, A29, _xlpm._集計年, YEAR(H29), _xlpm._依頼列,_t受注ﾌｧｲﾙ_東レ[依頼Ｎｏ], _xlpm._集計日列, _t受注ﾌｧｲﾙ_東レ[集計日], COUNTIFS( _xlpm._依頼列, _xlpm._依頼NO, _xlpm._集計日列, ">=" & DATE(_xlpm._集計年,1,1), _xlpm._集計日列, "<" & DATE(_xlpm._集計年+1,1,1) ) ) -> 1 | N29: =IFERROR( INDEX( _xlfn.TEXTSPLIT( SUBSTITUTE(SUBSTITUTE(B29, "，", ","), "、", ","), ",", ), 1, 1 ), "" ) -> ｽﾘｯﾄ | O29: =IFERROR( INDEX( _xlfn.TEXTSPLIT( SUBSTITUTE(SUBSTITUTE(B29, "，", ","), "、", ","), ",", ), 1, 2 ), "" ) -> EC | P29: =IFERROR( INDEX( _xlfn.TEXTSPLIT( SUBSTITUTE(SUBSTITUTE(B29, "，", ","), "、", ","), ",", ), 1, 3 ), "" ) -> 検査 | Q29: =IFERROR( INDEX( _xlfn.TEXTSPLIT( SUBSTITUTE(SUBSTITUTE(B29, "，", ","), "、", ","), ",", ), 1, 4 ), "" ) | R29: =IFERROR( INDEX( _xlfn.TEXTSPLIT( SUBSTITUTE(SUBSTITUTE(B29, "，", ","), "、", ","), ",", ), 1, 5 ), "" ) | T29: =IF(_t受注ﾌｧｲﾙ_総合計[[#This Row],[加工金額]]=_t受注ﾌｧｲﾙ_総合計[[#This Row],[受注金額(修正)]],TRUE) -> TRUE
A30: W6-20 | B30: EC，検査 | C30: 46196 | D30: 6600 | E30: 250800 | F30: {=_xlfn.LET( _xlpm._完了日,_加工実績DATA[加工完了日], _xlpm._調整納期列,_t受注ﾌｧｲﾙ_総合計[調整納期], _xlpm._加工完了日,_xlfn.TAKE( _xlfn._xlws.FILTER(_xlpm._完了日, (A30=_加工実績DATA[依頼NO])* (YEAR(C30) = YEAR(_xlpm._完了日)) ),1), IF(_xlpm._加工完了日 = 0,NA(),_xlpm._加工完了日) )} -> 46196 | G30: {=_xlfn.LET( _xlpm._完了日列,#REF!, _xlpm._完了日, _xlfn.TAKE( _xlfn._xlws.FILTER(_xlpm._完了日列, (A30=#REF!)* (DATEVALUE("2025/1/1") < C30) ),1 ), IFERROR(_xlpm._完了日,"") )} | H30: {=_xlfn.LET( _xlpm.f, IFERROR(F30, 0), _xlpm.g, IFERROR(G30, 0), _xlpm.c, IFERROR(C30, 0), _xlfn.IFS( ISNUMBER(_xlpm.f)*(_xlpm.f>0), _xlpm.f, ISNUMBER(_xlpm.g)*(_xlpm.g>0), _xlpm.g, ISNUMBER(_xlpm.c)*(_xlpm.c>0), _xlpm.c, TRUE, "" ) )} -> 46196 | I30: {=_xlfn.LET( _xlpm._加工金額合計列,_t月次実績表[--合計--], _xlpm._月次年月日列,_t月次実績表[年月], _xlpm._依頼NO列,_t月次実績表[依頼NO(-1除外)], IFERROR( SUM( _xlfn._xlws.FILTER(_xlpm._加工金額合計列, (A30=_xlpm._依頼NO列) * (YEAR(_xlpm._月次年月日列) = YEAR(H30)) ) ), 0) )} -> 0 | J30: =IFERROR( IF( _t受注ﾌｧｲﾙ_総合計[[#This Row],[受注金額(修正)]] > _t受注ﾌｧｲﾙ_総合計[[#This Row],[加工金額合計(月次実績)]], _t受注ﾌｧｲﾙ_総合計[[#This Row],[受注金額(修正)]], _t受注ﾌｧｲﾙ_総合計[[#This Row],[加工金額合計(月次実績)]] ), 0 ) -> 250800 | K30: =IF(ISERROR(F30),0,E30) -> 250800 | L30: =_xlfn.LET( _xlpm._依頼NO, A30, _xlpm._集計年, YEAR(H30), _xlpm._依頼列, _t受注ﾌｧｲﾙ_TPI[依頼Ｎｏ], _xlpm._集計日列, _t受注ﾌｧｲﾙ_TPI[集計日], COUNTIFS( _xlpm._依頼列, _xlpm._依頼NO, _xlpm._集計日列, ">=" & DATE(_xlpm._集計年,1,1), _xlpm._集計日列, "<" & DATE(_xlpm._集計年+1,1,1) ) ) -> 0 | M30: =_xlfn.LET( _xlpm._依頼NO, A30, _xlpm._集計年, YEAR(H30), _xlpm._依頼列,_t受注ﾌｧｲﾙ_東レ[依頼Ｎｏ], _xlpm._集計日列, _t受注ﾌｧｲﾙ_東レ[集計日], COUNTIFS( _xlpm._依頼列, _xlpm._依頼NO, _xlpm._集計日列, ">=" & DATE(_xlpm._集計年,1,1), _xlpm._集計日列, "<" & DATE(_xlpm._集計年+1,1,1) ) ) -> 1 | N30: =IFERROR( INDEX( _xlfn.TEXTSPLIT( SUBSTITUTE(SUBSTITUTE(B30, "，", ","), "、", ","), ",", ), 1, 1 ), "" ) -> EC | O30: =IFERROR( INDEX( _xlfn.TEXTSPLIT( SUBSTITUTE(SUBSTITUTE(B30, "，", ","), "、", ","), ",", ), 1, 2 ), "" ) -> 検査 | P30: =IFERROR( INDEX( _xlfn.TEXTSPLIT( SUBSTITUTE(SUBSTITUTE(B30, "，", ","), "、", ","), ",", ), 1, 3 ), "" ) | Q30: =IFERROR( INDEX( _xlfn.TEXTSPLIT( SUBSTITUTE(SUBSTITUTE(B30, "，", ","), "、", ","), ",", ), 1, 4 ), "" ) | R30: =IFERROR( INDEX( _xlfn.TEXTSPLIT( SUBSTITUTE(SUBSTITUTE(B30, "，", ","), "、", ","), ",", ), 1, 5 ), "" ) | T30: =IF(_t受注ﾌｧｲﾙ_総合計[[#This Row],[加工金額]]=_t受注ﾌｧｲﾙ_総合計[[#This Row],[受注金額(修正)]],TRUE) -> TRUE
A31: Y6-25 | B31: ｽﾗｲｽ | C31: 46217 | D31: 20000 | E31: 220000 | F31: {=_xlfn.LET( _xlpm._完了日,_加工実績DATA[加工完了日], _xlpm._調整納期列,_t受注ﾌｧｲﾙ_総合計[調整納期], _xlpm._加工完了日,_xlfn.TAKE( _xlfn._xlws.FILTER(_xlpm._完了日, (A31=_加工実績DATA[依頼NO])* (YEAR(C31) = YEAR(_xlpm._完了日)) ),1), IF(_xlpm._加工完了日 = 0,NA(),_xlpm._加工完了日) )} -> 46213 | G31: {=_xlfn.LET( _xlpm._完了日列,#REF!, _xlpm._完了日, _xlfn.TAKE( _xlfn._xlws.FILTER(_xlpm._完了日列, (A31=#REF!)* (DATEVALUE("2025/1/1") < C31) ),1 ), IFERROR(_xlpm._完了日,"") )} | H31: {=_xlfn.LET( _xlpm.f, IFERROR(F31, 0), _xlpm.g, IFERROR(G31, 0), _xlpm.c, IFERROR(C31, 0), _xlfn.IFS( ISNUMBER(_xlpm.f)*(_xlpm.f>0), _xlpm.f, ISNUMBER(_xlpm.g)*(_xlpm.g>0), _xlpm.g, ISNUMBER(_xlpm.c)*(_xlpm.c>0), _xlpm.c, TRUE, "" ) )} -> 46213 | I31: {=_xlfn.LET( _xlpm._加工金額合計列,_t月次実績表[--合計--], _xlpm._月次年月日列,_t月次実績表[年月], _xlpm._依頼NO列,_t月次実績表[依頼NO(-1除外)], IFERROR( SUM( _xlfn._xlws.FILTER(_xlpm._加工金額合計列, (A31=_xlpm._依頼NO列) * (YEAR(_xlpm._月次年月日列) = YEAR(H31)) ) ), 0) )} -> 0 | J31: =IFERROR( IF( _t受注ﾌｧｲﾙ_総合計[[#This Row],[受注金額(修正)]] > _t受注ﾌｧｲﾙ_総合計[[#This Row],[加工金額合計(月次実績)]], _t受注ﾌｧｲﾙ_総合計[[#This Row],[受注金額(修正)]], _t受注ﾌｧｲﾙ_総合計[[#This Row],[加工金額合計(月次実績)]] ), 0 ) -> 220000 | K31: =IF(ISERROR(F31),0,E31) -> 220000 | L31: =_xlfn.LET( _xlpm._依頼NO, A31, _xlpm._集計年, YEAR(H31), _xlpm._依頼列, _t受注ﾌｧｲﾙ_TPI[依頼Ｎｏ], _xlpm._集計日列, _t受注ﾌｧｲﾙ_TPI[集計日], COUNTIFS( _xlpm._依頼列, _xlpm._依頼NO, _xlpm._集計日列, ">=" & DATE(_xlpm._集計年,1,1), _xlpm._集計日列, "<" & DATE(_xlpm._集計年+1,1,1) ) ) -> 0 | M31: =_xlfn.LET( _xlpm._依頼NO, A31, _xlpm._集計年, YEAR(H31), _xlpm._依頼列,_t受注ﾌｧｲﾙ_東レ[依頼Ｎｏ], _xlpm._集計日列, _t受注ﾌｧｲﾙ_東レ[集計日], COUNTIFS( _xlpm._依頼列, _xlpm._依頼NO, _xlpm._集計日列, ">=" & DATE(_xlpm._集計年,1,1), _xlpm._集計日列, "<" & DATE(_xlpm._集計年+1,1,1) ) ) -> 1 | N31: =IFERROR( INDEX( _xlfn.TEXTSPLIT( SUBSTITUTE(SUBSTITUTE(B31, "，", ","), "、", ","), ",", ), 1, 1 ), "" ) -> ｽﾗｲｽ | O31: =IFERROR( INDEX( _xlfn.TEXTSPLIT( SUBSTITUTE(SUBSTITUTE(B31, "，", ","), "、", ","), ",", ), 1, 2 ), "" ) | P31: =IFERROR( INDEX( _xlfn.TEXTSPLIT( SUBSTITUTE(SUBSTITUTE(B31, "，", ","), "、", ","), ",", ), 1, 3 ), "" ) | Q31: =IFERROR( INDEX( _xlfn.TEXTSPLIT( SUBSTITUTE(SUBSTITUTE(B31, "，", ","), "、", ","), ",", ), 1, 4 ), "" ) | R31: =IFERROR( INDEX( _xlfn.TEXTSPLIT( SUBSTITUTE(SUBSTITUTE(B31, "，", ","), "、", ","), ",", ), 1, 5 ), "" ) | T31: =IF(_t受注ﾌｧｲﾙ_総合計[[#This Row],[加工金額]]=_t受注ﾌｧｲﾙ_総合計[[#This Row],[受注金額(修正)]],TRUE) -> TRUE
A32: Y6-27 | B32: ｽﾗｲｽ | C32: 46197 | D32: 22200 | E32: 244200 | F32: {=_xlfn.LET( _xlpm._完了日,_加工実績DATA[加工完了日], _xlpm._調整納期列,_t受注ﾌｧｲﾙ_総合計[調整納期], _xlpm._加工完了日,_xlfn.TAKE( _xlfn._xlws.FILTER(_xlpm._完了日, (A32=_加工実績DATA[依頼NO])* (YEAR(C32) = YEAR(_xlpm._完了日)) ),1), IF(_xlpm._加工完了日 = 0,NA(),_xlpm._加工完了日) )} -> 46195 | G32: {=_xlfn.LET( _xlpm._完了日列,#REF!, _xlpm._完了日, _xlfn.TAKE( _xlfn._xlws.FILTER(_xlpm._完了日列, (A32=#REF!)* (DATEVALUE("2025/1/1") < C32) ),1 ), IFERROR(_xlpm._完了日,"") )} | H32: {=_xlfn.LET( _xlpm.f, IFERROR(F32, 0), _xlpm.g, IFERROR(G32, 0), _xlpm.c, IFERROR(C32, 0), _xlfn.IFS( ISNUMBER(_xlpm.f)*(_xlpm.f>0), _xlpm.f, ISNUMBER(_xlpm.g)*(_xlpm.g>0), _xlpm.g, ISNUMBER(_xlpm.c)*(_xlpm.c>0), _xlpm.c, TRUE, "" ) )} -> 46195 | I32: {=_xlfn.LET( _xlpm._加工金額合計列,_t月次実績表[--合計--], _xlpm._月次年月日列,_t月次実績表[年月], _xlpm._依頼NO列,_t月次実績表[依頼NO(-1除外)], IFERROR( SUM( _xlfn._xlws.FILTER(_xlpm._加工金額合計列, (A32=_xlpm._依頼NO列) * (YEAR(_xlpm._月次年月日列) = YEAR(H32)) ) ), 0) )} -> 0 | J32: =IFERROR( IF( _t受注ﾌｧｲﾙ_総合計[[#This Row],[受注金額(修正)]] > _t受注ﾌｧｲﾙ_総合計[[#This Row],[加工金額合計(月次実績)]], _t受注ﾌｧｲﾙ_総合計[[#This Row],[受注金額(修正)]], _t受注ﾌｧｲﾙ_総合計[[#This Row],[加工金額合計(月次実績)]] ), 0 ) -> 244200 | K32: =IF(ISERROR(F32),0,E32) -> 244200 | L32: =_xlfn.LET( _xlpm._依頼NO, A32, _xlpm._集計年, YEAR(H32), _xlpm._依頼列, _t受注ﾌｧｲﾙ_TPI[依頼Ｎｏ], _xlpm._集計日列, _t受注ﾌｧｲﾙ_TPI[集計日], COUNTIFS( _xlpm._依頼列, _xlpm._依頼NO, _xlpm._集計日列, ">=" & DATE(_xlpm._集計年,1,1), _xlpm._集計日列, "<" & DATE(_xlpm._集計年+1,1,1) ) ) -> 0 | M32: =_xlfn.LET( _xlpm._依頼NO, A32, _xlpm._集計年, YEAR(H32), _xlpm._依頼列,_t受注ﾌｧｲﾙ_東レ[依頼Ｎｏ], _xlpm._集計日列, _t受注ﾌｧｲﾙ_東レ[集計日], COUNTIFS( _xlpm._依頼列, _xlpm._依頼NO, _xlpm._集計日列, ">=" & DATE(_xlpm._集計年,1,1), _xlpm._集計日列, "<" & DATE(_xlpm._集計年+1,1,1) ) ) -> 1 | N32: =IFERROR( INDEX( _xlfn.TEXTSPLIT( SUBSTITUTE(SUBSTITUTE(B32, "，", ","), "、", ","), ",", ), 1, 1 ), "" ) -> ｽﾗｲｽ | O32: =IFERROR( INDEX( _xlfn.TEXTSPLIT( SUBSTITUTE(SUBSTITUTE(B32, "，", ","), "、", ","), ",", ), 1, 2 ), "" ) | P32: =IFERROR( INDEX( _xlfn.TEXTSPLIT( SUBSTITUTE(SUBSTITUTE(B32, "，", ","), "、", ","), ",", ), 1, 3 ), "" ) | Q32: =IFERROR( INDEX( _xlfn.TEXTSPLIT( SUBSTITUTE(SUBSTITUTE(B32, "，", ","), "、", ","), ",", ), 1, 4 ), "" ) | R32: =IFERROR( INDEX( _xlfn.TEXTSPLIT( SUBSTITUTE(SUBSTITUTE(B32, "，", ","), "、", ","), ",", ), 1, 5 ), "" ) | T32: =IF(_t受注ﾌｧｲﾙ_総合計[[#This Row],[加工金額]]=_t受注ﾌｧｲﾙ_総合計[[#This Row],[受注金額(修正)]],TRUE) -> TRUE
A33: Y6-28 | B33: ｽﾘｯﾄ，欠点表示 | C33: 46206 | D33: 0 | E33: 0 | F33: {=_xlfn.LET( _xlpm._完了日,_加工実績DATA[加工完了日], _xlpm._調整納期列,_t受注ﾌｧｲﾙ_総合計[調整納期], _xlpm._加工完了日,_xlfn.TAKE( _xlfn._xlws.FILTER(_xlpm._完了日, (A33=_加工実績DATA[依頼NO])* (YEAR(C33) = YEAR(_xlpm._完了日)) ),1), IF(_xlpm._加工完了日 = 0,NA(),_xlpm._加工完了日) )} -> #VALUE! | G33: {=_xlfn.LET( _xlpm._完了日列,#REF!, _xlpm._完了日, _xlfn.TAKE( _xlfn._xlws.FILTER(_xlpm._完了日列, (A33=#REF!)* (DATEVALUE("2025/1/1") < C33) ),1 ), IFERROR(_xlpm._完了日,"") )} | H33: {=_xlfn.LET( _xlpm.f, IFERROR(F33, 0), _xlpm.g, IFERROR(G33, 0), _xlpm.c, IFERROR(C33, 0), _xlfn.IFS( ISNUMBER(_xlpm.f)*(_xlpm.f>0), _xlpm.f, ISNUMBER(_xlpm.g)*(_xlpm.g>0), _xlpm.g, ISNUMBER(_xlpm.c)*(_xlpm.c>0), _xlpm.c, TRUE, "" ) )} -> 46206 | I33: {=_xlfn.LET( _xlpm._加工金額合計列,_t月次実績表[--合計--], _xlpm._月次年月日列,_t月次実績表[年月], _xlpm._依頼NO列,_t月次実績表[依頼NO(-1除外)], IFERROR( SUM( _xlfn._xlws.FILTER(_xlpm._加工金額合計列, (A33=_xlpm._依頼NO列) * (YEAR(_xlpm._月次年月日列) = YEAR(H33)) ) ), 0) )} -> 0 | J33: =IFERROR( IF( _t受注ﾌｧｲﾙ_総合計[[#This Row],[受注金額(修正)]] > _t受注ﾌｧｲﾙ_総合計[[#This Row],[加工金額合計(月次実績)]], _t受注ﾌｧｲﾙ_総合計[[#This Row],[受注金額(修正)]], _t受注ﾌｧｲﾙ_総合計[[#This Row],[加工金額合計(月次実績)]] ), 0 ) -> 0 | K33: =IF(ISERROR(F33),0,E33) -> 0 | L33: =_xlfn.LET( _xlpm._依頼NO, A33, _xlpm._集計年, YEAR(H33), _xlpm._依頼列, _t受注ﾌｧｲﾙ_TPI[依頼Ｎｏ], _xlpm._集計日列, _t受注ﾌｧｲﾙ_TPI[集計日], COUNTIFS( _xlpm._依頼列, _xlpm._依頼NO, _xlpm._集計日列, ">=" & DATE(_xlpm._集計年,1,1), _xlpm._集計日列, "<" & DATE(_xlpm._集計年+1,1,1) ) ) -> 0 | M33: =_xlfn.LET( _xlpm._依頼NO, A33, _xlpm._集計年, YEAR(H33), _xlpm._依頼列,_t受注ﾌｧｲﾙ_東レ[依頼Ｎｏ], _xlpm._集計日列, _t受注ﾌｧｲﾙ_東レ[集計日], COUNTIFS( _xlpm._依頼列, _xlpm._依頼NO, _xlpm._集計日列, ">=" & DATE(_xlpm._集計年,1,1), _xlpm._集計日列, "<" & DATE(_xlpm._集計年+1,1,1) ) ) -> 1 | N33: =IFERROR( INDEX( _xlfn.TEXTSPLIT( SUBSTITUTE(SUBSTITUTE(B33, "，", ","), "、", ","), ",", ), 1, 1 ), "" ) -> ｽﾘｯﾄ | O33: =IFERROR( INDEX( _xlfn.TEXTSPLIT( SUBSTITUTE(SUBSTITUTE(B33, "，", ","), "、", ","), ",", ), 1, 2 ), "" ) -> 欠点表示 | P33: =IFERROR( INDEX( _xlfn.TEXTSPLIT( SUBSTITUTE(SUBSTITUTE(B33, "，", ","), "、", ","), ",", ), 1, 3 ), "" ) | Q33: =IFERROR( INDEX( _xlfn.TEXTSPLIT( SUBSTITUTE(SUBSTITUTE(B33, "，", ","), "、", ","), ",", ), 1, 4 ), "" ) | R33: =IFERROR( INDEX( _xlfn.TEXTSPLIT( SUBSTITUTE(SUBSTITUTE(B33, "，", ","), "、", ","), ",", ), 1, 5 ), "" ) | T33: =IF(_t受注ﾌｧｲﾙ_総合計[[#This Row],[加工金額]]=_t受注ﾌｧｲﾙ_総合計[[#This Row],[受注金額(修正)]],TRUE) -> TRUE
A34: T6-20 | B34: EC | C34: 46195 | D34: 1600 | E34: 28800 | F34: {=_xlfn.LET( _xlpm._完了日,_加工実績DATA[加工完了日], _xlpm._調整納期列,_t受注ﾌｧｲﾙ_総合計[調整納期], _xlpm._加工完了日,_xlfn.TAKE( _xlfn._xlws.FILTER(_xlpm._完了日, (A34=_加工実績DATA[依頼NO])* (YEAR(C34) = YEAR(_xlpm._完了日)) ),1), IF(_xlpm._加工完了日 = 0,NA(),_xlpm._加工完了日) )} -> 46191 | G34: {=_xlfn.LET( _xlpm._完了日列,#REF!, _xlpm._完了日, _xlfn.TAKE( _xlfn._xlws.FILTER(_xlpm._完了日列, (A34=#REF!)* (DATEVALUE("2025/1/1") < C34) ),1 ), IFERROR(_xlpm._完了日,"") )} | H34: {=_xlfn.LET( _xlpm.f, IFERROR(F34, 0), _xlpm.g, IFERROR(G34, 0), _xlpm.c, IFERROR(C34, 0), _xlfn.IFS( ISNUMBER(_xlpm.f)*(_xlpm.f>0), _xlpm.f, ISNUMBER(_xlpm.g)*(_xlpm.g>0), _xlpm.g, ISNUMBER(_xlpm.c)*(_xlpm.c>0), _xlpm.c, TRUE, "" ) )} -> 46191 | I34: {=_xlfn.LET( _xlpm._加工金額合計列,_t月次実績表[--合計--], _xlpm._月次年月日列,_t月次実績表[年月], _xlpm._依頼NO列,_t月次実績表[依頼NO(-1除外)], IFERROR( SUM( _xlfn._xlws.FILTER(_xlpm._加工金額合計列, (A34=_xlpm._依頼NO列) * (YEAR(_xlpm._月次年月日列) = YEAR(H34)) ) ), 0) )} -> 0 | J34: =IFERROR( IF( _t受注ﾌｧｲﾙ_総合計[[#This Row],[受注金額(修正)]] > _t受注ﾌｧｲﾙ_総合計[[#This Row],[加工金額合計(月次実績)]], _t受注ﾌｧｲﾙ_総合計[[#This Row],[受注金額(修正)]], _t受注ﾌｧｲﾙ_総合計[[#This Row],[加工金額合計(月次実績)]] ), 0 ) -> 28800 | K34: =IF(ISERROR(F34),0,E34) -> 28800 | L34: =_xlfn.LET( _xlpm._依頼NO, A34, _xlpm._集計年, YEAR(H34), _xlpm._依頼列, _t受注ﾌｧｲﾙ_TPI[依頼Ｎｏ], _xlpm._集計日列, _t受注ﾌｧｲﾙ_TPI[集計日], COUNTIFS( _xlpm._依頼列, _xlpm._依頼NO, _xlpm._集計日列, ">=" & DATE(_xlpm._集計年,1,1), _xlpm._集計日列, "<" & DATE(_xlpm._集計年+1,1,1) ) ) -> 0 | M34: =_xlfn.LET( _xlpm._依頼NO, A34, _xlpm._集計年, YEAR(H34), _xlpm._依頼列,_t受注ﾌｧｲﾙ_東レ[依頼Ｎｏ], _xlpm._集計日列, _t受注ﾌｧｲﾙ_東レ[集計日], COUNTIFS( _xlpm._依頼列, _xlpm._依頼NO, _xlpm._集計日列, ">=" & DATE(_xlpm._集計年,1,1), _xlpm._集計日列, "<" & DATE(_xlpm._集計年+1,1,1) ) ) -> 1 | N34: =IFERROR( INDEX( _xlfn.TEXTSPLIT( SUBSTITUTE(SUBSTITUTE(B34, "，", ","), "、", ","), ",", ), 1, 1 ), "" ) -> EC | O34: =IFERROR( INDEX( _xlfn.TEXTSPLIT( SUBSTITUTE(SUBSTITUTE(B34, "，", ","), "、", ","), ",", ), 1, 2 ), "" ) | P34: =IFERROR( INDEX( _xlfn.TEXTSPLIT( SUBSTITUTE(SUBSTITUTE(B34, "，", ","), "、", ","), ",", ), 1, 3 ), "" ) | Q34: =IFERROR( INDEX( _xlfn.TEXTSPLIT( SUBSTITUTE(SUBSTITUTE(B34, "，", ","), "、", ","), ",", ), 1, 4 ), "" ) | R34: =IFERROR( INDEX( _xlfn.TEXTSPLIT( SUBSTITUTE(SUBSTITUTE(B34, "，", ","), "、", ","), ",", ), 1, 5 ), "" ) | T34: =IF(_t受注ﾌｧｲﾙ_総合計[[#This Row],[加工金額]]=_t受注ﾌｧｲﾙ_総合計[[#This Row],[受注金額(修正)]],TRUE) -> TRUE
A35: T6-21 | B35: エンボス | C35: 46198 | D35: 400 | E35: 6800 | F35: {=_xlfn.LET( _xlpm._完了日,_加工実績DATA[加工完了日], _xlpm._調整納期列,_t受注ﾌｧｲﾙ_総合計[調整納期], _xlpm._加工完了日,_xlfn.TAKE( _xlfn._xlws.FILTER(_xlpm._完了日, (A35=_加工実績DATA[依頼NO])* (YEAR(C35) = YEAR(_xlpm._完了日)) ),1), IF(_xlpm._加工完了日 = 0,NA(),_xlpm._加工完了日) )} -> 46190 | G35: {=_xlfn.LET( _xlpm._完了日列,#REF!, _xlpm._完了日, _xlfn.TAKE( _xlfn._xlws.FILTER(_xlpm._完了日列, (A35=#REF!)* (DATEVALUE("2025/1/1") < C35) ),1 ), IFERROR(_xlpm._完了日,"") )} | H35: {=_xlfn.LET( _xlpm.f, IFERROR(F35, 0), _xlpm.g, IFERROR(G35, 0), _xlpm.c, IFERROR(C35, 0), _xlfn.IFS( ISNUMBER(_xlpm.f)*(_xlpm.f>0), _xlpm.f, ISNUMBER(_xlpm.g)*(_xlpm.g>0), _xlpm.g, ISNUMBER(_xlpm.c)*(_xlpm.c>0), _xlpm.c, TRUE, "" ) )} -> 46190 | I35: {=_xlfn.LET( _xlpm._加工金額合計列,_t月次実績表[--合計--], _xlpm._月次年月日列,_t月次実績表[年月], _xlpm._依頼NO列,_t月次実績表[依頼NO(-1除外)], IFERROR( SUM( _xlfn._xlws.FILTER(_xlpm._加工金額合計列, (A35=_xlpm._依頼NO列) * (YEAR(_xlpm._月次年月日列) = YEAR(H35)) ) ), 0) )} -> 0 | J35: =IFERROR( IF( _t受注ﾌｧｲﾙ_総合計[[#This Row],[受注金額(修正)]] > _t受注ﾌｧｲﾙ_総合計[[#This Row],[加工金額合計(月次実績)]], _t受注ﾌｧｲﾙ_総合計[[#This Row],[受注金額(修正)]], _t受注ﾌｧｲﾙ_総合計[[#This Row],[加工金額合計(月次実績)]] ), 0 ) -> 6800 | K35: =IF(ISERROR(F35),0,E35) -> 6800 | L35: =_xlfn.LET( _xlpm._依頼NO, A35, _xlpm._集計年, YEAR(H35), _xlpm._依頼列, _t受注ﾌｧｲﾙ_TPI[依頼Ｎｏ], _xlpm._集計日列, _t受注ﾌｧｲﾙ_TPI[集計日], COUNTIFS( _xlpm._依頼列, _xlpm._依頼NO, _xlpm._集計日列, ">=" & DATE(_xlpm._集計年,1,1), _xlpm._集計日列, "<" & DATE(_xlpm._集計年+1,1,1) ) ) -> 0 | M35: =_xlfn.LET( _xlpm._依頼NO, A35, _xlpm._集計年, YEAR(H35), _xlpm._依頼列,_t受注ﾌｧｲﾙ_東レ[依頼Ｎｏ], _xlpm._集計日列, _t受注ﾌｧｲﾙ_東レ[集計日], COUNTIFS( _xlpm._依頼列, _xlpm._依頼NO, _xlpm._集計日列, ">=" & DATE(_xlpm._集計年,1,1), _xlpm._集計日列, "<" & DATE(_xlpm._集計年+1,1,1) ) ) -> 1 | N35: =IFERROR( INDEX( _xlfn.TEXTSPLIT( SUBSTITUTE(SUBSTITUTE(B35, "，", ","), "、", ","), ",", ), 1, 1 ), "" ) -> エンボス | O35: =IFERROR( INDEX( _xlfn.TEXTSPLIT( SUBSTITUTE(SUBSTITUTE(B35, "，", ","), "、", ","), ",", ), 1, 2 ), "" ) | P35: =IFERROR( INDEX( _xlfn.TEXTSPLIT( SUBSTITUTE(SUBSTITUTE(B35, "，", ","), "、", ","), ",", ), 1, 3 ), "" ) | Q35: =IFERROR( INDEX( _xlfn.TEXTSPLIT( SUBSTITUTE(SUBSTITUTE(B35, "，", ","), "、", ","), ",", ), 1, 4 ), "" ) | R35: =IFERROR( INDEX( _xlfn.TEXTSPLIT( SUBSTITUTE(SUBSTITUTE(B35, "，", ","), "、", ","), ",", ), 1, 5 ), "" ) | T35: =IF(_t受注ﾌｧｲﾙ_総合計[[#This Row],[加工金額]]=_t受注ﾌｧｲﾙ_総合計[[#This Row],[受注金額(修正)]],TRUE) -> TRUE
A36: JR260604-1 | B36: 熱融着 | C36: 46195 | D36: 190 | E36: 0 | F36: {=_xlfn.LET( _xlpm._完了日,_加工実績DATA[加工完了日], _xlpm._調整納期列,_t受注ﾌｧｲﾙ_総合計[調整納期], _xlpm._加工完了日,_xlfn.TAKE( _xlfn._xlws.FILTER(_xlpm._完了日, (A36=_加工実績DATA[依頼NO])* (YEAR(C36) = YEAR(_xlpm._完了日)) ),1), IF(_xlpm._加工完了日 = 0,NA(),_xlpm._加工完了日) )} -> 46185 | G36: {=_xlfn.LET( _xlpm._完了日列,#REF!, _xlpm._完了日, _xlfn.TAKE( _xlfn._xlws.FILTER(_xlpm._完了日列, (A36=#REF!)* (DATEVALUE("2025/1/1") < C36) ),1 ), IFERROR(_xlpm._完了日,"") )} | H36: {=_xlfn.LET( _xlpm.f, IFERROR(F36, 0), _xlpm.g, IFERROR(G36, 0), _xlpm.c, IFERROR(C36, 0), _xlfn.IFS( ISNUMBER(_xlpm.f)*(_xlpm.f>0), _xlpm.f, ISNUMBER(_xlpm.g)*(_xlpm.g>0), _xlpm.g, ISNUMBER(_xlpm.c)*(_xlpm.c>0), _xlpm.c, TRUE, "" ) )} -> 46185 | I36: {=_xlfn.LET( _xlpm._加工金額合計列,_t月次実績表[--合計--], _xlpm._月次年月日列,_t月次実績表[年月], _xlpm._依頼NO列,_t月次実績表[依頼NO(-1除外)], IFERROR( SUM( _xlfn._xlws.FILTER(_xlpm._加工金額合計列, (A36=_xlpm._依頼NO列) * (YEAR(_xlpm._月次年月日列) = YEAR(H36)) ) ), 0) )} -> 0 | J36: =IFERROR( IF( _t受注ﾌｧｲﾙ_総合計[[#This Row],[受注金額(修正)]] > _t受注ﾌｧｲﾙ_総合計[[#This Row],[加工金額合計(月次実績)]], _t受注ﾌｧｲﾙ_総合計[[#This Row],[受注金額(修正)]], _t受注ﾌｧｲﾙ_総合計[[#This Row],[加工金額合計(月次実績)]] ), 0 ) -> 0 | K36: =IF(ISERROR(F36),0,E36) -> 0 | L36: =_xlfn.LET( _xlpm._依頼NO, A36, _xlpm._集計年, YEAR(H36), _xlpm._依頼列, _t受注ﾌｧｲﾙ_TPI[依頼Ｎｏ], _xlpm._集計日列, _t受注ﾌｧｲﾙ_TPI[集計日], COUNTIFS( _xlpm._依頼列, _xlpm._依頼NO, _xlpm._集計日列, ">=" & DATE(_xlpm._集計年,1,1), _xlpm._集計日列, "<" & DATE(_xlpm._集計年+1,1,1) ) ) -> 1 | M36: =_xlfn.LET( _xlpm._依頼NO, A36, _xlpm._集計年, YEAR(H36), _xlpm._依頼列,_t受注ﾌｧｲﾙ_東レ[依頼Ｎｏ], _xlpm._集計日列, _t受注ﾌｧｲﾙ_東レ[集計日], COUNTIFS( _xlpm._依頼列, _xlpm._依頼NO, _xlpm._集計日列, ">=" & DATE(_xlpm._集計年,1,1), _xlpm._集計日列, "<" & DATE(_xlpm._集計年+1,1,1) ) ) -> 0 | N36: =IFERROR( INDEX( _xlfn.TEXTSPLIT( SUBSTITUTE(SUBSTITUTE(B36, "，", ","), "、", ","), ",", ), 1, 1 ), "" ) -> 熱融着 | O36: =IFERROR( INDEX( _xlfn.TEXTSPLIT( SUBSTITUTE(SUBSTITUTE(B36, "，", ","), "、", ","), ",", ), 1, 2 ), "" ) | P36: =IFERROR( INDEX( _xlfn.TEXTSPLIT( SUBSTITUTE(SUBSTITUTE(B36, "，", ","), "、", ","), ",", ), 1, 3 ), "" ) | Q36: =IFERROR( INDEX( _xlfn.TEXTSPLIT( SUBSTITUTE(SUBSTITUTE(B36, "，", ","), "、", ","), ",", ), 1, 4 ), "" ) | R36: =IFERROR( INDEX( _xlfn.TEXTSPLIT( SUBSTITUTE(SUBSTITUTE(B36, "，", ","), "、", ","), ",", ), 1, 5 ), "" ) | T36: =IF(_t受注ﾌｧｲﾙ_総合計[[#This Row],[加工金額]]=_t受注ﾌｧｲﾙ_総合計[[#This Row],[受注金額(修正)]],TRUE) -> TRUE
A37: W6-15 | B37: EC,欠点表示 | C37: 46190 | D37: 400 | E37: 12400 | F37: {=_xlfn.LET( _xlpm._完了日,_加工実績DATA[加工完了日], _xlpm._調整納期列,_t受注ﾌｧｲﾙ_総合計[調整納期], _xlpm._加工完了日,_xlfn.TAKE( _xlfn._xlws.FILTER(_xlpm._完了日, (A37=_加工実績DATA[依頼NO])* (YEAR(C37) = YEAR(_xlpm._完了日)) ),1), IF(_xlpm._加工完了日 = 0,NA(),_xlpm._加工完了日) )} -> 46188 | G37: {=_xlfn.LET( _xlpm._完了日列,#REF!, _xlpm._完了日, _xlfn.TAKE( _xlfn._xlws.FILTER(_xlpm._完了日列, (A37=#REF!)* (DATEVALUE("2025/1/1") < C37) ),1 ), IFERROR(_xlpm._完了日,"") )} | H37: {=_xlfn.LET( _xlpm.f, IFERROR(F37, 0), _xlpm.g, IFERROR(G37, 0), _xlpm.c, IFERROR(C37, 0), _xlfn.IFS( ISNUMBER(_xlpm.f)*(_xlpm.f>0), _xlpm.f, ISNUMBER(_xlpm.g)*(_xlpm.g>0), _xlpm.g, ISNUMBER(_xlpm.c)*(_xlpm.c>0), _xlpm.c, TRUE, "" ) )} -> 46188 | I37: {=_xlfn.LET( _xlpm._加工金額合計列,_t月次実績表[--合計--], _xlpm._月次年月日列,_t月次実績表[年月], _xlpm._依頼NO列,_t月次実績表[依頼NO(-1除外)], IFERROR( SUM( _xlfn._xlws.FILTER(_xlpm._加工金額合計列, (A37=_xlpm._依頼NO列) * (YEAR(_xlpm._月次年月日列) = YEAR(H37)) ) ), 0) )} -> 0 | J37: =IFERROR( IF( _t受注ﾌｧｲﾙ_総合計[[#This Row],[受注金額(修正)]] > _t受注ﾌｧｲﾙ_総合計[[#This Row],[加工金額合計(月次実績)]], _t受注ﾌｧｲﾙ_総合計[[#This Row],[受注金額(修正)]], _t受注ﾌｧｲﾙ_総合計[[#This Row],[加工金額合計(月次実績)]] ), 0 ) -> 12400 | K37: =IF(ISERROR(F37),0,E37) -> 12400 | L37: =_xlfn.LET( _xlpm._依頼NO, A37, _xlpm._集計年, YEAR(H37), _xlpm._依頼列, _t受注ﾌｧｲﾙ_TPI[依頼Ｎｏ], _xlpm._集計日列, _t受注ﾌｧｲﾙ_TPI[集計日], COUNTIFS( _xlpm._依頼列, _xlpm._依頼NO, _xlpm._集計日列, ">=" & DATE(_xlpm._集計年,1,1), _xlpm._集計日列, "<" & DATE(_xlpm._集計年+1,1,1) ) ) -> 0 | M37: =_xlfn.LET( _xlpm._依頼NO, A37, _xlpm._集計年, YEAR(H37), _xlpm._依頼列,_t受注ﾌｧｲﾙ_東レ[依頼Ｎｏ], _xlpm._集計日列, _t受注ﾌｧｲﾙ_東レ[集計日], COUNTIFS( _xlpm._依頼列, _xlpm._依頼NO, _xlpm._集計日列, ">=" & DATE(_xlpm._集計年,1,1), _xlpm._集計日列, "<" & DATE(_xlpm._集計年+1,1,1) ) ) -> 1 | N37: =IFERROR( INDEX( _xlfn.TEXTSPLIT( SUBSTITUTE(SUBSTITUTE(B37, "，", ","), "、", ","), ",", ), 1, 1 ), "" ) -> EC | O37: =IFERROR( INDEX( _xlfn.TEXTSPLIT( SUBSTITUTE(SUBSTITUTE(B37, "，", ","), "、", ","), ",", ), 1, 2 ), "" ) -> 欠点表示 | P37: =IFERROR( INDEX( _xlfn.TEXTSPLIT( SUBSTITUTE(SUBSTITUTE(B37, "，", ","), "、", ","), ",", ), 1, 3 ), "" ) | Q37: =IFERROR( INDEX( _xlfn.TEXTSPLIT( SUBSTITUTE(SUBSTITUTE(B37, "，", ","), "、", ","), ",", ), 1, 4 ), "" ) | R37: =IFERROR( INDEX( _xlfn.TEXTSPLIT( SUBSTITUTE(SUBSTITUTE(B37, "，", ","), "、", ","), ",", ), 1, 5 ), "" ) | T37: =IF(_t受注ﾌｧｲﾙ_総合計[[#This Row],[加工金額]]=_t受注ﾌｧｲﾙ_総合計[[#This Row],[受注金額(修正)]],TRUE) -> TRUE
A38: W6-16 | B38: EC,ｽﾘｯﾄ | C38: 46190 | D38: 500 | E38: 17500 | F38: {=_xlfn.LET( _xlpm._完了日,_加工実績DATA[加工完了日], _xlpm._調整納期列,_t受注ﾌｧｲﾙ_総合計[調整納期], _xlpm._加工完了日,_xlfn.TAKE( _xlfn._xlws.FILTER(_xlpm._完了日, (A38=_加工実績DATA[依頼NO])* (YEAR(C38) = YEAR(_xlpm._完了日)) ),1), IF(_xlpm._加工完了日 = 0,NA(),_xlpm._加工完了日) )} -> 46188 | G38: {=_xlfn.LET( _xlpm._完了日列,#REF!, _xlpm._完了日, _xlfn.TAKE( _xlfn._xlws.FILTER(_xlpm._完了日列, (A38=#REF!)* (DATEVALUE("2025/1/1") < C38) ),1 ), IFERROR(_xlpm._完了日,"") )} | H38: {=_xlfn.LET( _xlpm.f, IFERROR(F38, 0), _xlpm.g, IFERROR(G38, 0), _xlpm.c, IFERROR(C38, 0), _xlfn.IFS( ISNUMBER(_xlpm.f)*(_xlpm.f>0), _xlpm.f, ISNUMBER(_xlpm.g)*(_xlpm.g>0), _xlpm.g, ISNUMBER(_xlpm.c)*(_xlpm.c>0), _xlpm.c, TRUE, "" ) )} -> 46188 | I38: {=_xlfn.LET( _xlpm._加工金額合計列,_t月次実績表[--合計--], _xlpm._月次年月日列,_t月次実績表[年月], _xlpm._依頼NO列,_t月次実績表[依頼NO(-1除外)], IFERROR( SUM( _xlfn._xlws.FILTER(_xlpm._加工金額合計列, (A38=_xlpm._依頼NO列) * (YEAR(_xlpm._月次年月日列) = YEAR(H38)) ) ), 0) )} -> 0 | J38: =IFERROR( IF( _t受注ﾌｧｲﾙ_総合計[[#This Row],[受注金額(修正)]] > _t受注ﾌｧｲﾙ_総合計[[#This Row],[加工金額合計(月次実績)]], _t受注ﾌｧｲﾙ_総合計[[#This Row],[受注金額(修正)]], _t受注ﾌｧｲﾙ_総合計[[#This Row],[加工金額合計(月次実績)]] ), 0 ) -> 17500 | K38: =IF(ISERROR(F38),0,E38) -> 17500 | L38: =_xlfn.LET( _xlpm._依頼NO, A38, _xlpm._集計年, YEAR(H38), _xlpm._依頼列, _t受注ﾌｧｲﾙ_TPI[依頼Ｎｏ], _xlpm._集計日列, _t受注ﾌｧｲﾙ_TPI[集計日], COUNTIFS( _xlpm._依頼列, _xlpm._依頼NO, _xlpm._集計日列, ">=" & DATE(_xlpm._集計年,1,1), _xlpm._集計日列, "<" & DATE(_xlpm._集計年+1,1,1) ) ) -> 0 | M38: =_xlfn.LET( _xlpm._依頼NO, A38, _xlpm._集計年, YEAR(H38), _xlpm._依頼列,_t受注ﾌｧｲﾙ_東レ[依頼Ｎｏ], _xlpm._集計日列, _t受注ﾌｧｲﾙ_東レ[集計日], COUNTIFS( _xlpm._依頼列, _xlpm._依頼NO, _xlpm._集計日列, ">=" & DATE(_xlpm._集計年,1,1), _xlpm._集計日列, "<" & DATE(_xlpm._集計年+1,1,1) ) ) -> 1 | N38: =IFERROR( INDEX( _xlfn.TEXTSPLIT( SUBSTITUTE(SUBSTITUTE(B38, "，", ","), "、", ","), ",", ), 1, 1 ), "" ) -> EC | O38: =IFERROR( INDEX( _xlfn.TEXTSPLIT( SUBSTITUTE(SUBSTITUTE(B38, "，", ","), "、", ","), ",", ), 1, 2 ), "" ) -> ｽﾘｯﾄ | P38: =IFERROR( INDEX( _xlfn.TEXTSPLIT( SUBSTITUTE(SUBSTITUTE(B38, "，", ","), "、", ","), ",", ), 1, 3 ), "" ) | Q38: =IFERROR( INDEX( _xlfn.TEXTSPLIT( SUBSTITUTE(SUBSTITUTE(B38, "，", ","), "、", ","), ",", ), 1, 4 ), "" ) | R38: =IFERROR( INDEX( _xlfn.TEXTSPLIT( SUBSTITUTE(SUBSTITUTE(B38, "，", ","), "、", ","), ",", ), 1, 5 ), "" ) | T38: =IF(_t受注ﾌｧｲﾙ_総合計[[#This Row],[加工金額]]=_t受注ﾌｧｲﾙ_総合計[[#This Row],[受注金額(修正)]],TRUE) -> TRUE
A39: W6-17 | B39: スリット、分割 | C39: 46190 | D39: 60 60 | E39: 3840 | F39: {=_xlfn.LET( _xlpm._完了日,_加工実績DATA[加工完了日], _xlpm._調整納期列,_t受注ﾌｧｲﾙ_総合計[調整納期], _xlpm._加工完了日,_xlfn.TAKE( _xlfn._xlws.FILTER(_xlpm._完了日, (A39=_加工実績DATA[依頼NO])* (YEAR(C39) = YEAR(_xlpm._完了日)) ),1), IF(_xlpm._加工完了日 = 0,NA(),_xlpm._加工完了日) )} -> 46190 | G39: {=_xlfn.LET( _xlpm._完了日列,#REF!, _xlpm._完了日, _xlfn.TAKE( _xlfn._xlws.FILTER(_xlpm._完了日列, (A39=#REF!)* (DATEVALUE("2025/1/1") < C39) ),1 ), IFERROR(_xlpm._完了日,"") )} | H39: {=_xlfn.LET( _xlpm.f, IFERROR(F39, 0), _xlpm.g, IFERROR(G39, 0), _xlpm.c, IFERROR(C39, 0), _xlfn.IFS( ISNUMBER(_xlpm.f)*(_xlpm.f>0), _xlpm.f, ISNUMBER(_xlpm.g)*(_xlpm.g>0), _xlpm.g, ISNUMBER(_xlpm.c)*(_xlpm.c>0), _xlpm.c, TRUE, "" ) )} -> 46190 | I39: {=_xlfn.LET( _xlpm._加工金額合計列,_t月次実績表[--合計--], _xlpm._月次年月日列,_t月次実績表[年月], _xlpm._依頼NO列,_t月次実績表[依頼NO(-1除外)], IFERROR( SUM( _xlfn._xlws.FILTER(_xlpm._加工金額合計列, (A39=_xlpm._依頼NO列) * (YEAR(_xlpm._月次年月日列) = YEAR(H39)) ) ), 0) )} -> 0 | J39: =IFERROR( IF( _t受注ﾌｧｲﾙ_総合計[[#This Row],[受注金額(修正)]] > _t受注ﾌｧｲﾙ_総合計[[#This Row],[加工金額合計(月次実績)]], _t受注ﾌｧｲﾙ_総合計[[#This Row],[受注金額(修正)]], _t受注ﾌｧｲﾙ_総合計[[#This Row],[加工金額合計(月次実績)]] ), 0 ) -> 3840 | K39: =IF(ISERROR(F39),0,E39) -> 3840 | L39: =_xlfn.LET( _xlpm._依頼NO, A39, _xlpm._集計年, YEAR(H39), _xlpm._依頼列, _t受注ﾌｧｲﾙ_TPI[依頼Ｎｏ], _xlpm._集計日列, _t受注ﾌｧｲﾙ_TPI[集計日], COUNTIFS( _xlpm._依頼列, _xlpm._依頼NO, _xlpm._集計日列, ">=" & DATE(_xlpm._集計年,1,1), _xlpm._集計日列, "<" & DATE(_xlpm._集計年+1,1,1) ) ) -> 0 | M39: =_xlfn.LET( _xlpm._依頼NO, A39, _xlpm._集計年, YEAR(H39), _xlpm._依頼列,_t受注ﾌｧｲﾙ_東レ[依頼Ｎｏ], _xlpm._集計日列, _t受注ﾌｧｲﾙ_東レ[集計日], COUNTIFS( _xlpm._依頼列, _xlpm._依頼NO, _xlpm._集計日列, ">=" & DATE(_xlpm._集計年,1,1), _xlpm._集計日列, "<" & DATE(_xlpm._集計年+1,1,1) ) ) -> 1 | N39: =IFERROR( INDEX( _xlfn.TEXTSPLIT( SUBSTITUTE(SUBSTITUTE(B39, "，", ","), "、", ","), ",", ), 1, 1 ), "" ) -> スリット | O39: =IFERROR( INDEX( _xlfn.TEXTSPLIT( SUBSTITUTE(SUBSTITUTE(B39, "，", ","), "、", ","), ",", ), 1, 2 ), "" ) -> 分割 | P39: =IFERROR( INDEX( _xlfn.TEXTSPLIT( SUBSTITUTE(SUBSTITUTE(B39, "，", ","), "、", ","), ",", ), 1, 3 ), "" ) | Q39: =IFERROR( INDEX( _xlfn.TEXTSPLIT( SUBSTITUTE(SUBSTITUTE(B39, "，", ","), "、", ","), ",", ), 1, 4 ), "" ) | R39: =IFERROR( INDEX( _xlfn.TEXTSPLIT( SUBSTITUTE(SUBSTITUTE(B39, "，", ","), "、", ","), ",", ), 1, 5 ), "" ) | T39: =IF(_t受注ﾌｧｲﾙ_総合計[[#This Row],[加工金額]]=_t受注ﾌｧｲﾙ_総合計[[#This Row],[受注金額(修正)]],TRUE) -> TRUE
A40: T6-19 | B40: EC | C40: 46195 | D40: 800 | E40: 14400 | F40: {=_xlfn.LET( _xlpm._完了日,_加工実績DATA[加工完了日], _xlpm._調整納期列,_t受注ﾌｧｲﾙ_総合計[調整納期], _xlpm._加工完了日,_xlfn.TAKE( _xlfn._xlws.FILTER(_xlpm._完了日, (A40=_加工実績DATA[依頼NO])* (YEAR(C40) = YEAR(_xlpm._完了日)) ),1), IF(_xlpm._加工完了日 = 0,NA(),_xlpm._加工完了日) )} -> 46188 | G40: {=_xlfn.LET( _xlpm._完了日列,#REF!, _xlpm._完了日, _xlfn.TAKE( _xlfn._xlws.FILTER(_xlpm._完了日列, (A40=#REF!)* (DATEVALUE("2025/1/1") < C40) ),1 ), IFERROR(_xlpm._完了日,"") )} | H40: {=_xlfn.LET( _xlpm.f, IFERROR(F40, 0), _xlpm.g, IFERROR(G40, 0), _xlpm.c, IFERROR(C40, 0), _xlfn.IFS( ISNUMBER(_xlpm.f)*(_xlpm.f>0), _xlpm.f, ISNUMBER(_xlpm.g)*(_xlpm.g>0), _xlpm.g, ISNUMBER(_xlpm.c)*(_xlpm.c>0), _xlpm.c, TRUE, "" ) )} -> 46188 | I40: {=_xlfn.LET( _xlpm._加工金額合計列,_t月次実績表[--合計--], _xlpm._月次年月日列,_t月次実績表[年月], _xlpm._依頼NO列,_t月次実績表[依頼NO(-1除外)], IFERROR( SUM( _xlfn._xlws.FILTER(_xlpm._加工金額合計列, (A40=_xlpm._依頼NO列) * (YEAR(_xlpm._月次年月日列) = YEAR(H40)) ) ), 0) )} -> 0 | J40: =IFERROR( IF( _t受注ﾌｧｲﾙ_総合計[[#This Row],[受注金額(修正)]] > _t受注ﾌｧｲﾙ_総合計[[#This Row],[加工金額合計(月次実績)]], _t受注ﾌｧｲﾙ_総合計[[#This Row],[受注金額(修正)]], _t受注ﾌｧｲﾙ_総合計[[#This Row],[加工金額合計(月次実績)]] ), 0 ) -> 14400 | K40: =IF(ISERROR(F40),0,E40) -> 14400 | L40: =_xlfn.LET( _xlpm._依頼NO, A40, _xlpm._集計年, YEAR(H40), _xlpm._依頼列, _t受注ﾌｧｲﾙ_TPI[依頼Ｎｏ], _xlpm._集計日列, _t受注ﾌｧｲﾙ_TPI[集計日], COUNTIFS( _xlpm._依頼列, _xlpm._依頼NO, _xlpm._集計日列, ">=" & DATE(_xlpm._集計年,1,1), _xlpm._集計日列, "<" & DATE(_xlpm._集計年+1,1,1) ) ) -> 0 | M40: =_xlfn.LET( _xlpm._依頼NO, A40, _xlpm._集計年, YEAR(H40), _xlpm._依頼列,_t受注ﾌｧｲﾙ_東レ[依頼Ｎｏ], _xlpm._集計日列, _t受注ﾌｧｲﾙ_東レ[集計日], COUNTIFS( _xlpm._依頼列, _xlpm._依頼NO, _xlpm._集計日列, ">=" & DATE(_xlpm._集計年,1,1), _xlpm._集計日列, "<" & DATE(_xlpm._集計年+1,1,1) ) ) -> 1 | N40: =IFERROR( INDEX( _xlfn.TEXTSPLIT( SUBSTITUTE(SUBSTITUTE(B40, "，", ","), "、", ","), ",", ), 1, 1 ), "" ) -> EC | O40: =IFERROR( INDEX( _xlfn.TEXTSPLIT( SUBSTITUTE(SUBSTITUTE(B40, "，", ","), "、", ","), ",", ), 1, 2 ), "" ) | P40: =IFERROR( INDEX( _xlfn.TEXTSPLIT( SUBSTITUTE(SUBSTITUTE(B40, "，", ","), "、", ","), ",", ), 1, 3 ), "" ) | Q40: =IFERROR( INDEX( _xlfn.TEXTSPLIT( SUBSTITUTE(SUBSTITUTE(B40, "，", ","), "、", ","), ",", ), 1, 4 ), "" ) | R40: =IFERROR( INDEX( _xlfn.TEXTSPLIT( SUBSTITUTE(SUBSTITUTE(B40, "，", ","), "、", ","), ",", ), 1, 5 ), "" ) | T40: =IF(_t受注ﾌｧｲﾙ_総合計[[#This Row],[加工金額]]=_t受注ﾌｧｲﾙ_総合計[[#This Row],[受注金額(修正)]],TRUE) -> TRUE
A41: V6-14 | B41: 分割 | C41: 46203 | D41: 7000 | E41: 105000 | F41: {=_xlfn.LET( _xlpm._完了日,_加工実績DATA[加工完了日], _xlpm._調整納期列,_t受注ﾌｧｲﾙ_総合計[調整納期], _xlpm._加工完了日,_xlfn.TAKE( _xlfn._xlws.FILTER(_xlpm._完了日, (A41=_加工実績DATA[依頼NO])* (YEAR(C41) = YEAR(_xlpm._完了日)) ),1), IF(_xlpm._加工完了日 = 0,NA(),_xlpm._加工完了日) )} -> 46197 | G41: {=_xlfn.LET( _xlpm._完了日列,#REF!, _xlpm._完了日, _xlfn.TAKE( _xlfn._xlws.FILTER(_xlpm._完了日列, (A41=#REF!)* (DATEVALUE("2025/1/1") < C41) ),1 ), IFERROR(_xlpm._完了日,"") )} | H41: {=_xlfn.LET( _xlpm.f, IFERROR(F41, 0), _xlpm.g, IFERROR(G41, 0), _xlpm.c, IFERROR(C41, 0), _xlfn.IFS( ISNUMBER(_xlpm.f)*(_xlpm.f>0), _xlpm.f, ISNUMBER(_xlpm.g)*(_xlpm.g>0), _xlpm.g, ISNUMBER(_xlpm.c)*(_xlpm.c>0), _xlpm.c, TRUE, "" ) )} -> 46197 | I41: {=_xlfn.LET( _xlpm._加工金額合計列,_t月次実績表[--合計--], _xlpm._月次年月日列,_t月次実績表[年月], _xlpm._依頼NO列,_t月次実績表[依頼NO(-1除外)], IFERROR( SUM( _xlfn._xlws.FILTER(_xlpm._加工金額合計列, (A41=_xlpm._依頼NO列) * (YEAR(_xlpm._月次年月日列) = YEAR(H41)) ) ), 0) )} -> 0 | J41: =IFERROR( IF( _t受注ﾌｧｲﾙ_総合計[[#This Row],[受注金額(修正)]] > _t受注ﾌｧｲﾙ_総合計[[#This Row],[加工金額合計(月次実績)]], _t受注ﾌｧｲﾙ_総合計[[#This Row],[受注金額(修正)]], _t受注ﾌｧｲﾙ_総合計[[#This Row],[加工金額合計(月次実績)]] ), 0 ) -> 105000 | K41: =IF(ISERROR(F41),0,E41) -> 105000 | L41: =_xlfn.LET( _xlpm._依頼NO, A41, _xlpm._集計年, YEAR(H41), _xlpm._依頼列, _t受注ﾌｧｲﾙ_TPI[依頼Ｎｏ], _xlpm._集計日列, _t受注ﾌｧｲﾙ_TPI[集計日], COUNTIFS( _xlpm._依頼列, _xlpm._依頼NO, _xlpm._集計日列, ">=" & DATE(_xlpm._集計年,1,1), _xlpm._集計日列, "<" & DATE(_xlpm._集計年+1,1,1) ) ) -> 0 | M41: =_xlfn.LET( _xlpm._依頼NO, A41, _xlpm._集計年, YEAR(H41), _xlpm._依頼列,_t受注ﾌｧｲﾙ_東レ[依頼Ｎｏ], _xlpm._集計日列, _t受注ﾌｧｲﾙ_東レ[集計日], COUNTIFS( _xlpm._依頼列, _xlpm._依頼NO, _xlpm._集計日列, ">=" & DATE(_xlpm._集計年,1,1), _xlpm._集計日列, "<" & DATE(_xlpm._集計年+1,1,1) ) ) -> 1 | N41: =IFERROR( INDEX( _xlfn.TEXTSPLIT( SUBSTITUTE(SUBSTITUTE(B41, "，", ","), "、", ","), ",", ), 1, 1 ), "" ) -> 分割 | O41: =IFERROR( INDEX( _xlfn.TEXTSPLIT( SUBSTITUTE(SUBSTITUTE(B41, "，", ","), "、", ","), ",", ), 1, 2 ), "" ) | P41: =IFERROR( INDEX( _xlfn.TEXTSPLIT( SUBSTITUTE(SUBSTITUTE(B41, "，", ","), "、", ","), ",", ), 1, 3 ), "" ) | Q41: =IFERROR( INDEX( _xlfn.TEXTSPLIT( SUBSTITUTE(SUBSTITUTE(B41, "，", ","), "、", ","), ",", ), 1, 4 ), "" ) | R41: =IFERROR( INDEX( _xlfn.TEXTSPLIT( SUBSTITUTE(SUBSTITUTE(B41, "，", ","), "、", ","), ",", ), 1, 5 ), "" ) | T41: =IF(_t受注ﾌｧｲﾙ_総合計[[#This Row],[加工金額]]=_t受注ﾌｧｲﾙ_総合計[[#This Row],[受注金額(修正)]],TRUE) -> TRUE
A42: V6-15 | B42: 分割 | C42: 46203 | D42: 3100 | E42: 46500 | F42: {=_xlfn.LET( _xlpm._完了日,_加工実績DATA[加工完了日], _xlpm._調整納期列,_t受注ﾌｧｲﾙ_総合計[調整納期], _xlpm._加工完了日,_xlfn.TAKE( _xlfn._xlws.FILTER(_xlpm._完了日, (A42=_加工実績DATA[依頼NO])* (YEAR(C42) = YEAR(_xlpm._完了日)) ),1), IF(_xlpm._加工完了日 = 0,NA(),_xlpm._加工完了日) )} -> 46202 | G42: {=_xlfn.LET( _xlpm._完了日列,#REF!, _xlpm._完了日, _xlfn.TAKE( _xlfn._xlws.FILTER(_xlpm._完了日列, (A42=#REF!)* (DATEVALUE("2025/1/1") < C42) ),1 ), IFERROR(_xlpm._完了日,"") )} | H42: {=_xlfn.LET( _xlpm.f, IFERROR(F42, 0), _xlpm.g, IFERROR(G42, 0), _xlpm.c, IFERROR(C42, 0), _xlfn.IFS( ISNUMBER(_xlpm.f)*(_xlpm.f>0), _xlpm.f, ISNUMBER(_xlpm.g)*(_xlpm.g>0), _xlpm.g, ISNUMBER(_xlpm.c)*(_xlpm.c>0), _xlpm.c, TRUE, "" ) )} -> 46202 | I42: {=_xlfn.LET( _xlpm._加工金額合計列,_t月次実績表[--合計--], _xlpm._月次年月日列,_t月次実績表[年月], _xlpm._依頼NO列,_t月次実績表[依頼NO(-1除外)], IFERROR( SUM( _xlfn._xlws.FILTER(_xlpm._加工金額合計列, (A42=_xlpm._依頼NO列) * (YEAR(_xlpm._月次年月日列) = YEAR(H42)) ) ), 0) )} -> 0 | J42: =IFERROR( IF( _t受注ﾌｧｲﾙ_総合計[[#This Row],[受注金額(修正)]] > _t受注ﾌｧｲﾙ_総合計[[#This Row],[加工金額合計(月次実績)]], _t受注ﾌｧｲﾙ_総合計[[#This Row],[受注金額(修正)]], _t受注ﾌｧｲﾙ_総合計[[#This Row],[加工金額合計(月次実績)]] ), 0 ) -> 46500 | K42: =IF(ISERROR(F42),0,E42) -> 46500 | L42: =_xlfn.LET( _xlpm._依頼NO, A42, _xlpm._集計年, YEAR(H42), _xlpm._依頼列, _t受注ﾌｧｲﾙ_TPI[依頼Ｎｏ], _xlpm._集計日列, _t受注ﾌｧｲﾙ_TPI[集計日], COUNTIFS( _xlpm._依頼列, _xlpm._依頼NO, _xlpm._集計日列, ">=" & DATE(_xlpm._集計年,1,1), _xlpm._集計日列, "<" & DATE(_xlpm._集計年+1,1,1) ) ) -> 0 | M42: =_xlfn.LET( _xlpm._依頼NO, A42, _xlpm._集計年, YEAR(H42), _xlpm._依頼列,_t受注ﾌｧｲﾙ_東レ[依頼Ｎｏ], _xlpm._集計日列, _t受注ﾌｧｲﾙ_東レ[集計日], COUNTIFS( _xlpm._依頼列, _xlpm._依頼NO, _xlpm._集計日列, ">=" & DATE(_xlpm._集計年,1,1), _xlpm._集計日列, "<" & DATE(_xlpm._集計年+1,1,1) ) ) -> 1 | N42: =IFERROR( INDEX( _xlfn.TEXTSPLIT( SUBSTITUTE(SUBSTITUTE(B42, "，", ","), "、", ","), ",", ), 1, 1 ), "" ) -> 分割 | O42: =IFERROR( INDEX( _xlfn.TEXTSPLIT( SUBSTITUTE(SUBSTITUTE(B42, "，", ","), "、", ","), ",", ), 1, 2 ), "" ) | P42: =IFERROR( INDEX( _xlfn.TEXTSPLIT( SUBSTITUTE(SUBSTITUTE(B42, "，", ","), "、", ","), ",", ), 1, 3 ), "" ) | Q42: =IFERROR( INDEX( _xlfn.TEXTSPLIT( SUBSTITUTE(SUBSTITUTE(B42, "，", ","), "、", ","), ",", ), 1, 4 ), "" ) | R42: =IFERROR( INDEX( _xlfn.TEXTSPLIT( SUBSTITUTE(SUBSTITUTE(B42, "，", ","), "、", ","), ",", ), 1, 5 ), "" ) | T42: =IF(_t受注ﾌｧｲﾙ_総合計[[#This Row],[加工金額]]=_t受注ﾌｧｲﾙ_総合計[[#This Row],[受注金額(修正)]],TRUE) -> TRUE
A43: Y6-16 | B43: ｽﾗｲｽ | C43: 46190 | D43: 16200 | E43: 178200 | F43: {=_xlfn.LET( _xlpm._完了日,_加工実績DATA[加工完了日], _xlpm._調整納期列,_t受注ﾌｧｲﾙ_総合計[調整納期], _xlpm._加工完了日,_xlfn.TAKE( _xlfn._xlws.FILTER(_xlpm._完了日, (A43=_加工実績DATA[依頼NO])* (YEAR(C43) = YEAR(_xlpm._完了日)) ),1), IF(_xlpm._加工完了日 = 0,NA(),_xlpm._加工完了日) )} -> 46185 | G43: {=_xlfn.LET( _xlpm._完了日列,#REF!, _xlpm._完了日, _xlfn.TAKE( _xlfn._xlws.FILTER(_xlpm._完了日列, (A43=#REF!)* (DATEVALUE("2025/1/1") < C43) ),1 ), IFERROR(_xlpm._完了日,"") )} | H43: {=_xlfn.LET( _xlpm.f, IFERROR(F43, 0), _xlpm.g, IFERROR(G43, 0), _xlpm.c, IFERROR(C43, 0), _xlfn.IFS( ISNUMBER(_xlpm.f)*(_xlpm.f>0), _xlpm.f, ISNUMBER(_xlpm.g)*(_xlpm.g>0), _xlpm.g, ISNUMBER(_xlpm.c)*(_xlpm.c>0), _xlpm.c, TRUE, "" ) )} -> 46185 | I43: {=_xlfn.LET( _xlpm._加工金額合計列,_t月次実績表[--合計--], _xlpm._月次年月日列,_t月次実績表[年月], _xlpm._依頼NO列,_t月次実績表[依頼NO(-1除外)], IFERROR( SUM( _xlfn._xlws.FILTER(_xlpm._加工金額合計列, (A43=_xlpm._依頼NO列) * (YEAR(_xlpm._月次年月日列) = YEAR(H43)) ) ), 0) )} -> 0 | J43: =IFERROR( IF( _t受注ﾌｧｲﾙ_総合計[[#This Row],[受注金額(修正)]] > _t受注ﾌｧｲﾙ_総合計[[#This Row],[加工金額合計(月次実績)]], _t受注ﾌｧｲﾙ_総合計[[#This Row],[受注金額(修正)]], _t受注ﾌｧｲﾙ_総合計[[#This Row],[加工金額合計(月次実績)]] ), 0 ) -> 178200 | K43: =IF(ISERROR(F43),0,E43) -> 178200 | L43: =_xlfn.LET( _xlpm._依頼NO, A43, _xlpm._集計年, YEAR(H43), _xlpm._依頼列, _t受注ﾌｧｲﾙ_TPI[依頼Ｎｏ], _xlpm._集計日列, _t受注ﾌｧｲﾙ_TPI[集計日], COUNTIFS( _xlpm._依頼列, _xlpm._依頼NO, _xlpm._集計日列, ">=" & DATE(_xlpm._集計年,1,1), _xlpm._集計日列, "<" & DATE(_xlpm._集計年+1,1,1) ) ) -> 0 | M43: =_xlfn.LET( _xlpm._依頼NO, A43, _xlpm._集計年, YEAR(H43), _xlpm._依頼列,_t受注ﾌｧｲﾙ_東レ[依頼Ｎｏ], _xlpm._集計日列, _t受注ﾌｧｲﾙ_東レ[集計日], COUNTIFS( _xlpm._依頼列, _xlpm._依頼NO, _xlpm._集計日列, ">=" & DATE(_xlpm._集計年,1,1), _xlpm._集計日列, "<" & DATE(_xlpm._集計年+1,1,1) ) ) -> 1 | N43: =IFERROR( INDEX( _xlfn.TEXTSPLIT( SUBSTITUTE(SUBSTITUTE(B43, "，", ","), "、", ","), ",", ), 1, 1 ), "" ) -> ｽﾗｲｽ | O43: =IFERROR( INDEX( _xlfn.TEXTSPLIT( SUBSTITUTE(SUBSTITUTE(B43, "，", ","), "、", ","), ",", ), 1, 2 ), "" ) | P43: =IFERROR( INDEX( _xlfn.TEXTSPLIT( SUBSTITUTE(SUBSTITUTE(B43, "，", ","), "、", ","), ",", ), 1, 3 ), "" ) | Q43: =IFERROR( INDEX( _xlfn.TEXTSPLIT( SUBSTITUTE(SUBSTITUTE(B43, "，", ","), "、", ","), ",", ), 1, 4 ), "" ) | R43: =IFERROR( INDEX( _xlfn.TEXTSPLIT( SUBSTITUTE(SUBSTITUTE(B43, "，", ","), "、", ","), ",", ), 1, 5 ), "" ) | T43: =IF(_t受注ﾌｧｲﾙ_総合計[[#This Row],[加工金額]]=_t受注ﾌｧｲﾙ_総合計[[#This Row],[受注金額(修正)]],TRUE) -> TRUE
A44: T6-15 | B44: スライス | C44: 46195 | D44: 300 | E44: 3300 | F44: {=_xlfn.LET( _xlpm._完了日,_加工実績DATA[加工完了日], _xlpm._調整納期列,_t受注ﾌｧｲﾙ_総合計[調整納期], _xlpm._加工完了日,_xlfn.TAKE( _xlfn._xlws.FILTER(_xlpm._完了日, (A44=_加工実績DATA[依頼NO])* (YEAR(C44) = YEAR(_xlpm._完了日)) ),1), IF(_xlpm._加工完了日 = 0,NA(),_xlpm._加工完了日) )} -> 46190 | G44: {=_xlfn.LET( _xlpm._完了日列,#REF!, _xlpm._完了日, _xlfn.TAKE( _xlfn._xlws.FILTER(_xlpm._完了日列, (A44=#REF!)* (DATEVALUE("2025/1/1") < C44) ),1 ), IFERROR(_xlpm._完了日,"") )} | H44: {=_xlfn.LET( _xlpm.f, IFERROR(F44, 0), _xlpm.g, IFERROR(G44, 0), _xlpm.c, IFERROR(C44, 0), _xlfn.IFS( ISNUMBER(_xlpm.f)*(_xlpm.f>0), _xlpm.f, ISNUMBER(_xlpm.g)*(_xlpm.g>0), _xlpm.g, ISNUMBER(_xlpm.c)*(_xlpm.c>0), _xlpm.c, TRUE, "" ) )} -> 46190 | I44: {=_xlfn.LET( _xlpm._加工金額合計列,_t月次実績表[--合計--], _xlpm._月次年月日列,_t月次実績表[年月], _xlpm._依頼NO列,_t月次実績表[依頼NO(-1除外)], IFERROR( SUM( _xlfn._xlws.FILTER(_xlpm._加工金額合計列, (A44=_xlpm._依頼NO列) * (YEAR(_xlpm._月次年月日列) = YEAR(H44)) ) ), 0) )} -> 0 | J44: =IFERROR( IF( _t受注ﾌｧｲﾙ_総合計[[#This Row],[受注金額(修正)]] > _t受注ﾌｧｲﾙ_総合計[[#This Row],[加工金額合計(月次実績)]], _t受注ﾌｧｲﾙ_総合計[[#This Row],[受注金額(修正)]], _t受注ﾌｧｲﾙ_総合計[[#This Row],[加工金額合計(月次実績)]] ), 0 ) -> 3300 | K44: =IF(ISERROR(F44),0,E44) -> 3300 | L44: =_xlfn.LET( _xlpm._依頼NO, A44, _xlpm._集計年, YEAR(H44), _xlpm._依頼列, _t受注ﾌｧｲﾙ_TPI[依頼Ｎｏ], _xlpm._集計日列, _t受注ﾌｧｲﾙ_TPI[集計日], COUNTIFS( _xlpm._依頼列, _xlpm._依頼NO, _xlpm._集計日列, ">=" & DATE(_xlpm._集計年,1,1), _xlpm._集計日列, "<" & DATE(_xlpm._集計年+1,1,1) ) ) -> 0 | M44: =_xlfn.LET( _xlpm._依頼NO, A44, _xlpm._集計年, YEAR(H44), _xlpm._依頼列,_t受注ﾌｧｲﾙ_東レ[依頼Ｎｏ], _xlpm._集計日列, _t受注ﾌｧｲﾙ_東レ[集計日], COUNTIFS( _xlpm._依頼列, _xlpm._依頼NO, _xlpm._集計日列, ">=" & DATE(_xlpm._集計年,1,1), _xlpm._集計日列, "<" & DATE(_xlpm._集計年+1,1,1) ) ) -> 1 | N44: =IFERROR( INDEX( _xlfn.TEXTSPLIT( SUBSTITUTE(SUBSTITUTE(B44, "，", ","), "、", ","), ",", ), 1, 1 ), "" ) -> スライス | O44: =IFERROR( INDEX( _xlfn.TEXTSPLIT( SUBSTITUTE(SUBSTITUTE(B44, "，", ","), "、", ","), ",", ), 1, 2 ), "" ) | P44: =IFERROR( INDEX( _xlfn.TEXTSPLIT( SUBSTITUTE(SUBSTITUTE(B44, "，", ","), "、", ","), ",", ), 1, 3 ), "" ) | Q44: =IFERROR( INDEX( _xlfn.TEXTSPLIT( SUBSTITUTE(SUBSTITUTE(B44, "，", ","), "、", ","), ",", ), 1, 4 ), "" ) | R44: =IFERROR( INDEX( _xlfn.TEXTSPLIT( SUBSTITUTE(SUBSTITUTE(B44, "，", ","), "、", ","), ",", ), 1, 5 ), "" ) | T44: =IF(_t受注ﾌｧｲﾙ_総合計[[#This Row],[加工金額]]=_t受注ﾌｧｲﾙ_総合計[[#This Row],[受注金額(修正)]],TRUE) -> TRUE
A45: T6-16 | B45: スライス | C45: 46195 | D45: 800 | E45: 8800 | F45: {=_xlfn.LET( _xlpm._完了日,_加工実績DATA[加工完了日], _xlpm._調整納期列,_t受注ﾌｧｲﾙ_総合計[調整納期], _xlpm._加工完了日,_xlfn.TAKE( _xlfn._xlws.FILTER(_xlpm._完了日, (A45=_加工実績DATA[依頼NO])* (YEAR(C45) = YEAR(_xlpm._完了日)) ),1), IF(_xlpm._加工完了日 = 0,NA(),_xlpm._加工完了日) )} -> 46190 | G45: {=_xlfn.LET( _xlpm._完了日列,#REF!, _xlpm._完了日, _xlfn.TAKE( _xlfn._xlws.FILTER(_xlpm._完了日列, (A45=#REF!)* (DATEVALUE("2025/1/1") < C45) ),1 ), IFERROR(_xlpm._完了日,"") )} | H45: {=_xlfn.LET( _xlpm.f, IFERROR(F45, 0), _xlpm.g, IFERROR(G45, 0), _xlpm.c, IFERROR(C45, 0), _xlfn.IFS( ISNUMBER(_xlpm.f)*(_xlpm.f>0), _xlpm.f, ISNUMBER(_xlpm.g)*(_xlpm.g>0), _xlpm.g, ISNUMBER(_xlpm.c)*(_xlpm.c>0), _xlpm.c, TRUE, "" ) )} -> 46190 | I45: {=_xlfn.LET( _xlpm._加工金額合計列,_t月次実績表[--合計--], _xlpm._月次年月日列,_t月次実績表[年月], _xlpm._依頼NO列,_t月次実績表[依頼NO(-1除外)], IFERROR( SUM( _xlfn._xlws.FILTER(_xlpm._加工金額合計列, (A45=_xlpm._依頼NO列) * (YEAR(_xlpm._月次年月日列) = YEAR(H45)) ) ), 0) )} -> 0 | J45: =IFERROR( IF( _t受注ﾌｧｲﾙ_総合計[[#This Row],[受注金額(修正)]] > _t受注ﾌｧｲﾙ_総合計[[#This Row],[加工金額合計(月次実績)]], _t受注ﾌｧｲﾙ_総合計[[#This Row],[受注金額(修正)]], _t受注ﾌｧｲﾙ_総合計[[#This Row],[加工金額合計(月次実績)]] ), 0 ) -> 8800 | K45: =IF(ISERROR(F45),0,E45) -> 8800 | L45: =_xlfn.LET( _xlpm._依頼NO, A45, _xlpm._集計年, YEAR(H45), _xlpm._依頼列, _t受注ﾌｧｲﾙ_TPI[依頼Ｎｏ], _xlpm._集計日列, _t受注ﾌｧｲﾙ_TPI[集計日], COUNTIFS( _xlpm._依頼列, _xlpm._依頼NO, _xlpm._集計日列, ">=" & DATE(_xlpm._集計年,1,1), _xlpm._集計日列, "<" & DATE(_xlpm._集計年+1,1,1) ) ) -> 0 | M45: =_xlfn.LET( _xlpm._依頼NO, A45, _xlpm._集計年, YEAR(H45), _xlpm._依頼列,_t受注ﾌｧｲﾙ_東レ[依頼Ｎｏ], _xlpm._集計日列, _t受注ﾌｧｲﾙ_東レ[集計日], COUNTIFS( _xlpm._依頼列, _xlpm._依頼NO, _xlpm._集計日列, ">=" & DATE(_xlpm._集計年,1,1), _xlpm._集計日列, "<" & DATE(_xlpm._集計年+1,1,1) ) ) -> 1 | N45: =IFERROR( INDEX( _xlfn.TEXTSPLIT( SUBSTITUTE(SUBSTITUTE(B45, "，", ","), "、", ","), ",", ), 1, 1 ), "" ) -> スライス | O45: =IFERROR( INDEX( _xlfn.TEXTSPLIT( SUBSTITUTE(SUBSTITUTE(B45, "，", ","), "、", ","), ",", ), 1, 2 ), "" ) | P45: =IFERROR( INDEX( _xlfn.TEXTSPLIT( SUBSTITUTE(SUBSTITUTE(B45, "，", ","), "、", ","), ",", ), 1, 3 ), "" ) | Q45: =IFERROR( INDEX( _xlfn.TEXTSPLIT( SUBSTITUTE(SUBSTITUTE(B45, "，", ","), "、", ","), ",", ), 1, 4 ), "" ) | R45: =IFERROR( INDEX( _xlfn.TEXTSPLIT( SUBSTITUTE(SUBSTITUTE(B45, "，", ","), "、", ","), ",", ), 1, 5 ), "" ) | T45: =IF(_t受注ﾌｧｲﾙ_総合計[[#This Row],[加工金額]]=_t受注ﾌｧｲﾙ_総合計[[#This Row],[受注金額(修正)]],TRUE) -> TRUE
A46: T6-17 | B46: スライス | C46: 46195 | D46: 800 | E46: 8800 | F46: {=_xlfn.LET( _xlpm._完了日,_加工実績DATA[加工完了日], _xlpm._調整納期列,_t受注ﾌｧｲﾙ_総合計[調整納期], _xlpm._加工完了日,_xlfn.TAKE( _xlfn._xlws.FILTER(_xlpm._完了日, (A46=_加工実績DATA[依頼NO])* (YEAR(C46) = YEAR(_xlpm._完了日)) ),1), IF(_xlpm._加工完了日 = 0,NA(),_xlpm._加工完了日) )} -> 46190 | G46: {=_xlfn.LET( _xlpm._完了日列,#REF!, _xlpm._完了日, _xlfn.TAKE( _xlfn._xlws.FILTER(_xlpm._完了日列, (A46=#REF!)* (DATEVALUE("2025/1/1") < C46) ),1 ), IFERROR(_xlpm._完了日,"") )} | H46: {=_xlfn.LET( _xlpm.f, IFERROR(F46, 0), _xlpm.g, IFERROR(G46, 0), _xlpm.c, IFERROR(C46, 0), _xlfn.IFS( ISNUMBER(_xlpm.f)*(_xlpm.f>0), _xlpm.f, ISNUMBER(_xlpm.g)*(_xlpm.g>0), _xlpm.g, ISNUMBER(_xlpm.c)*(_xlpm.c>0), _xlpm.c, TRUE, "" ) )} -> 46190 | I46: {=_xlfn.LET( _xlpm._加工金額合計列,_t月次実績表[--合計--], _xlpm._月次年月日列,_t月次実績表[年月], _xlpm._依頼NO列,_t月次実績表[依頼NO(-1除外)], IFERROR( SUM( _xlfn._xlws.FILTER(_xlpm._加工金額合計列, (A46=_xlpm._依頼NO列) * (YEAR(_xlpm._月次年月日列) = YEAR(H46)) ) ), 0) )} -> 0 | J46: =IFERROR( IF( _t受注ﾌｧｲﾙ_総合計[[#This Row],[受注金額(修正)]] > _t受注ﾌｧｲﾙ_総合計[[#This Row],[加工金額合計(月次実績)]], _t受注ﾌｧｲﾙ_総合計[[#This Row],[受注金額(修正)]], _t受注ﾌｧｲﾙ_総合計[[#This Row],[加工金額合計(月次実績)]] ), 0 ) -> 8800 | K46: =IF(ISERROR(F46),0,E46) -> 8800 | L46: =_xlfn.LET( _xlpm._依頼NO, A46, _xlpm._集計年, YEAR(H46), _xlpm._依頼列, _t受注ﾌｧｲﾙ_TPI[依頼Ｎｏ], _xlpm._集計日列, _t受注ﾌｧｲﾙ_TPI[集計日], COUNTIFS( _xlpm._依頼列, _xlpm._依頼NO, _xlpm._集計日列, ">=" & DATE(_xlpm._集計年,1,1), _xlpm._集計日列, "<" & DATE(_xlpm._集計年+1,1,1) ) ) -> 0 | M46: =_xlfn.LET( _xlpm._依頼NO, A46, _xlpm._集計年, YEAR(H46), _xlpm._依頼列,_t受注ﾌｧｲﾙ_東レ[依頼Ｎｏ], _xlpm._集計日列, _t受注ﾌｧｲﾙ_東レ[集計日], COUNTIFS( _xlpm._依頼列, _xlpm._依頼NO, _xlpm._集計日列, ">=" & DATE(_xlpm._集計年,1,1), _xlpm._集計日列, "<" & DATE(_xlpm._集計年+1,1,1) ) ) -> 1 | N46: =IFERROR( INDEX( _xlfn.TEXTSPLIT( SUBSTITUTE(SUBSTITUTE(B46, "，", ","), "、", ","), ",", ), 1, 1 ), "" ) -> スライス | O46: =IFERROR( INDEX( _xlfn.TEXTSPLIT( SUBSTITUTE(SUBSTITUTE(B46, "，", ","), "、", ","), ",", ), 1, 2 ), "" ) | P46: =IFERROR( INDEX( _xlfn.TEXTSPLIT( SUBSTITUTE(SUBSTITUTE(B46, "，", ","), "、", ","), ",", ), 1, 3 ), "" ) | Q46: =IFERROR( INDEX( _xlfn.TEXTSPLIT( SUBSTITUTE(SUBSTITUTE(B46, "，", ","), "、", ","), ",", ), 1, 4 ), "" ) | R46: =IFERROR( INDEX( _xlfn.TEXTSPLIT( SUBSTITUTE(SUBSTITUTE(B46, "，", ","), "、", ","), ",", ), 1, 5 ), "" ) | T46: =IF(_t受注ﾌｧｲﾙ_総合計[[#This Row],[加工金額]]=_t受注ﾌｧｲﾙ_総合計[[#This Row],[受注金額(修正)]],TRUE) -> TRUE
A47: T6-18 | B47: ＥＣ | C47: 46189 | D47: 1000 | E47: 18000 | F47: {=_xlfn.LET( _xlpm._完了日,_加工実績DATA[加工完了日], _xlpm._調整納期列,_t受注ﾌｧｲﾙ_総合計[調整納期], _xlpm._加工完了日,_xlfn.TAKE( _xlfn._xlws.FILTER(_xlpm._完了日, (A47=_加工実績DATA[依頼NO])* (YEAR(C47) = YEAR(_xlpm._完了日)) ),1), IF(_xlpm._加工完了日 = 0,NA(),_xlpm._加工完了日) )} -> 46184 | G47: {=_xlfn.LET( _xlpm._完了日列,#REF!, _xlpm._完了日, _xlfn.TAKE( _xlfn._xlws.FILTER(_xlpm._完了日列, (A47=#REF!)* (DATEVALUE("2025/1/1") < C47) ),1 ), IFERROR(_xlpm._完了日,"") )} | H47: {=_xlfn.LET( _xlpm.f, IFERROR(F47, 0), _xlpm.g, IFERROR(G47, 0), _xlpm.c, IFERROR(C47, 0), _xlfn.IFS( ISNUMBER(_xlpm.f)*(_xlpm.f>0), _xlpm.f, ISNUMBER(_xlpm.g)*(_xlpm.g>0), _xlpm.g, ISNUMBER(_xlpm.c)*(_xlpm.c>0), _xlpm.c, TRUE, "" ) )} -> 46184 | I47: {=_xlfn.LET( _xlpm._加工金額合計列,_t月次実績表[--合計--], _xlpm._月次年月日列,_t月次実績表[年月], _xlpm._依頼NO列,_t月次実績表[依頼NO(-1除外)], IFERROR( SUM( _xlfn._xlws.FILTER(_xlpm._加工金額合計列, (A47=_xlpm._依頼NO列) * (YEAR(_xlpm._月次年月日列) = YEAR(H47)) ) ), 0) )} -> 0 | J47: =IFERROR( IF( _t受注ﾌｧｲﾙ_総合計[[#This Row],[受注金額(修正)]] > _t受注ﾌｧｲﾙ_総合計[[#This Row],[加工金額合計(月次実績)]], _t受注ﾌｧｲﾙ_総合計[[#This Row],[受注金額(修正)]], _t受注ﾌｧｲﾙ_総合計[[#This Row],[加工金額合計(月次実績)]] ), 0 ) -> 18000 | K47: =IF(ISERROR(F47),0,E47) -> 18000 | L47: =_xlfn.LET( _xlpm._依頼NO, A47, _xlpm._集計年, YEAR(H47), _xlpm._依頼列, _t受注ﾌｧｲﾙ_TPI[依頼Ｎｏ], _xlpm._集計日列, _t受注ﾌｧｲﾙ_TPI[集計日], COUNTIFS( _xlpm._依頼列, _xlpm._依頼NO, _xlpm._集計日列, ">=" & DATE(_xlpm._集計年,1,1), _xlpm._集計日列, "<" & DATE(_xlpm._集計年+1,1,1) ) ) -> 0 | M47: =_xlfn.LET( _xlpm._依頼NO, A47, _xlpm._集計年, YEAR(H47), _xlpm._依頼列,_t受注ﾌｧｲﾙ_東レ[依頼Ｎｏ], _xlpm._集計日列, _t受注ﾌｧｲﾙ_東レ[集計日], COUNTIFS( _xlpm._依頼列, _xlpm._依頼NO, _xlpm._集計日列, ">=" & DATE(_xlpm._集計年,1,1), _xlpm._集計日列, "<" & DATE(_xlpm._集計年+1,1,1) ) ) -> 1 | N47: =IFERROR( INDEX( _xlfn.TEXTSPLIT( SUBSTITUTE(SUBSTITUTE(B47, "，", ","), "、", ","), ",", ), 1, 1 ), "" ) -> ＥＣ | O47: =IFERROR( INDEX( _xlfn.TEXTSPLIT( SUBSTITUTE(SUBSTITUTE(B47, "，", ","), "、", ","), ",", ), 1, 2 ), "" ) | P47: =IFERROR( INDEX( _xlfn.TEXTSPLIT( SUBSTITUTE(SUBSTITUTE(B47, "，", ","), "、", ","), ",", ), 1, 3 ), "" ) | Q47: =IFERROR( INDEX( _xlfn.TEXTSPLIT( SUBSTITUTE(SUBSTITUTE(B47, "，", ","), "、", ","), ",", ), 1, 4 ), "" ) | R47: =IFERROR( INDEX( _xlfn.TEXTSPLIT( SUBSTITUTE(SUBSTITUTE(B47, "，", ","), "、", ","), ",", ), 1, 5 ), "" ) | T47: =IF(_t受注ﾌｧｲﾙ_総合計[[#This Row],[加工金額]]=_t受注ﾌｧｲﾙ_総合計[[#This Row],[受注金額(修正)]],TRUE) -> TRUE
A48: C6-4 | B48: SEC | C48: 46199 | D48: 10,000 10,000 | E48: 260000 | F48: {=_xlfn.LET( _xlpm._完了日,_加工実績DATA[加工完了日], _xlpm._調整納期列,_t受注ﾌｧｲﾙ_総合計[調整納期], _xlpm._加工完了日,_xlfn.TAKE( _xlfn._xlws.FILTER(_xlpm._完了日, (A48=_加工実績DATA[依頼NO])* (YEAR(C48) = YEAR(_xlpm._完了日)) ),1), IF(_xlpm._加工完了日 = 0,NA(),_xlpm._加工完了日) )} -> 46198 | G48: {=_xlfn.LET( _xlpm._完了日列,#REF!, _xlpm._完了日, _xlfn.TAKE( _xlfn._xlws.FILTER(_xlpm._完了日列, (A48=#REF!)* (DATEVALUE("2025/1/1") < C48) ),1 ), IFERROR(_xlpm._完了日,"") )} | H48: {=_xlfn.LET( _xlpm.f, IFERROR(F48, 0), _xlpm.g, IFERROR(G48, 0), _xlpm.c, IFERROR(C48, 0), _xlfn.IFS( ISNUMBER(_xlpm.f)*(_xlpm.f>0), _xlpm.f, ISNUMBER(_xlpm.g)*(_xlpm.g>0), _xlpm.g, ISNUMBER(_xlpm.c)*(_xlpm.c>0), _xlpm.c, TRUE, "" ) )} -> 46198 | I48: {=_xlfn.LET( _xlpm._加工金額合計列,_t月次実績表[--合計--], _xlpm._月次年月日列,_t月次実績表[年月], _xlpm._依頼NO列,_t月次実績表[依頼NO(-1除外)], IFERROR( SUM( _xlfn._xlws.FILTER(_xlpm._加工金額合計列, (A48=_xlpm._依頼NO列) * (YEAR(_xlpm._月次年月日列) = YEAR(H48)) ) ), 0) )} -> 0 | J48: =IFERROR( IF( _t受注ﾌｧｲﾙ_総合計[[#This Row],[受注金額(修正)]] > _t受注ﾌｧｲﾙ_総合計[[#This Row],[加工金額合計(月次実績)]], _t受注ﾌｧｲﾙ_総合計[[#This Row],[受注金額(修正)]], _t受注ﾌｧｲﾙ_総合計[[#This Row],[加工金額合計(月次実績)]] ), 0 ) -> 260000 | K48: =IF(ISERROR(F48),0,E48) -> 260000 | L48: =_xlfn.LET( _xlpm._依頼NO, A48, _xlpm._集計年, YEAR(H48), _xlpm._依頼列, _t受注ﾌｧｲﾙ_TPI[依頼Ｎｏ], _xlpm._集計日列, _t受注ﾌｧｲﾙ_TPI[集計日], COUNTIFS( _xlpm._依頼列, _xlpm._依頼NO, _xlpm._集計日列, ">=" & DATE(_xlpm._集計年,1,1), _xlpm._集計日列, "<" & DATE(_xlpm._集計年+1,1,1) ) ) -> 0 | M48: =_xlfn.LET( _xlpm._依頼NO, A48, _xlpm._集計年, YEAR(H48), _xlpm._依頼列,_t受注ﾌｧｲﾙ_東レ[依頼Ｎｏ], _xlpm._集計日列, _t受注ﾌｧｲﾙ_東レ[集計日], COUNTIFS( _xlpm._依頼列, _xlpm._依頼NO, _xlpm._集計日列, ">=" & DATE(_xlpm._集計年,1,1), _xlpm._集計日列, "<" & DATE(_xlpm._集計年+1,1,1) ) ) -> 1 | N48: =IFERROR( INDEX( _xlfn.TEXTSPLIT( SUBSTITUTE(SUBSTITUTE(B48, "，", ","), "、", ","), ",", ), 1, 1 ), "" ) -> SEC | O48: =IFERROR( INDEX( _xlfn.TEXTSPLIT( SUBSTITUTE(SUBSTITUTE(B48, "，", ","), "、", ","), ",", ), 1, 2 ), "" ) | P48: =IFERROR( INDEX( _xlfn.TEXTSPLIT( SUBSTITUTE(SUBSTITUTE(B48, "，", ","), "、", ","), ",", ), 1, 3 ), "" ) | Q48: =IFERROR( INDEX( _xlfn.TEXTSPLIT( SUBSTITUTE(SUBSTITUTE(B48, "，", ","), "、", ","), ",", ), 1, 4 ), "" ) | R48: =IFERROR( INDEX( _xlfn.TEXTSPLIT( SUBSTITUTE(SUBSTITUTE(B48, "，", ","), "、", ","), ",", ), 1, 5 ), "" ) | T48: =IF(_t受注ﾌｧｲﾙ_総合計[[#This Row],[加工金額]]=_t受注ﾌｧｲﾙ_総合計[[#This Row],[受注金額(修正)]],TRUE) -> TRUE
A49: C6-3 | B49: SEC | C49: 46198 | D49: 10,000 10,000 | E49: 260000 | F49: {=_xlfn.LET( _xlpm._完了日,_加工実績DATA[加工完了日], _xlpm._調整納期列,_t受注ﾌｧｲﾙ_総合計[調整納期], _xlpm._加工完了日,_xlfn.TAKE( _xlfn._xlws.FILTER(_xlpm._完了日, (A49=_加工実績DATA[依頼NO])* (YEAR(C49) = YEAR(_xlpm._完了日)) ),1), IF(_xlpm._加工完了日 = 0,NA(),_xlpm._加工完了日) )} -> 46197 | G49: {=_xlfn.LET( _xlpm._完了日列,#REF!, _xlpm._完了日, _xlfn.TAKE( _xlfn._xlws.FILTER(_xlpm._完了日列, (A49=#REF!)* (DATEVALUE("2025/1/1") < C49) ),1 ), IFERROR(_xlpm._完了日,"") )} | H49: {=_xlfn.LET( _xlpm.f, IFERROR(F49, 0), _xlpm.g, IFERROR(G49, 0), _xlpm.c, IFERROR(C49, 0), _xlfn.IFS( ISNUMBER(_xlpm.f)*(_xlpm.f>0), _xlpm.f, ISNUMBER(_xlpm.g)*(_xlpm.g>0), _xlpm.g, ISNUMBER(_xlpm.c)*(_xlpm.c>0), _xlpm.c, TRUE, "" ) )} -> 46197 | I49: {=_xlfn.LET( _xlpm._加工金額合計列,_t月次実績表[--合計--], _xlpm._月次年月日列,_t月次実績表[年月], _xlpm._依頼NO列,_t月次実績表[依頼NO(-1除外)], IFERROR( SUM( _xlfn._xlws.FILTER(_xlpm._加工金額合計列, (A49=_xlpm._依頼NO列) * (YEAR(_xlpm._月次年月日列) = YEAR(H49)) ) ), 0) )} -> 0 | J49: =IFERROR( IF( _t受注ﾌｧｲﾙ_総合計[[#This Row],[受注金額(修正)]] > _t受注ﾌｧｲﾙ_総合計[[#This Row],[加工金額合計(月次実績)]], _t受注ﾌｧｲﾙ_総合計[[#This Row],[受注金額(修正)]], _t受注ﾌｧｲﾙ_総合計[[#This Row],[加工金額合計(月次実績)]] ), 0 ) -> 260000 | K49: =IF(ISERROR(F49),0,E49) -> 260000 | L49: =_xlfn.LET( _xlpm._依頼NO, A49, _xlpm._集計年, YEAR(H49), _xlpm._依頼列, _t受注ﾌｧｲﾙ_TPI[依頼Ｎｏ], _xlpm._集計日列, _t受注ﾌｧｲﾙ_TPI[集計日], COUNTIFS( _xlpm._依頼列, _xlpm._依頼NO, _xlpm._集計日列, ">=" & DATE(_xlpm._集計年,1,1), _xlpm._集計日列, "<" & DATE(_xlpm._集計年+1,1,1) ) ) -> 0 | M49: =_xlfn.LET( _xlpm._依頼NO, A49, _xlpm._集計年, YEAR(H49), _xlpm._依頼列,_t受注ﾌｧｲﾙ_東レ[依頼Ｎｏ], _xlpm._集計日列, _t受注ﾌｧｲﾙ_東レ[集計日], COUNTIFS( _xlpm._依頼列, _xlpm._依頼NO, _xlpm._集計日列, ">=" & DATE(_xlpm._集計年,1,1), _xlpm._集計日列, "<" & DATE(_xlpm._集計年+1,1,1) ) ) -> 1 | N49: =IFERROR( INDEX( _xlfn.TEXTSPLIT( SUBSTITUTE(SUBSTITUTE(B49, "，", ","), "、", ","), ",", ), 1, 1 ), "" ) -> SEC | O49: =IFERROR( INDEX( _xlfn.TEXTSPLIT( SUBSTITUTE(SUBSTITUTE(B49, "，", ","), "、", ","), ",", ), 1, 2 ), "" ) | P49: =IFERROR( INDEX( _xlfn.TEXTSPLIT( SUBSTITUTE(SUBSTITUTE(B49, "，", ","), "、", ","), ",", ), 1, 3 ), "" ) | Q49: =IFERROR( INDEX( _xlfn.TEXTSPLIT( SUBSTITUTE(SUBSTITUTE(B49, "，", ","), "、", ","), ",", ), 1, 4 ), "" ) | R49: =IFERROR( INDEX( _xlfn.TEXTSPLIT( SUBSTITUTE(SUBSTITUTE(B49, "，", ","), "、", ","), ",", ), 1, 5 ), "" ) | T49: =IF(_t受注ﾌｧｲﾙ_総合計[[#This Row],[加工金額]]=_t受注ﾌｧｲﾙ_総合計[[#This Row],[受注金額(修正)]],TRUE) -> TRUE
A50: C6-5 | B50: SEC | C50: 46203 | D50: 20000 | E50: 260000 | F50: {=_xlfn.LET( _xlpm._完了日,_加工実績DATA[加工完了日], _xlpm._調整納期列,_t受注ﾌｧｲﾙ_総合計[調整納期], _xlpm._加工完了日,_xlfn.TAKE( _xlfn._xlws.FILTER(_xlpm._完了日, (A50=_加工実績DATA[依頼NO])* (YEAR(C50) = YEAR(_xlpm._完了日)) ),1), IF(_xlpm._加工完了日 = 0,NA(),_xlpm._加工完了日) )} -> 46199 | G50: {=_xlfn.LET( _xlpm._完了日列,#REF!, _xlpm._完了日, _xlfn.TAKE( _xlfn._xlws.FILTER(_xlpm._完了日列, (A50=#REF!)* (DATEVALUE("2025/1/1") < C50) ),1 ), IFERROR(_xlpm._完了日,"") )} | H50: {=_xlfn.LET( _xlpm.f, IFERROR(F50, 0), _xlpm.g, IFERROR(G50, 0), _xlpm.c, IFERROR(C50, 0), _xlfn.IFS( ISNUMBER(_xlpm.f)*(_xlpm.f>0), _xlpm.f, ISNUMBER(_xlpm.g)*(_xlpm.g>0), _xlpm.g, ISNUMBER(_xlpm.c)*(_xlpm.c>0), _xlpm.c, TRUE, "" ) )} -> 46199 | I50: {=_xlfn.LET( _xlpm._加工金額合計列,_t月次実績表[--合計--], _xlpm._月次年月日列,_t月次実績表[年月], _xlpm._依頼NO列,_t月次実績表[依頼NO(-1除外)], IFERROR( SUM( _xlfn._xlws.FILTER(_xlpm._加工金額合計列, (A50=_xlpm._依頼NO列) * (YEAR(_xlpm._月次年月日列) = YEAR(H50)) ) ), 0) )} -> 0 | J50: =IFERROR( IF( _t受注ﾌｧｲﾙ_総合計[[#This Row],[受注金額(修正)]] > _t受注ﾌｧｲﾙ_総合計[[#This Row],[加工金額合計(月次実績)]], _t受注ﾌｧｲﾙ_総合計[[#This Row],[受注金額(修正)]], _t受注ﾌｧｲﾙ_総合計[[#This Row],[加工金額合計(月次実績)]] ), 0 ) -> 260000 | K50: =IF(ISERROR(F50),0,E50) -> 260000 | L50: =_xlfn.LET( _xlpm._依頼NO, A50, _xlpm._集計年, YEAR(H50), _xlpm._依頼列, _t受注ﾌｧｲﾙ_TPI[依頼Ｎｏ], _xlpm._集計日列, _t受注ﾌｧｲﾙ_TPI[集計日], COUNTIFS( _xlpm._依頼列, _xlpm._依頼NO, _xlpm._集計日列, ">=" & DATE(_xlpm._集計年,1,1), _xlpm._集計日列, "<" & DATE(_xlpm._集計年+1,1,1) ) ) -> 0 | M50: =_xlfn.LET( _xlpm._依頼NO, A50, _xlpm._集計年, YEAR(H50), _xlpm._依頼列,_t受注ﾌｧｲﾙ_東レ[依頼Ｎｏ], _xlpm._集計日列, _t受注ﾌｧｲﾙ_東レ[集計日], COUNTIFS( _xlpm._依頼列, _xlpm._依頼NO, _xlpm._集計日列, ">=" & DATE(_xlpm._集計年,1,1), _xlpm._集計日列, "<" & DATE(_xlpm._集計年+1,1,1) ) ) -> 1 | N50: =IFERROR( INDEX( _xlfn.TEXTSPLIT( SUBSTITUTE(SUBSTITUTE(B50, "，", ","), "、", ","), ",", ), 1, 1 ), "" ) -> SEC | O50: =IFERROR( INDEX( _xlfn.TEXTSPLIT( SUBSTITUTE(SUBSTITUTE(B50, "，", ","), "、", ","), ",", ), 1, 2 ), "" ) | P50: =IFERROR( INDEX( _xlfn.TEXTSPLIT( SUBSTITUTE(SUBSTITUTE(B50, "，", ","), "、", ","), ",", ), 1, 3 ), "" ) | Q50: =IFERROR( INDEX( _xlfn.TEXTSPLIT( SUBSTITUTE(SUBSTITUTE(B50, "，", ","), "、", ","), ",", ), 1, 4 ), "" ) | R50: =IFERROR( INDEX( _xlfn.TEXTSPLIT( SUBSTITUTE(SUBSTITUTE(B50, "，", ","), "、", ","), ",", ), 1, 5 ), "" ) | T50: =IF(_t受注ﾌｧｲﾙ_総合計[[#This Row],[加工金額]]=_t受注ﾌｧｲﾙ_総合計[[#This Row],[受注金額(修正)]],TRUE) -> TRUE
A51: V6-12 | B51: 分割 | C51: 46197 | D51: 3000 | E51: 45000 | F51: {=_xlfn.LET( _xlpm._完了日,_加工実績DATA[加工完了日], _xlpm._調整納期列,_t受注ﾌｧｲﾙ_総合計[調整納期], _xlpm._加工完了日,_xlfn.TAKE( _xlfn._xlws.FILTER(_xlpm._完了日, (A51=_加工実績DATA[依頼NO])* (YEAR(C51) = YEAR(_xlpm._完了日)) ),1), IF(_xlpm._加工完了日 = 0,NA(),_xlpm._加工完了日) )} -> 46195 | G51: {=_xlfn.LET( _xlpm._完了日列,#REF!, _xlpm._完了日, _xlfn.TAKE( _xlfn._xlws.FILTER(_xlpm._完了日列, (A51=#REF!)* (DATEVALUE("2025/1/1") < C51) ),1 ), IFERROR(_xlpm._完了日,"") )} | H51: {=_xlfn.LET( _xlpm.f, IFERROR(F51, 0), _xlpm.g, IFERROR(G51, 0), _xlpm.c, IFERROR(C51, 0), _xlfn.IFS( ISNUMBER(_xlpm.f)*(_xlpm.f>0), _xlpm.f, ISNUMBER(_xlpm.g)*(_xlpm.g>0), _xlpm.g, ISNUMBER(_xlpm.c)*(_xlpm.c>0), _xlpm.c, TRUE, "" ) )} -> 46195 | I51: {=_xlfn.LET( _xlpm._加工金額合計列,_t月次実績表[--合計--], _xlpm._月次年月日列,_t月次実績表[年月], _xlpm._依頼NO列,_t月次実績表[依頼NO(-1除外)], IFERROR( SUM( _xlfn._xlws.FILTER(_xlpm._加工金額合計列, (A51=_xlpm._依頼NO列) * (YEAR(_xlpm._月次年月日列) = YEAR(H51)) ) ), 0) )} -> 0 | J51: =IFERROR( IF( _t受注ﾌｧｲﾙ_総合計[[#This Row],[受注金額(修正)]] > _t受注ﾌｧｲﾙ_総合計[[#This Row],[加工金額合計(月次実績)]], _t受注ﾌｧｲﾙ_総合計[[#This Row],[受注金額(修正)]], _t受注ﾌｧｲﾙ_総合計[[#This Row],[加工金額合計(月次実績)]] ), 0 ) -> 45000 | K51: =IF(ISERROR(F51),0,E51) -> 45000 | L51: =_xlfn.LET( _xlpm._依頼NO, A51, _xlpm._集計年, YEAR(H51), _xlpm._依頼列, _t受注ﾌｧｲﾙ_TPI[依頼Ｎｏ], _xlpm._集計日列, _t受注ﾌｧｲﾙ_TPI[集計日], COUNTIFS( _xlpm._依頼列, _xlpm._依頼NO, _xlpm._集計日列, ">=" & DATE(_xlpm._集計年,1,1), _xlpm._集計日列, "<" & DATE(_xlpm._集計年+1,1,1) ) ) -> 0 | M51: =_xlfn.LET( _xlpm._依頼NO, A51, _xlpm._集計年, YEAR(H51), _xlpm._依頼列,_t受注ﾌｧｲﾙ_東レ[依頼Ｎｏ], _xlpm._集計日列, _t受注ﾌｧｲﾙ_東レ[集計日], COUNTIFS( _xlpm._依頼列, _xlpm._依頼NO, _xlpm._集計日列, ">=" & DATE(_xlpm._集計年,1,1), _xlpm._集計日列, "<" & DATE(_xlpm._集計年+1,1,1) ) ) -> 1 | N51: =IFERROR( INDEX( _xlfn.TEXTSPLIT( SUBSTITUTE(SUBSTITUTE(B51, "，", ","), "、", ","), ",", ), 1, 1 ), "" ) -> 分割 | O51: =IFERROR( INDEX( _xlfn.TEXTSPLIT( SUBSTITUTE(SUBSTITUTE(B51, "，", ","), "、", ","), ",", ), 1, 2 ), "" ) | P51: =IFERROR( INDEX( _xlfn.TEXTSPLIT( SUBSTITUTE(SUBSTITUTE(B51, "，", ","), "、", ","), ",", ), 1, 3 ), "" ) | Q51: =IFERROR( INDEX( _xlfn.TEXTSPLIT( SUBSTITUTE(SUBSTITUTE(B51, "，", ","), "、", ","), ",", ), 1, 4 ), "" ) | R51: =IFERROR( INDEX( _xlfn.TEXTSPLIT( SUBSTITUTE(SUBSTITUTE(B51, "，", ","), "、", ","), ",", ), 1, 5 ), "" ) | T51: =IF(_t受注ﾌｧｲﾙ_総合計[[#This Row],[加工金額]]=_t受注ﾌｧｲﾙ_総合計[[#This Row],[受注金額(修正)]],TRUE) -> TRUE
A52: V6-13 | B52: 分割 | C52: 46199 | D52: 1000 | E52: 15000 | F52: {=_xlfn.LET( _xlpm._完了日,_加工実績DATA[加工完了日], _xlpm._調整納期列,_t受注ﾌｧｲﾙ_総合計[調整納期], _xlpm._加工完了日,_xlfn.TAKE( _xlfn._xlws.FILTER(_xlpm._完了日, (A52=_加工実績DATA[依頼NO])* (YEAR(C52) = YEAR(_xlpm._完了日)) ),1), IF(_xlpm._加工完了日 = 0,NA(),_xlpm._加工完了日) )} -> 46197 | G52: {=_xlfn.LET( _xlpm._完了日列,#REF!, _xlpm._完了日, _xlfn.TAKE( _xlfn._xlws.FILTER(_xlpm._完了日列, (A52=#REF!)* (DATEVALUE("2025/1/1") < C52) ),1 ), IFERROR(_xlpm._完了日,"") )} | H52: {=_xlfn.LET( _xlpm.f, IFERROR(F52, 0), _xlpm.g, IFERROR(G52, 0), _xlpm.c, IFERROR(C52, 0), _xlfn.IFS( ISNUMBER(_xlpm.f)*(_xlpm.f>0), _xlpm.f, ISNUMBER(_xlpm.g)*(_xlpm.g>0), _xlpm.g, ISNUMBER(_xlpm.c)*(_xlpm.c>0), _xlpm.c, TRUE, "" ) )} -> 46197 | I52: {=_xlfn.LET( _xlpm._加工金額合計列,_t月次実績表[--合計--], _xlpm._月次年月日列,_t月次実績表[年月], _xlpm._依頼NO列,_t月次実績表[依頼NO(-1除外)], IFERROR( SUM( _xlfn._xlws.FILTER(_xlpm._加工金額合計列, (A52=_xlpm._依頼NO列) * (YEAR(_xlpm._月次年月日列) = YEAR(H52)) ) ), 0) )} -> 0 | J52: =IFERROR( IF( _t受注ﾌｧｲﾙ_総合計[[#This Row],[受注金額(修正)]] > _t受注ﾌｧｲﾙ_総合計[[#This Row],[加工金額合計(月次実績)]], _t受注ﾌｧｲﾙ_総合計[[#This Row],[受注金額(修正)]], _t受注ﾌｧｲﾙ_総合計[[#This Row],[加工金額合計(月次実績)]] ), 0 ) -> 15000 | K52: =IF(ISERROR(F52),0,E52) -> 15000 | L52: =_xlfn.LET( _xlpm._依頼NO, A52, _xlpm._集計年, YEAR(H52), _xlpm._依頼列, _t受注ﾌｧｲﾙ_TPI[依頼Ｎｏ], _xlpm._集計日列, _t受注ﾌｧｲﾙ_TPI[集計日], COUNTIFS( _xlpm._依頼列, _xlpm._依頼NO, _xlpm._集計日列, ">=" & DATE(_xlpm._集計年,1,1), _xlpm._集計日列, "<" & DATE(_xlpm._集計年+1,1,1) ) ) -> 0 | M52: =_xlfn.LET( _xlpm._依頼NO, A52, _xlpm._集計年, YEAR(H52), _xlpm._依頼列,_t受注ﾌｧｲﾙ_東レ[依頼Ｎｏ], _xlpm._集計日列, _t受注ﾌｧｲﾙ_東レ[集計日], COUNTIFS( _xlpm._依頼列, _xlpm._依頼NO, _xlpm._集計日列, ">=" & DATE(_xlpm._集計年,1,1), _xlpm._集計日列, "<" & DATE(_xlpm._集計年+1,1,1) ) ) -> 1 | N52: =IFERROR( INDEX( _xlfn.TEXTSPLIT( SUBSTITUTE(SUBSTITUTE(B52, "，", ","), "、", ","), ",", ), 1, 1 ), "" ) -> 分割 | O52: =IFERROR( INDEX( _xlfn.TEXTSPLIT( SUBSTITUTE(SUBSTITUTE(B52, "，", ","), "、", ","), ",", ), 1, 2 ), "" ) | P52: =IFERROR( INDEX( _xlfn.TEXTSPLIT( SUBSTITUTE(SUBSTITUTE(B52, "，", ","), "、", ","), ",", ), 1, 3 ), "" ) | Q52: =IFERROR( INDEX( _xlfn.TEXTSPLIT( SUBSTITUTE(SUBSTITUTE(B52, "，", ","), "、", ","), ",", ), 1, 4 ), "" ) | R52: =IFERROR( INDEX( _xlfn.TEXTSPLIT( SUBSTITUTE(SUBSTITUTE(B52, "，", ","), "、", ","), ",", ), 1, 5 ), "" ) | T52: =IF(_t受注ﾌｧｲﾙ_総合計[[#This Row],[加工金額]]=_t受注ﾌｧｲﾙ_総合計[[#This Row],[受注金額(修正)]],TRUE) -> TRUE
A53: E6-4 | B53: EC,巻き返し | C53: 46190 | D53: 2500 | E53: 122500 | F53: {=_xlfn.LET( _xlpm._完了日,_加工実績DATA[加工完了日], _xlpm._調整納期列,_t受注ﾌｧｲﾙ_総合計[調整納期], _xlpm._加工完了日,_xlfn.TAKE( _xlfn._xlws.FILTER(_xlpm._完了日, (A53=_加工実績DATA[依頼NO])* (YEAR(C53) = YEAR(_xlpm._完了日)) ),1), IF(_xlpm._加工完了日 = 0,NA(),_xlpm._加工完了日) )} -> 46188 | G53: {=_xlfn.LET( _xlpm._完了日列,#REF!, _xlpm._完了日, _xlfn.TAKE( _xlfn._xlws.FILTER(_xlpm._完了日列, (A53=#REF!)* (DATEVALUE("2025/1/1") < C53) ),1 ), IFERROR(_xlpm._完了日,"") )} | H53: {=_xlfn.LET( _xlpm.f, IFERROR(F53, 0), _xlpm.g, IFERROR(G53, 0), _xlpm.c, IFERROR(C53, 0), _xlfn.IFS( ISNUMBER(_xlpm.f)*(_xlpm.f>0), _xlpm.f, ISNUMBER(_xlpm.g)*(_xlpm.g>0), _xlpm.g, ISNUMBER(_xlpm.c)*(_xlpm.c>0), _xlpm.c, TRUE, "" ) )} -> 46188 | I53: {=_xlfn.LET( _xlpm._加工金額合計列,_t月次実績表[--合計--], _xlpm._月次年月日列,_t月次実績表[年月], _xlpm._依頼NO列,_t月次実績表[依頼NO(-1除外)], IFERROR( SUM( _xlfn._xlws.FILTER(_xlpm._加工金額合計列, (A53=_xlpm._依頼NO列) * (YEAR(_xlpm._月次年月日列) = YEAR(H53)) ) ), 0) )} -> 0 | J53: =IFERROR( IF( _t受注ﾌｧｲﾙ_総合計[[#This Row],[受注金額(修正)]] > _t受注ﾌｧｲﾙ_総合計[[#This Row],[加工金額合計(月次実績)]], _t受注ﾌｧｲﾙ_総合計[[#This Row],[受注金額(修正)]], _t受注ﾌｧｲﾙ_総合計[[#This Row],[加工金額合計(月次実績)]] ), 0 ) -> 122500 | K53: =IF(ISERROR(F53),0,E53) -> 122500 | L53: =_xlfn.LET( _xlpm._依頼NO, A53, _xlpm._集計年, YEAR(H53), _xlpm._依頼列, _t受注ﾌｧｲﾙ_TPI[依頼Ｎｏ], _xlpm._集計日列, _t受注ﾌｧｲﾙ_TPI[集計日], COUNTIFS( _xlpm._依頼列, _xlpm._依頼NO, _xlpm._集計日列, ">=" & DATE(_xlpm._集計年,1,1), _xlpm._集計日列, "<" & DATE(_xlpm._集計年+1,1,1) ) ) -> 0 | M53: =_xlfn.LET( _xlpm._依頼NO, A53, _xlpm._集計年, YEAR(H53), _xlpm._依頼列,_t受注ﾌｧｲﾙ_東レ[依頼Ｎｏ], _xlpm._集計日列, _t受注ﾌｧｲﾙ_東レ[集計日], COUNTIFS( _xlpm._依頼列, _xlpm._依頼NO, _xlpm._集計日列, ">=" & DATE(_xlpm._集計年,1,1), _xlpm._集計日列, "<" & DATE(_xlpm._集計年+1,1,1) ) ) -> 1 | N53: =IFERROR( INDEX( _xlfn.TEXTSPLIT( SUBSTITUTE(SUBSTITUTE(B53, "，", ","), "、", ","), ",", ), 1, 1 ), "" ) -> EC | O53: =IFERROR( INDEX( _xlfn.TEXTSPLIT( SUBSTITUTE(SUBSTITUTE(B53, "，", ","), "、", ","), ",", ), 1, 2 ), "" ) -> 巻き返し | P53: =IFERROR( INDEX( _xlfn.TEXTSPLIT( SUBSTITUTE(SUBSTITUTE(B53, "，", ","), "、", ","), ",", ), 1, 3 ), "" ) | Q53: =IFERROR( INDEX( _xlfn.TEXTSPLIT( SUBSTITUTE(SUBSTITUTE(B53, "，", ","), "、", ","), ",", ), 1, 4 ), "" ) | R53: =IFERROR( INDEX( _xlfn.TEXTSPLIT( SUBSTITUTE(SUBSTITUTE(B53, "，", ","), "、", ","), ",", ), 1, 5 ), "" ) | T53: =IF(_t受注ﾌｧｲﾙ_総合計[[#This Row],[加工金額]]=_t受注ﾌｧｲﾙ_総合計[[#This Row],[受注金額(修正)]],TRUE) -> TRUE
A54: V6-11 | B54: 分割 | C54: 46197 | D54: 2000 | E54: 30000 | F54: {=_xlfn.LET( _xlpm._完了日,_加工実績DATA[加工完了日], _xlpm._調整納期列,_t受注ﾌｧｲﾙ_総合計[調整納期], _xlpm._加工完了日,_xlfn.TAKE( _xlfn._xlws.FILTER(_xlpm._完了日, (A54=_加工実績DATA[依頼NO])* (YEAR(C54) = YEAR(_xlpm._完了日)) ),1), IF(_xlpm._加工完了日 = 0,NA(),_xlpm._加工完了日) )} -> 46196 | G54: {=_xlfn.LET( _xlpm._完了日列,#REF!, _xlpm._完了日, _xlfn.TAKE( _xlfn._xlws.FILTER(_xlpm._完了日列, (A54=#REF!)* (DATEVALUE("2025/1/1") < C54) ),1 ), IFERROR(_xlpm._完了日,"") )} | H54: {=_xlfn.LET( _xlpm.f, IFERROR(F54, 0), _xlpm.g, IFERROR(G54, 0), _xlpm.c, IFERROR(C54, 0), _xlfn.IFS( ISNUMBER(_xlpm.f)*(_xlpm.f>0), _xlpm.f, ISNUMBER(_xlpm.g)*(_xlpm.g>0), _xlpm.g, ISNUMBER(_xlpm.c)*(_xlpm.c>0), _xlpm.c, TRUE, "" ) )} -> 46196 | I54: {=_xlfn.LET( _xlpm._加工金額合計列,_t月次実績表[--合計--], _xlpm._月次年月日列,_t月次実績表[年月], _xlpm._依頼NO列,_t月次実績表[依頼NO(-1除外)], IFERROR( SUM( _xlfn._xlws.FILTER(_xlpm._加工金額合計列, (A54=_xlpm._依頼NO列) * (YEAR(_xlpm._月次年月日列) = YEAR(H54)) ) ), 0) )} -> 0 | J54: =IFERROR( IF( _t受注ﾌｧｲﾙ_総合計[[#This Row],[受注金額(修正)]] > _t受注ﾌｧｲﾙ_総合計[[#This Row],[加工金額合計(月次実績)]], _t受注ﾌｧｲﾙ_総合計[[#This Row],[受注金額(修正)]], _t受注ﾌｧｲﾙ_総合計[[#This Row],[加工金額合計(月次実績)]] ), 0 ) -> 30000 | K54: =IF(ISERROR(F54),0,E54) -> 30000 | L54: =_xlfn.LET( _xlpm._依頼NO, A54, _xlpm._集計年, YEAR(H54), _xlpm._依頼列, _t受注ﾌｧｲﾙ_TPI[依頼Ｎｏ], _xlpm._集計日列, _t受注ﾌｧｲﾙ_TPI[集計日], COUNTIFS( _xlpm._依頼列, _xlpm._依頼NO, _xlpm._集計日列, ">=" & DATE(_xlpm._集計年,1,1), _xlpm._集計日列, "<" & DATE(_xlpm._集計年+1,1,1) ) ) -> 0 | M54: =_xlfn.LET( _xlpm._依頼NO, A54, _xlpm._集計年, YEAR(H54), _xlpm._依頼列,_t受注ﾌｧｲﾙ_東レ[依頼Ｎｏ], _xlpm._集計日列, _t受注ﾌｧｲﾙ_東レ[集計日], COUNTIFS( _xlpm._依頼列, _xlpm._依頼NO, _xlpm._集計日列, ">=" & DATE(_xlpm._集計年,1,1), _xlpm._集計日列, "<" & DATE(_xlpm._集計年+1,1,1) ) ) -> 1 | N54: =IFERROR( INDEX( _xlfn.TEXTSPLIT( SUBSTITUTE(SUBSTITUTE(B54, "，", ","), "、", ","), ",", ), 1, 1 ), "" ) -> 分割 | O54: =IFERROR( INDEX( _xlfn.TEXTSPLIT( SUBSTITUTE(SUBSTITUTE(B54, "，", ","), "、", ","), ",", ), 1, 2 ), "" ) | P54: =IFERROR( INDEX( _xlfn.TEXTSPLIT( SUBSTITUTE(SUBSTITUTE(B54, "，", ","), "、", ","), ",", ), 1, 3 ), "" ) | Q54: =IFERROR( INDEX( _xlfn.TEXTSPLIT( SUBSTITUTE(SUBSTITUTE(B54, "，", ","), "、", ","), ",", ), 1, 4 ), "" ) | R54: =IFERROR( INDEX( _xlfn.TEXTSPLIT( SUBSTITUTE(SUBSTITUTE(B54, "，", ","), "、", ","), ",", ), 1, 5 ), "" ) | T54: =IF(_t受注ﾌｧｲﾙ_総合計[[#This Row],[加工金額]]=_t受注ﾌｧｲﾙ_総合計[[#This Row],[受注金額(修正)]],TRUE) -> TRUE
A55: W6-11 | B55: EC,欠点表示 | C55: 46188 | D55: 400 | E55: 12400 | F55: {=_xlfn.LET( _xlpm._完了日,_加工実績DATA[加工完了日], _xlpm._調整納期列,_t受注ﾌｧｲﾙ_総合計[調整納期], _xlpm._加工完了日,_xlfn.TAKE( _xlfn._xlws.FILTER(_xlpm._完了日, (A55=_加工実績DATA[依頼NO])* (YEAR(C55) = YEAR(_xlpm._完了日)) ),1), IF(_xlpm._加工完了日 = 0,NA(),_xlpm._加工完了日) )} -> 46184 | G55: {=_xlfn.LET( _xlpm._完了日列,#REF!, _xlpm._完了日, _xlfn.TAKE( _xlfn._xlws.FILTER(_xlpm._完了日列, (A55=#REF!)* (DATEVALUE("2025/1/1") < C55) ),1 ), IFERROR(_xlpm._完了日,"") )} | H55: {=_xlfn.LET( _xlpm.f, IFERROR(F55, 0), _xlpm.g, IFERROR(G55, 0), _xlpm.c, IFERROR(C55, 0), _xlfn.IFS( ISNUMBER(_xlpm.f)*(_xlpm.f>0), _xlpm.f, ISNUMBER(_xlpm.g)*(_xlpm.g>0), _xlpm.g, ISNUMBER(_xlpm.c)*(_xlpm.c>0), _xlpm.c, TRUE, "" ) )} -> 46184 | I55: {=_xlfn.LET( _xlpm._加工金額合計列,_t月次実績表[--合計--], _xlpm._月次年月日列,_t月次実績表[年月], _xlpm._依頼NO列,_t月次実績表[依頼NO(-1除外)], IFERROR( SUM( _xlfn._xlws.FILTER(_xlpm._加工金額合計列, (A55=_xlpm._依頼NO列) * (YEAR(_xlpm._月次年月日列) = YEAR(H55)) ) ), 0) )} -> 0 | J55: =IFERROR( IF( _t受注ﾌｧｲﾙ_総合計[[#This Row],[受注金額(修正)]] > _t受注ﾌｧｲﾙ_総合計[[#This Row],[加工金額合計(月次実績)]], _t受注ﾌｧｲﾙ_総合計[[#This Row],[受注金額(修正)]], _t受注ﾌｧｲﾙ_総合計[[#This Row],[加工金額合計(月次実績)]] ), 0 ) -> 12400 | K55: =IF(ISERROR(F55),0,E55) -> 12400 | L55: =_xlfn.LET( _xlpm._依頼NO, A55, _xlpm._集計年, YEAR(H55), _xlpm._依頼列, _t受注ﾌｧｲﾙ_TPI[依頼Ｎｏ], _xlpm._集計日列, _t受注ﾌｧｲﾙ_TPI[集計日], COUNTIFS( _xlpm._依頼列, _xlpm._依頼NO, _xlpm._集計日列, ">=" & DATE(_xlpm._集計年,1,1), _xlpm._集計日列, "<" & DATE(_xlpm._集計年+1,1,1) ) ) -> 0 | M55: =_xlfn.LET( _xlpm._依頼NO, A55, _xlpm._集計年, YEAR(H55), _xlpm._依頼列,_t受注ﾌｧｲﾙ_東レ[依頼Ｎｏ], _xlpm._集計日列, _t受注ﾌｧｲﾙ_東レ[集計日], COUNTIFS( _xlpm._依頼列, _xlpm._依頼NO, _xlpm._集計日列, ">=" & DATE(_xlpm._集計年,1,1), _xlpm._集計日列, "<" & DATE(_xlpm._集計年+1,1,1) ) ) -> 1 | N55: =IFERROR( INDEX( _xlfn.TEXTSPLIT( SUBSTITUTE(SUBSTITUTE(B55, "，", ","), "、", ","), ",", ), 1, 1 ), "" ) -> EC | O55: =IFERROR( INDEX( _xlfn.TEXTSPLIT( SUBSTITUTE(SUBSTITUTE(B55, "，", ","), "、", ","), ",", ), 1, 2 ), "" ) -> 欠点表示 | P55: =IFERROR( INDEX( _xlfn.TEXTSPLIT( SUBSTITUTE(SUBSTITUTE(B55, "，", ","), "、", ","), ",", ), 1, 3 ), "" ) | Q55: =IFERROR( INDEX( _xlfn.TEXTSPLIT( SUBSTITUTE(SUBSTITUTE(B55, "，", ","), "、", ","), ",", ), 1, 4 ), "" ) | R55: =IFERROR( INDEX( _xlfn.TEXTSPLIT( SUBSTITUTE(SUBSTITUTE(B55, "，", ","), "、", ","), ",", ), 1, 5 ), "" ) | T55: =IF(_t受注ﾌｧｲﾙ_総合計[[#This Row],[加工金額]]=_t受注ﾌｧｲﾙ_総合計[[#This Row],[受注金額(修正)]],TRUE) -> TRUE
A56: W6-12 | B56: EC,ｽﾘｯﾄ | C56: 46189 | D56: 500 | E56: 17500 | F56: {=_xlfn.LET( _xlpm._完了日,_加工実績DATA[加工完了日], _xlpm._調整納期列,_t受注ﾌｧｲﾙ_総合計[調整納期], _xlpm._加工完了日,_xlfn.TAKE( _xlfn._xlws.FILTER(_xlpm._完了日, (A56=_加工実績DATA[依頼NO])* (YEAR(C56) = YEAR(_xlpm._完了日)) ),1), IF(_xlpm._加工完了日 = 0,NA(),_xlpm._加工完了日) )} -> 46184 | G56: {=_xlfn.LET( _xlpm._完了日列,#REF!, _xlpm._完了日, _xlfn.TAKE( _xlfn._xlws.FILTER(_xlpm._完了日列, (A56=#REF!)* (DATEVALUE("2025/1/1") < C56) ),1 ), IFERROR(_xlpm._完了日,"") )} | H56: {=_xlfn.LET( _xlpm.f, IFERROR(F56, 0), _xlpm.g, IFERROR(G56, 0), _xlpm.c, IFERROR(C56, 0), _xlfn.IFS( ISNUMBER(_xlpm.f)*(_xlpm.f>0), _xlpm.f, ISNUMBER(_xlpm.g)*(_xlpm.g>0), _xlpm.g, ISNUMBER(_xlpm.c)*(_xlpm.c>0), _xlpm.c, TRUE, "" ) )} -> 46184 | I56: {=_xlfn.LET( _xlpm._加工金額合計列,_t月次実績表[--合計--], _xlpm._月次年月日列,_t月次実績表[年月], _xlpm._依頼NO列,_t月次実績表[依頼NO(-1除外)], IFERROR( SUM( _xlfn._xlws.FILTER(_xlpm._加工金額合計列, (A56=_xlpm._依頼NO列) * (YEAR(_xlpm._月次年月日列) = YEAR(H56)) ) ), 0) )} -> 0 | J56: =IFERROR( IF( _t受注ﾌｧｲﾙ_総合計[[#This Row],[受注金額(修正)]] > _t受注ﾌｧｲﾙ_総合計[[#This Row],[加工金額合計(月次実績)]], _t受注ﾌｧｲﾙ_総合計[[#This Row],[受注金額(修正)]], _t受注ﾌｧｲﾙ_総合計[[#This Row],[加工金額合計(月次実績)]] ), 0 ) -> 17500 | K56: =IF(ISERROR(F56),0,E56) -> 17500 | L56: =_xlfn.LET( _xlpm._依頼NO, A56, _xlpm._集計年, YEAR(H56), _xlpm._依頼列, _t受注ﾌｧｲﾙ_TPI[依頼Ｎｏ], _xlpm._集計日列, _t受注ﾌｧｲﾙ_TPI[集計日], COUNTIFS( _xlpm._依頼列, _xlpm._依頼NO, _xlpm._集計日列, ">=" & DATE(_xlpm._集計年,1,1), _xlpm._集計日列, "<" & DATE(_xlpm._集計年+1,1,1) ) ) -> 0 | M56: =_xlfn.LET( _xlpm._依頼NO, A56, _xlpm._集計年, YEAR(H56), _xlpm._依頼列,_t受注ﾌｧｲﾙ_東レ[依頼Ｎｏ], _xlpm._集計日列, _t受注ﾌｧｲﾙ_東レ[集計日], COUNTIFS( _xlpm._依頼列, _xlpm._依頼NO, _xlpm._集計日列, ">=" & DATE(_xlpm._集計年,1,1), _xlpm._集計日列, "<" & DATE(_xlpm._集計年+1,1,1) ) ) -> 1 | N56: =IFERROR( INDEX( _xlfn.TEXTSPLIT( SUBSTITUTE(SUBSTITUTE(B56, "，", ","), "、", ","), ",", ), 1, 1 ), "" ) -> EC | O56: =IFERROR( INDEX( _xlfn.TEXTSPLIT( SUBSTITUTE(SUBSTITUTE(B56, "，", ","), "、", ","), ",", ), 1, 2 ), "" ) -> ｽﾘｯﾄ | P56: =IFERROR( INDEX( _xlfn.TEXTSPLIT( SUBSTITUTE(SUBSTITUTE(B56, "，", ","), "、", ","), ",", ), 1, 3 ), "" ) | Q56: =IFERROR( INDEX( _xlfn.TEXTSPLIT( SUBSTITUTE(SUBSTITUTE(B56, "，", ","), "、", ","), ",", ), 1, 4 ), "" ) | R56: =IFERROR( INDEX( _xlfn.TEXTSPLIT( SUBSTITUTE(SUBSTITUTE(B56, "，", ","), "、", ","), ",", ), 1, 5 ), "" ) | T56: =IF(_t受注ﾌｧｲﾙ_総合計[[#This Row],[加工金額]]=_t受注ﾌｧｲﾙ_総合計[[#This Row],[受注金額(修正)]],TRUE) -> TRUE
A57: W6-13 | B57: EC,ｽﾘｯﾄ | C57: 46189 | D57: 0 | E57: 0 | F57: {=_xlfn.LET( _xlpm._完了日,_加工実績DATA[加工完了日], _xlpm._調整納期列,_t受注ﾌｧｲﾙ_総合計[調整納期], _xlpm._加工完了日,_xlfn.TAKE( _xlfn._xlws.FILTER(_xlpm._完了日, (A57=_加工実績DATA[依頼NO])* (YEAR(C57) = YEAR(_xlpm._完了日)) ),1), IF(_xlpm._加工完了日 = 0,NA(),_xlpm._加工完了日) )} -> #VALUE! | G57: {=_xlfn.LET( _xlpm._完了日列,#REF!, _xlpm._完了日, _xlfn.TAKE( _xlfn._xlws.FILTER(_xlpm._完了日列, (A57=#REF!)* (DATEVALUE("2025/1/1") < C57) ),1 ), IFERROR(_xlpm._完了日,"") )} | H57: {=_xlfn.LET( _xlpm.f, IFERROR(F57, 0), _xlpm.g, IFERROR(G57, 0), _xlpm.c, IFERROR(C57, 0), _xlfn.IFS( ISNUMBER(_xlpm.f)*(_xlpm.f>0), _xlpm.f, ISNUMBER(_xlpm.g)*(_xlpm.g>0), _xlpm.g, ISNUMBER(_xlpm.c)*(_xlpm.c>0), _xlpm.c, TRUE, "" ) )} -> 46189 | I57: {=_xlfn.LET( _xlpm._加工金額合計列,_t月次実績表[--合計--], _xlpm._月次年月日列,_t月次実績表[年月], _xlpm._依頼NO列,_t月次実績表[依頼NO(-1除外)], IFERROR( SUM( _xlfn._xlws.FILTER(_xlpm._加工金額合計列, (A57=_xlpm._依頼NO列) * (YEAR(_xlpm._月次年月日列) = YEAR(H57)) ) ), 0) )} -> 0 | J57: =IFERROR( IF( _t受注ﾌｧｲﾙ_総合計[[#This Row],[受注金額(修正)]] > _t受注ﾌｧｲﾙ_総合計[[#This Row],[加工金額合計(月次実績)]], _t受注ﾌｧｲﾙ_総合計[[#This Row],[受注金額(修正)]], _t受注ﾌｧｲﾙ_総合計[[#This Row],[加工金額合計(月次実績)]] ), 0 ) -> 0 | K57: =IF(ISERROR(F57),0,E57) -> 0 | L57: =_xlfn.LET( _xlpm._依頼NO, A57, _xlpm._集計年, YEAR(H57), _xlpm._依頼列, _t受注ﾌｧｲﾙ_TPI[依頼Ｎｏ], _xlpm._集計日列, _t受注ﾌｧｲﾙ_TPI[集計日], COUNTIFS( _xlpm._依頼列, _xlpm._依頼NO, _xlpm._集計日列, ">=" & DATE(_xlpm._集計年,1,1), _xlpm._集計日列, "<" & DATE(_xlpm._集計年+1,1,1) ) ) -> 0 | M57: =_xlfn.LET( _xlpm._依頼NO, A57, _xlpm._集計年, YEAR(H57), _xlpm._依頼列,_t受注ﾌｧｲﾙ_東レ[依頼Ｎｏ], _xlpm._集計日列, _t受注ﾌｧｲﾙ_東レ[集計日], COUNTIFS( _xlpm._依頼列, _xlpm._依頼NO, _xlpm._集計日列, ">=" & DATE(_xlpm._集計年,1,1), _xlpm._集計日列, "<" & DATE(_xlpm._集計年+1,1,1) ) ) -> 1 | N57: =IFERROR( INDEX( _xlfn.TEXTSPLIT( SUBSTITUTE(SUBSTITUTE(B57, "，", ","), "、", ","), ",", ), 1, 1 ), "" ) -> EC | O57: =IFERROR( INDEX( _xlfn.TEXTSPLIT( SUBSTITUTE(SUBSTITUTE(B57, "，", ","), "、", ","), ",", ), 1, 2 ), "" ) -> ｽﾘｯﾄ | P57: =IFERROR( INDEX( _xlfn.TEXTSPLIT( SUBSTITUTE(SUBSTITUTE(B57, "，", ","), "、", ","), ",", ), 1, 3 ), "" ) | Q57: =IFERROR( INDEX( _xlfn.TEXTSPLIT( SUBSTITUTE(SUBSTITUTE(B57, "，", ","), "、", ","), ",", ), 1, 4 ), "" ) | R57: =IFERROR( INDEX( _xlfn.TEXTSPLIT( SUBSTITUTE(SUBSTITUTE(B57, "，", ","), "、", ","), ",", ), 1, 5 ), "" ) | T57: =IF(_t受注ﾌｧｲﾙ_総合計[[#This Row],[加工金額]]=_t受注ﾌｧｲﾙ_総合計[[#This Row],[受注金額(修正)]],TRUE) -> TRUE
A58: W6-14 | B58: EC | C58: 46189 | D58: 1000 | E58: 18000 | F58: {=_xlfn.LET( _xlpm._完了日,_加工実績DATA[加工完了日], _xlpm._調整納期列,_t受注ﾌｧｲﾙ_総合計[調整納期], _xlpm._加工完了日,_xlfn.TAKE( _xlfn._xlws.FILTER(_xlpm._完了日, (A58=_加工実績DATA[依頼NO])* (YEAR(C58) = YEAR(_xlpm._完了日)) ),1), IF(_xlpm._加工完了日 = 0,NA(),_xlpm._加工完了日) )} -> 46188 | G58: {=_xlfn.LET( _xlpm._完了日列,#REF!, _xlpm._完了日, _xlfn.TAKE( _xlfn._xlws.FILTER(_xlpm._完了日列, (A58=#REF!)* (DATEVALUE("2025/1/1") < C58) ),1 ), IFERROR(_xlpm._完了日,"") )} | H58: {=_xlfn.LET( _xlpm.f, IFERROR(F58, 0), _xlpm.g, IFERROR(G58, 0), _xlpm.c, IFERROR(C58, 0), _xlfn.IFS( ISNUMBER(_xlpm.f)*(_xlpm.f>0), _xlpm.f, ISNUMBER(_xlpm.g)*(_xlpm.g>0), _xlpm.g, ISNUMBER(_xlpm.c)*(_xlpm.c>0), _xlpm.c, TRUE, "" ) )} -> 46188 | I58: {=_xlfn.LET( _xlpm._加工金額合計列,_t月次実績表[--合計--], _xlpm._月次年月日列,_t月次実績表[年月], _xlpm._依頼NO列,_t月次実績表[依頼NO(-1除外)], IFERROR( SUM( _xlfn._xlws.FILTER(_xlpm._加工金額合計列, (A58=_xlpm._依頼NO列) * (YEAR(_xlpm._月次年月日列) = YEAR(H58)) ) ), 0) )} -> 0 | J58: =IFERROR( IF( _t受注ﾌｧｲﾙ_総合計[[#This Row],[受注金額(修正)]] > _t受注ﾌｧｲﾙ_総合計[[#This Row],[加工金額合計(月次実績)]], _t受注ﾌｧｲﾙ_総合計[[#This Row],[受注金額(修正)]], _t受注ﾌｧｲﾙ_総合計[[#This Row],[加工金額合計(月次実績)]] ), 0 ) -> 18000 | K58: =IF(ISERROR(F58),0,E58) -> 18000 | L58: =_xlfn.LET( _xlpm._依頼NO, A58, _xlpm._集計年, YEAR(H58), _xlpm._依頼列, _t受注ﾌｧｲﾙ_TPI[依頼Ｎｏ], _xlpm._集計日列, _t受注ﾌｧｲﾙ_TPI[集計日], COUNTIFS( _xlpm._依頼列, _xlpm._依頼NO, _xlpm._集計日列, ">=" & DATE(_xlpm._集計年,1,1), _xlpm._集計日列, "<" & DATE(_xlpm._集計年+1,1,1) ) ) -> 0 | M58: =_xlfn.LET( _xlpm._依頼NO, A58, _xlpm._集計年, YEAR(H58), _xlpm._依頼列,_t受注ﾌｧｲﾙ_東レ[依頼Ｎｏ], _xlpm._集計日列, _t受注ﾌｧｲﾙ_東レ[集計日], COUNTIFS( _xlpm._依頼列, _xlpm._依頼NO, _xlpm._集計日列, ">=" & DATE(_xlpm._集計年,1,1), _xlpm._集計日列, "<" & DATE(_xlpm._集計年+1,1,1) ) ) -> 1 | N58: =IFERROR( INDEX( _xlfn.TEXTSPLIT( SUBSTITUTE(SUBSTITUTE(B58, "，", ","), "、", ","), ",", ), 1, 1 ), "" ) -> EC | O58: =IFERROR( INDEX( _xlfn.TEXTSPLIT( SUBSTITUTE(SUBSTITUTE(B58, "，", ","), "、", ","), ",", ), 1, 2 ), "" ) | P58: =IFERROR( INDEX( _xlfn.TEXTSPLIT( SUBSTITUTE(SUBSTITUTE(B58, "，", ","), "、", ","), ",", ), 1, 3 ), "" ) | Q58: =IFERROR( INDEX( _xlfn.TEXTSPLIT( SUBSTITUTE(SUBSTITUTE(B58, "，", ","), "、", ","), ",", ), 1, 4 ), "" ) | R58: =IFERROR( INDEX( _xlfn.TEXTSPLIT( SUBSTITUTE(SUBSTITUTE(B58, "，", ","), "、", ","), ",", ), 1, 5 ), "" ) | T58: =IF(_t受注ﾌｧｲﾙ_総合計[[#This Row],[加工金額]]=_t受注ﾌｧｲﾙ_総合計[[#This Row],[受注金額(修正)]],TRUE) -> TRUE
